Workbook

Sheet FINAL MAP
A1: URL | B1: Title | C1: Key | H1: Definition of Sycophancy (what exactly do they mean by sycophancy) | M1: Outcomes (Are they measuring the impact of sycophancy on something else?)
E2: Human - Specialist | F2: Human - Authors | G2: AI - prompted | H2: Hallucination Agreement | I2: Bias Agreement | J2: Obsequiousness | K2: Stance Change | L2: Failure to challenge/trying to get along | M2: None | N2: User opinion | O2: User action | P2: System performance | Q2: User performance
E3: Having someone with expertise (psychologist, conversation expert, etc) judge | F3: Authors judging | G3: Some sort of prompted AI doing the judging | H3: Saying something objectively wrong/harmful becuase the user wants it to be so | I3: The LLM choosing something that isn't objectively wrong, but siding towards the version that it believes user would want | J3: Fawning or overly positive language | K3: Getting the LLM to change opinions/stance/viewpoint to please/mirror user | L3: LLM failing to push back or challenge user or just going along with user's suggestion despite potential problems | M3: Just measuing sycophancy directly with no impact | N3: Measuring how users feel/react in some way | O3: Measuring something about how users behave while/after interacting with sycophantic LLMS | P3: Some measure of how sycophantic LLMs perform on some task | Q3: Some measure of how well the user is able to accomplish a task with sycophantic/non-sycophantic agents
A4: https://ieeexplore.ieee.org/stamp/stamp.jsp?arnumber=11449950 | B4: Too Positive to Be True? Sentiment Analysis of AI-Guided vs. Human-Led Debriefings in Virtual Reality Counseling Training | C4: 10.1109/AIxVR67263.2026.00026 | G4: X | J4: X | L4: X | O4: X
A5: https://ieeexplore.ieee.org/stamp/stamp.jsp?arnumber=10825538 | B5: Mitigating Sycophancy in Large Language Models via Direct Preference Optimization | C5: 10.1109/BigData62323.2024.10825538 | G5: X | K5: X | L5: X | P5: X
A6: https://ieeexplore.ieee.org/stamp/stamp.jsp?arnumber=11460702 | B6: Towards Self-Evaluation of Sycophantic Hallucinations in Mathematical Reasoning | C6: 10.1109/ICASSP55912.2026.11460702 | G6: X | H6: X | K6: X | L6: X | P6: X
A7: https://ieeexplore.ieee.org/stamp/stamp.jsp?arnumber=10820709 | B7: SciTrust: Evaluating the Trustworthiness of Large Language Models for Science | C7: 10.1109/SCW63240.2024.00017 | F7: X | G7: X | H7: X | P7: X
A8: https://doi.org/10.1145/1518701.1519021 | B8: I'm sorry | C8: 10.1145/1518701.1519021 | L8: X | N8: X | O8: X
A9: https://doi.org/10.1145/3660650.3660656 | B9: Faceless Adversary | C9: 10.1145/3660650.3660656 | E9: X | J9: X | L9: X | M9: X
A10: https://doi.org/10.1145/3663547.3746319 | B10: Probing the Gaps in ChatGPT's Live Video Chat for Real-World Assistance for People who are Blind or Visually Impaired | C10: 10.1145/3663547.3746319 | F10: X | L10: X | N10: X | O10: X
A11: https://doi.org/10.1145/3703155 | B11: A Survey on Hallucination in Large Language Models: Principles | C11: 10.1145/3703155 | E11: X | H11: X | L11: X | P11: X
A12: https://doi.org/10.1145/3706599.3719976 | B12: Exploring Older Adults Personality Preferences for LLM-powered Conversational Companions | C12: 10.1145/3706599.3719976 | I12: X | L12: X | N12: X
A13: https://doi.org/10.1145/3715275.3732039 | B13: Expressing stigma and inappropriate responses prevents LLMs from safely replacing mental health providers. | C13: 10.1145/3715275.3732039 | E13: X | G13: X | L13: X | P13: X
A14: https://doi.org/10.1145/3717511.3747073 | B14: Interactive Social Agent Behaviors of Politeness and Compromise in Collaborative Decision-making | C14: 10.1145/3717511.3747073 | I14: X | L14: X | Q14: X
A15: https://doi.org/10.1145/3719160.3736618 | B15: Navigating the Fog: How University Students Recalibrate Sensemaking Practices to Address Plausible Falsehoods in LLM Outputs | C15: 10.1145/3719160.3736618 | K15: X | N15: X | O15: X
A16: https://doi.org/10.1145/3742413.3789120 | B16: Neural Transparency: Mechanistic Interpretability Interfaces for Anticipating Model Behaviors for Personalized AI | C16: 10.1145/3742413.3789120 | G16: X | L16: X | O16: X | Q16: X
A17: https://doi.org/10.1145/3744169.3744194 | B17: Reading the Praise/Prompt Machine: An Interface Criticism Approach to ChatGPT | C17: 10.1145/3744169.3744194 | F17: X | J17: X | L17: X | M17: X
A18: https://doi.org/10.1145/3746027.3755778 | B18: Evaluating and Mitigating Sycophancy in Large Vision-Language Models | C18: 10.1145/3746027.3755778 | F18: X | H18: X | K18: X | P18: X
A19: https://doi.org/10.1145/3772318.3790385 | B19: Understanding Compliance and Conversion Dynamics in Multi-Agent Collectives | C19: 10.1145/3772318.3790385 | K19: X | L19: X | N19: X | O19: X
A20: https://doi.org/10.1145/3772318.3790934 | B20: Does Sycophancy Change Decisions? Effect of LLM Sycophancy on AI-Assisted Decision-Making | C20: 10.1145/3772318.3790934 | I20: X | J20: X | N20: X | O20: X | Q20: X
A21: https://doi.org/10.1145/3772318.3791079 | B21: Be Friendly | C21: 10.1145/3772318.3791079 | J21: X | K21: X | N21: X
A22: https://doi.org/10.1145/3772318.3791149 | B22: The Siren Song of LLMs: How Users Perceive and Respond to Dark Patterns in Large Language Models | C22: 10.1145/3772318.3791149 | I22: X | J22: X | N22: X | O22: X
A23: https://doi.org/10.1145/3772318.3791233 | B23: When AI Gives Advice: Evaluating AI and Human Responses to Online Advice-Seeking for Well-Being | C23: 10.1145/3772318.3791233 | E23: X | I23: X | N23: X | P23: X
A24: https://doi.org/10.1145/3772318.3791300 | B24: All Accept | C24: 10.1145/3772318.3791300 | E24: X | I24: X | P24: X
A25: https://doi.org/10.1145/3772318.3791365 | B25: Invisible Saboteurs: Sycophantic LLMs Mislead Novices in Problem-Solving Tasks | C25: 10.1145/3772318.3791365 | L25: X | Q25: X
A26: https://doi.org/10.1145/3772318.3791851 | B26: Personal Validation Effect in LLMs: Positive AI Responses Bias Perceptions of Validity | C26: 10.1145/3772318.3791851 | I26: X | N26: X
A27: https://doi.org/10.1145/3772318.3791915 | B27: Interaction Context Often Increases Sycophancy in LLMs | C27: 10.1145/3772318.3791915 | I27: X | M27: X
A28: https://doi.org/10.1145/3772363.3798705 | B28: When AI Agrees | C28: 10.1145/3772363.3798705 | I28: X | N28: X
A29: https://doi.org/10.1145/3772363.3799334 | B29: Maintaining Stable Personas? Examining Temporal Stability in LLM-Based Human Simulation | C29: 10.1145/3772363.3799334 | F29: X | L29: X | P29: X
A30: https://doi.org/10.1145/3774904.3792506 | B30: Acting Flatterers via LLMs Sycophancy: Combating Clickbait with LLMs Opposing-Stance Reasoning | C30: 10.1145/3774904.3792506 | G30: X | I30: X | K30: X | P30: X
A31: https://doi.org/10.1145/3776734.3794532 | B31: Robotic Sycophancy: A Scoping Review | C31: 10.1145/3776734.3794532 | F31: X | I31: X | J31: X | L31: X | M31: X
A32: https://doi.org/10.1145/3786304.3787879 | B32: Confirmation | C32: 10.1145/3786304.3787879 | F32: X | I32: X | M32: X
A33: https://doi.org/10.1145/3786335.3813137 | B33: The Cost of Consensus: Isolated Self-Correction Prevails Over Unguided Homogeneous Multi-Agent Debate | C33: 10.1145/3786335.3813137 | F33: X | K33: X | P33: X
A34: https://doi.org/10.1145/3788646.3789536 | B34: AI-Assisted Moot Courts: Simulating Justice-Specific Questioning in Oral Arguments | C34: 10.1145/3788646.3789536 | G34: X | I34: X | L34: X | P34: X

Sheet All Papers
A1: URL | B1: DOI | C1: Title
A2: https://ieeexplore.ieee.org/stamp/stamp.jsp?arnumber=11460702 | B2: 10.1109/ICASSP55912.2026.11460702 | C2: Towards Self-Evaluation of Sycophantic Hallucinations in Mathematical Reasoning
A3: https://ieeexplore.ieee.org/stamp/stamp.jsp?arnumber=10825538 | B3: 10.1109/BigData62323.2024.10825538 | C3: Mitigating Sycophancy in Large Language Models via Direct Preference Optimization
A4: https://ieeexplore.ieee.org/stamp/stamp.jsp?arnumber=11424465 | B4: 10.1109/RAMS50514.2026.11424465 | C4: Autonomous AI-Driven FMEA Optimization For Safety And Reliability In Healthcare
A5: https://ieeexplore.ieee.org/stamp/stamp.jsp?arnumber=1431446 | B5: 10.1109/IRI.2004.1431446 | C5: Context learning can improve user interaction
A6: https://ieeexplore.ieee.org/stamp/stamp.jsp?arnumber=4299963 | B6: 10.1109/ICSEA.2007.67 | C6: Sycophant: An API for Research in Context-Aware User Interfaces
A7: https://ieeexplore.ieee.org/stamp/stamp.jsp?arnumber=735370 | B7: 10.1109/47.735370 | C7: The letter of submission: avoiding the promotional genre
A8: https://ieeexplore.ieee.org/stamp/stamp.jsp?arnumber=10771051 | B8: 10.1109/AIxSET62544.2024.00047 | C8: Towards Transparent Artificial Intelligence: Exploring Modern Approaches and Future Directions
A9: https://ieeexplore.ieee.org/stamp/stamp.jsp?arnumber=10590666 | B9: 10.1109/HPSC62738.2024.00012 | C9: Studying the Knowledge and Behavior of ChatGPT via Journey to the West
A10: https://ieeexplore.ieee.org/stamp/stamp.jsp?arnumber=11508939 | B10: 10.1109/ICAACE69793.2026.11508939 | C10: Tiny-Critic RAG: Empowering Agentic Fallback with Parameter-Efficient Small Language Models
A11: https://ieeexplore.ieee.org/stamp/stamp.jsp?arnumber=11345775 | B11: 10.1109/NKCon66957.2025.11345775 | C11: Improving Argumentative Reasoning in LLMs Using Online Debates and Agent-Based Interaction
A12: https://ieeexplore.ieee.org/stamp/stamp.jsp?arnumber=11462217 | B12: 10.1109/ICASSP55912.2026.11462217 | C12: FinLumen: A Game-Theoretic Multi-Agent Framework for Rational Portfolio Management
... A40: https://doi.org/10.1145/3746027.3755778 | B40: 10.1145/3746027.3755778 | C40: Evaluating and Mitigating Sycophancy in Large Vision-Language Models
A41: https://doi.org/10.1145/3772318.3791079 | B41: 10.1145/3772318.3791079 | C41: Be Friendly | D41: Not Friends: How LLM Sycophancy Shapes User Trust
A42: https://doi.org/10.1145/3772363.3798611 | B42: 10.1145/3772363.3798611 | C42: Verbalizing LLMs' Assumptions About the User to Calibrate Expectations and Reduce Sycophancy
A43: https://doi.org/10.1145/3772363.3798575 | B43: 10.1145/3772363.3798575 | C43: When Flattery Backfires: How Sycophancy and Interaction Context Shape Perceived Authenticity and Trust in Large Language AI Models
A44: https://doi.org/10.1145/3774904.3792506 | B44: 10.1145/3774904.3792506 | C44: Acting Flatterers via LLMs Sycophancy: Combating Clickbait with LLMs Opposing-Stance Reasoning
A45: https://doi.org/10.1145/3786335.3813137 | B45: 10.1145/3786335.3813137 | C45: The Cost of Consensus: Isolated Self-Correction Prevails Over Unguided Homogeneous Multi-Agent Debate
A46: https://doi.org/10.1145/3772363.3798923 | B46: 10.1145/3772363.3798923 | C46: ChatGPT Is a People Pleaser | D46: Especially When Taking Human vs. AI Advice
A47: https://doi.org/10.1145/3772363.3799156 | B47: 10.1145/3772363.3799156 | C47: Demoing Stochastic Parrot: A Candid AI Cohabitant
A48: https://doi.org/10.1145/3742413.3789120 | B48: 10.1145/3742413.3789120 | C48: Neural Transparency: Mechanistic Interpretability Interfaces for Anticipating Model Behaviors for Personalized AI
A49: https://doi.org/10.1145/3772318.3791233 | B49: 10.1145/3772318.3791233 | C49: When AI Gives Advice: Evaluating AI and Human Responses to Online Advice-Seeking for Well-Being
A50: https://doi.org/10.1145/3788646.3789536 | B50: 10.1145/3788646.3789536 | C50: AI-Assisted Moot Courts: Simulating Justice-Specific Questioning in Oral Arguments
A51: https://doi.org/10.1145/3719160.3736618 | B51: 10.1145/3719160.3736618 | C51: Navigating the Fog: How University Students Recalibrate Sensemaking Practices to Address Plausible Falsehoods in LLM Outputs
A52: https://doi.org/10.1145/3772318.3790739 | B52: 10.1145/3772318.3790739 | C52: Chat Should I Leave Him? Risks | D52: Rewards | E52: and Roles for AI in Relationship Advice
A53: https://doi.org/10.1109/SCW63240.2024.00017 | B53: 10.1109/SCW63240.2024.00017 | C53: SciTrust: Evaluating the Trustworthiness of Large Language Models for Science
A54: https://doi.org/10.1145/3715275.3732039 | B54: 10.1145/3715275.3732039 | C54: Expressing stigma and inappropriate responses prevents LLMs from safely replacing mental health providers.
A55: https://doi.org/10.1145/3663547.3746319 | B55: 10.1145/3663547.3746319 | C55: Probing the Gaps in ChatGPT's Live Video Chat for Real-World Assistance for People who are Blind or Visually Impaired
A56: https://doi.org/10.1145/3715070.3749272 | B56: 10.1145/3715070.3749272 | C56: Was there Bias in your Response?: LLM Anthropomorphic Traits in Context of Ability Bias Questioning
A57: https://doi.org/10.1145/3772318.3790279 | B57: 10.1145/3772318.3790279 | C57: Futuring Social Assemblages: How Enmeshing AIs into Social Life Challenges the Individual and the Interpersonal
A58: https://doi.org/10.1145/3772363.3798453 | B58: 10.1145/3772363.3798453 | C58: AI-Induced Delusional Spirals: Understanding Lived Experiences During Maladaptive Human-Chatbot Interactions
A59: https://doi.org/10.1145/3772318.3791149 | B59: 10.1145/3772318.3791149 | C59: The Siren Song of LLMs: How Users Perceive and Respond to Dark Patterns in Large Language Models
A60: https://doi.org/10.1145/3772318.3791851 | B60: 10.1145/3772318.3791851 | C60: Personal Validation Effect in LLMs: Positive AI Responses Bias Perceptions of Validity | D60: Reliability | E60: Personalization | F60: and Usefulness of Fictitious Predictions
A61: https://doi.org/10.1145/3772318.3791300 | B61: 10.1145/3772318.3791300 | C61: All Accept | D61: No Reject: Evaluating LLMs as “Peer” Reviewers
A62: https://doi.org/10.1145/3736731.3786118 | B62: 10.1145/3736731.3786118 | C62: Session Summary Podcast: Session 3: Posters
A63: https://doi.org/10.1145/3772318.3791775 | B63: 10.1145/3772318.3791775 | C63: From Symptoms to Systems: An Expert-Guided Approach to Understanding Risks of Generative AI for Eating Disorders
A64: https://doi.org/10.1145/3703155 | B64: 10.1145/3703155 | C64: A Survey on Hallucination in Large Language Models: Principles | D64: Taxonomy | E64: Challenges | F64: and Open Questions
A65: https://doi.org/10.1145/3765766.3765852 | B65: 10.1145/3765766.3765852 | C65: How Do People Evaluate Their Interactions with AI: A Qualitative Study of Emotionally Motivated AI Use and User Evaluation
A66: https://doi.org/10.1145/3746252.3761151 | B66: 10.1145/3746252.3761151 | C66: Where Does Legal AI Fail? Evaluating RAG Pipelines
A67: https://doi.org/10.1145/3706599.3719976 | B67: 10.1145/3706599.3719976 | C67: Exploring Older Adults Personality Preferences for LLM-powered Conversational Companions
A68: https://doi.org/10.1145/3772318.3808894 | B68: 10.1145/3772318.3808894 | C68: Session Summary Podcast: Session 14: AI for Youth Learning
A69: https://doi.org/10.1145/3774904.3792976 | B69: 10.1145/3774904.3792976 | C69: Belief-Driven Multi-Agent Collaboration via Approximate Perfect Bayesian Equilibrium for Social Simulation
A70: https://doi.org/10.1145/3772318.3791571 | B70: 10.1145/3772318.3791571 | C70: Interpretive Cultures: Resonance | D70: randomness | E70: and negotiated meaning for AI-assisted tarot divination
A71: https://doi.org/10.1145/3772363.3798705 | B71: 10.1145/3772363.3798705 | C71: When AI Agrees | D71: Polarization Sticks: Private AI Consulting May Increase Confidence and Reduces Depolarization
A72: https://doi.org/10.1145/3701188 | B72: 10.1145/3701188 | C72: Conversate: Supporting Reflective Learning in Interview Practice Through Interactive Simulation and Dialogic Feedback
A73: https://doi.org/10.1145/3708359.3712145 | B73: 10.1145/3708359.3712145 | C73: Enhancing Visitor Engagement in Interactive Art Exhibitions with Visual-Enhanced Conversational Agents
A74: https://doi.org/10.1145/3772318.3791556 | B74: 10.1145/3772318.3791556 | C74: Framing Responsible Design of AI for Mental Well-Being: AI as Primary Care | D74: Nutritional Supplement | E74: or Yoga Instructor?
A75: https://doi.org/10.1145/3772318.3809104 | B75: 10.1145/3772318.3809104 | C75: Session Summary Podcast: Session 216: The Dark Sides of AI
A76: https://doi.org/10.1145/3706468.3706564 | B76: 10.1145/3706468.3706564 | C76: When the Prompt becomes the Codebook: Grounded Prompt Engineering (GROPROE) and its application to Belonging Analytics
A77: https://doi.org/10.1145/3793679 | B77: 10.1145/3793679 | C77: Who’s Sorry Now: User Preferences Among Rote | D77: Empathic | E77: and Explanatory Apologies from LLM Chatbots
A78: https://doi.org/10.1145/3772318.3791363 | B78: 10.1145/3772318.3791363 | C78: How Generative AI Empowers Attackers and Defenders Across the Trust &amp; Safety Landscape
A79: https://doi.org/10.1145/3800687 | B79: 10.1145/3800687 | C79: Must Read: A Comprehensive Survey of Computational Persuasion
A80: https://doi.org/10.1145/3742413.3789218 | B80: 10.1145/3742413.3789218 | C80: Guiding | D80: Not Railroading: Design and Evaluation of a Multi-Agent System for Narrative Redirection in Role-playing Games
A81: https://doi.org/10.1145/3714394.3756275 | B81: 10.1145/3714394.3756275 | C81: Evaluating Large Language Models in Traditional Chinese Medicine with Enhanced Misinformation Detection
A82: https://doi.org/10.1145/3715073.3715075 | B82: 10.1145/3715073.3715075 | C82: Blockchain for Large Language Model Security and Safety: A Holistic Survey
A83: https://doi.org/10.1145/3716628 | B83: 10.1145/3716628 | C83: AI Agents Under Threat: A Survey of Key Security Challenges and Future Pathways
A84: https://doi.org/10.1145/3744169.3744194 | B84: 10.1145/3744169.3744194 | C84: Reading the Praise/Prompt Machine: An Interface Criticism Approach to ChatGPT
A85: https://doi.org/10.1145/3772318.3790340 | B85: 10.1145/3772318.3790340 | C85: Polite But Boring? Trade-offs Between Engagement and Psychological Reactance to Chatbot Feedback Styles
A86: https://doi.org/10.1145/3772363.3778745 | B86: 10.1145/3772363.3778745 | C86: From Generation to Simulation: Responsible Use of AI Personas in Human-Centered Design and Research
A87: https://doi.org/10.1145/3802598 | B87: 10.1145/3802598 | C87: Chatbots’ Downward Spiral
A88: https://doi.org/10.1145/3786167.3788413 | B88: 10.1145/3786167.3788413 | C88: Not All Problems Are Nails | D88: Not All Tools Should Be Hammers: A Position Paper on Agent Usage in Software Engineering Tasks
A89: https://doi.org/10.1145/3772363.3798812 | B89: 10.1145/3772363.3798812 | C89: I'm Thinking of Ending Things: Use of LLMs for Support During Break-ups
A90: https://doi.org/10.1145/3630106.3659037 | B90: 10.1145/3630106.3659037 | C90: Black-Box Access is Insufficient for Rigorous AI Audits
A91: https://doi.org/10.1145/3772363.3798995 | B91: 10.1145/3772363.3798995 | C91: Codex Relatio: A Descriptive Framework for Analyzing Relational Dynamics in Human–AI Interaction
A92: https://doi.org/10.1145/3769686 | B92: 10.1145/3769686 | C92: Rolling in the Deep of Cognitive and AI Biases
A93: https://doi.org/10.1145/3643834.3661525 | B93: 10.1145/3643834.3661525 | C93: Imagining a Future of Designing with AI: Dynamic Grounding | D93: Constructive Negotiation | E93: and Sustainable Motivation
A94: https://doi.org/10.1145/3772363.3798685 | B94: 10.1145/3772363.3798685 | C94: Who wants to be nagged by AI?: Investigating the Effects of Agreeableness on Older Adults' Perception of LLM-Based Voice Assistants' Explanations
A95: https://doi.org/10.1145/3772318.3790586 | B95: 10.1145/3772318.3790586 | C95: “Tinged with Heartbreak”: An Ethnographic Account of Navigating Autistic Loneliness and the Fragile Promise of AI Companionship: “Tinged with Heartbreak”: “Tinged with Heartbreak”
A96: https://doi.org/10.1145/3762989 | B96: 10.1145/3762989 | C96: Unsolved Problems in MLOps: Either find a better paradigm or fix the ones we're using now.
A97: https://doi.org/10.1145/3764687.3764716 | B97: 10.1145/3764687.3764716 | C97: Co-creating Vocal Imaginaries with Conversational AIs
A98: https://doi.org/10.1145/3772318.3791834 | B98: 10.1145/3772318.3791834 | C98: Say It My Way: Exploring Control in Conversational Visual Question Answering with Blind Users
A99: https://doi.org/10.1145/3720554.3735862 | B99: 10.1145/3720554.3735862 | C99: GenAI &amp; The Dual-Deception Process in Web Science
A100: https://doi.org/10.1145/3772318.3791068 | B100: 10.1145/3772318.3791068 | C100: LLM-based Embodied Conversational Agent for Reducing Foreign Language Speaking Anxiety in Social VR
A101: https://doi.org/10.1145/3742413.3789136 | B101: 10.1145/3742413.3789136 | C101: Adjust for Trust: Mitigating Trust-Induced Inappropriate Reliance on AI Assistance
A102: https://doi.org/10.1145/3772318.3790461 | B102: 10.1145/3772318.3790461 | C102: Rememo: A Research-through-Design Inquiry Towards an AI-in-the-loop Therapist’s Tool for Dementia Reminiscence
A103: https://doi.org/10.1145/3772318.3790812 | B103: 10.1145/3772318.3790812 | C103: Sometimes You Need Facts | D103: and Sometimes a Hug: Understanding Older Adults' Preferences for Explanations in LLM-Based Conversational AI Systems
A104: https://doi.org/10.1145/3786304.3787879 | B104: 10.1145/3786304.3787879 | C104: Confirmation | D104: Framing | E104: and Position Biases in LLM Responses
A105: https://doi.org/10.1145/3772318.3791484 | B105: 10.1145/3772318.3791484 | C105: Retelling the News: Exploring AI-Driven Conversational News Interactions
A106: https://doi.org/10.1145/3815195 | B106: 10.1145/3815195 | C106: Imperfect AI | D106: Imperfect Humans | E106: Effective Teams: Challenges and Opportunities of Human-AI Collaboration
A107: https://doi.org/10.1145/3772318.3790907 | B107: 10.1145/3772318.3790907 | C107: Generative AI in Children's Creative Collaboration: Impact | D107: Perception | E107: and Design Guidelines
A108: https://doi.org/10.1145/3742413.3789223 | B108: 10.1145/3742413.3789223 | C108: Mental Models in Human-AI Interaction: Systematic Review of Empirical Methodologies and Guidelines
A109: https://doi.org/10.1145/3799914.3799919 | B109: 10.1145/3799914.3799919 | C109: About Authenticity in Information Retrieval: A Keynote at ICTIR 2025
A110: https://doi.org/10.1145/3772318.3790697 | B110: 10.1145/3772318.3790697 | C110: Scaffolding Metacognition with GenAI: Exploring Design Opportunities to Support Task Management for University Students with ADHD
A111: https://doi.org/10.1145/3711896.3736563 | B111: 10.1145/3711896.3736563 | C111: A Survey on Small Language Models in the Era of Large Language Models: Architecture | D111: Capabilities | E111: and Trustworthiness
A112: https://doi.org/10.1145/3772318.3791760 | B112: 10.1145/3772318.3791760 | C112: OceanChat: The Effect of Virtual Conversational AI Agents on Sustainable Attitude and Behavior Change
A113: https://doi.org/10.1145/3717511.3747073 | B113: 10.1145/3717511.3747073 | C113: Interactive Social Agent Behaviors of Politeness and Compromise in Collaborative Decision-making
A114: https://doi.org/10.1145/3786304.3787865 | B114: 10.1145/3786304.3787865 | C114: Although Powerful it's not Infallible: Investigating Academic Researchers' Verification Challenges with LLMs
A115: https://doi.org/10.1145/3772318.3791319 | B115: 10.1145/3772318.3791319 | C115: Are we writing an advice column for Spock here? Understanding Stereotypes in AI Advice for Autistic Users
A116: https://doi.org/10.1145/3786304.3787891 | B116: 10.1145/3786304.3787891 | C116: Offscript: Agentic Auditing of Instruction Adherence in LLMs
A117: https://doi.org/10.1145/3772318.3809068 | B117: 10.1145/3772318.3809068 | C117: Session Summary Podcast: Session 180: Relationships with AI
A118: https://doi.org/10.1145/3772363.3778699 | B118: 10.1145/3772363.3778699 | C118: Social and Emotional Uses of AI
A119: https://doi.org/10.1145/3772363.3798919 | B119: 10.1145/3772363.3798919 | C119: When Objects Gossip: Exploring Object-to-Object Conversation with GAI
A120: https://doi.org/10.1145/3757619 | B120: 10.1145/3757619 | C120: Large Language Model Agents for Improving Engagement with Behavior Change Interventions: Application to Digital Mindfulness
A121: https://doi.org/10.1145/3772318.3790388 | B121: 10.1145/3772318.3790388 | C121: Vibe Check: Understanding the Effects of LLM-Based Conversational Agents' Personality and Alignment on User Perceptions in Goal-Oriented Tasks
A122: https://doi.org/10.1145/3706598.3713220 | B122: 10.1145/3706598.3713220 | C122: Simulacrum of Stories: Examining Large Language Models as Qualitative Research Participants
A123: https://doi.org/10.1145/3746059.3747680 | B123: 10.1145/3746059.3747680 | C123: Policy Maps: Tools for Guiding the Unbounded Space of LLM Behaviors
... A131: https://doi.org/10.1145/3757442 | B131: 10.1145/3757442 | C131: Mango Mango How to Let The Lettuce Dry Without A Spinner?: Exploring User Perceptions of Using An LLM-Based Conversational Assistant Toward Cooking Partner
A132: https://doi.org/10.1145/3746252.3761448 | B132: 10.1145/3746252.3761448 | C132: Socially Responsible and Trustworthy Generative Foundation Models: Principles | D132: Challenges | E132: and Practices
A133: https://doi.org/10.1145/3772363.3799334 | B133: 10.1145/3772363.3799334 | C133: Maintaining Stable Personas? Examining Temporal Stability in LLM-Based Human Simulation
A134: https://doi.org/10.1145/3772363.3798512 | B134: 10.1145/3772363.3798512 | C134: “Just Listening Was Enough—Until It Wasn't”: Relationship-Stage-Aware Cognitive Scaffolding in AI Companions
...

Sheet INCEXC A
B1: key | D1: Evaluator Name | E1: Included/Excluded | F1: Excluded Reason | G1: Other
A2: https://doi.org/10.1007/978-3-642-24322-6_15 | B2: 10.1007/978-3-642-24322-6_15 | C2: The search for energy-efficient building blocks for the data center | D2: Jonathan | E2: Exclude | F2: Not about either LLMs or Sycophancy
A3: https://doi.org/10.1007/978-3-642-24322-6_16 | B3: 10.1007/978-3-642-24322-6_16 | C3: KnightShift: shifting the I/O burden in datacenters to management processor for energy efficiency | D3: Marilyn | E3: Exclude | F3: Not about either LLMs or Sycophancy
A4: https://doi.org/10.1007/978-3-642-24322-6_19 | B4: 10.1007/978-3-642-24322-6_19 | C4: Achieving power-efficiency in clusters without distributed file system complexity | D4: Marilyn | E4: Exclude | F4: Not about either LLMs or Sycophancy
A5: https://ieeexplore.ieee.org/stamp/stamp.jsp?arnumber=8372225 | B5: 10.1049/cp.2016.1548 | C5: A SOFC based autonomous microgrid performance analysis using adaptive PI and PI controller | D5: Marilyn | E5: Exclude | F5: Not about either LLMs or Sycophancy
A6: https://ieeexplore.ieee.org/stamp/stamp.jsp?arnumber=735370 | B6: 10.1109/47.735370 | C6: The letter of submission: avoiding the promotional genre | D6: Jonathan | E6: Exclude | F6: Not about either LLMs or Sycophancy
A7: https://ieeexplore.ieee.org/stamp/stamp.jsp?arnumber=11467909 | B7: 10.1109/ACDSA67686.2026.11467909 | C7: Evaluating LLM-Induced Investment Biases via Persona Design and Prompt Analysis: A Quantitative Study of Post-Retirement Asset Depletion Risk Through Social Simulation | D7: Marilyn | E7: Include | G7: Syncopancy in context of reinforcing individual investment biases
A8: https://ieeexplore.ieee.org/stamp/stamp.jsp?arnumber=10771051 | B8: 10.1109/AIxSET62544.2024.00047 | C8: Towards Transparent Artificial Intelligence: Exploring Modern Approaches and Future Directions | D8: Kaiser | E8: Exclude | F8: Not about Sycophancy
A9: https://ieeexplore.ieee.org/stamp/stamp.jsp?arnumber=11449950 | B9: 10.1109/AIxVR67263.2026.00026 | C9: Too Positive to Be True? Sentiment Analysis of AI-Guided vs. Human-Led Debriefings in Virtual Reality Counseling Training | D9: Kaiser | E9: Include
A10: https://ieeexplore.ieee.org/stamp/stamp.jsp?arnumber=11334577 | B10: 10.1109/ASE63991.2025.00043 | C10: Why AI Agents Still Need You: Findings from Developer-Agent Collaborations in the Wild | D10: Kaiser | E10: Exclude | F10: Not about Sycophancy
A11: https://ieeexplore.ieee.org/stamp/stamp.jsp?arnumber=9381292 | B11: 10.1109/ASONAM49781.2020.9381292 | C11: Aspect Based Abusive Sentiment Detection in Nepali Social Media Texts | D11: Jonathan | E11: Exclude | F11: Not about either LLMs or Sycophancy
A12: https://doi.org/10.1109/ASONAM49781.2020.9381292 | B12: 10.1109/asonam49781.2020.9381292 | C12: Aspect based abusive sentiment detection in nepali social media texts | D12: Marilyn | E12: Exclude | F12: Not about Sycophancy
A13: https://ieeexplore.ieee.org/stamp/stamp.jsp?arnumber=10825538 | B13: 10.1109/BigData62323.2024.10825538 | C13: Mitigating Sycophancy in Large Language Models via Direct Preference Optimization | D13: Kaiser | E13: Include
A14: https://ieeexplore.ieee.org/stamp/stamp.jsp?arnumber=11400739 | B14: 10.1109/BigData66926.2025.11400739 | C14: Towards Uncertainty-Aware Low-Bit Quantized LLMs for On-Device Inference | D14: Kaiser | E14: Exclude | F14: Not about Sycophancy
A15: https://doi.org/10.1109/CCGrid.2012.84 | B15: 10.1109/ccgrid.2012.84 | C15: Energy- and Cost-Efficiency Analysis of ARM-Based Clusters | D15: Marilyn | E15: Exclude | F15: Not about either LLMs or Sycophancy
A16: https://doi.org/10.1109/CCGrid.2015.115 | B16: 10.1109/ccgrid.2015.115 | C16: Quantitative musings on the feasibility of smartphone clouds | D16: Jonathan | E16: Exclude | F16: Not about either LLMs or Sycophancy
A17: https://doi.org/10.1109/CCGrid.2015.150 | B17: 10.1109/ccgrid.2015.150 | C17: Deferred lightweight indexing for log-structured key-value stores | D17: Jonathan | E17: Exclude | F17: Not about either LLMs or Sycophancy
A18: https://doi.org/10.1109/CCGRID.2017.49 | B18: 10.1109/ccgrid.2017.49 | C18: High-Performance Key-Value Store On OpenSHMEM | D18: Kaiser | E18: Exclude | F18: Not about either LLMs or Sycophancy
A19: https://ieeexplore.ieee.org/stamp/stamp.jsp?arnumber=1554950 | B19: 10.1109/CEC.2005.1554950 | C19: Learning classifier systems for user context learning | D19: Jonathan | E19: Exclude | F19: Not about either LLMs or Sycophancy
A20: https://ieeexplore.ieee.org/stamp/stamp.jsp?arnumber=11519295 | B20: 10.1109/GAIIS69281.2026.11519295 | C20: PI-Embedding: Scientific Idea Representation Learning via Citation Intent and Paper Provenance | D20: Jonathan | E20: Exclude | F20: Not about Sycophancy
A21: https://ieeexplore.ieee.org/stamp/stamp.jsp?arnumber=10585495 | B21: 10.1109/GEM61861.2024.10585495 | C21: Leveraging Large Language Models for Enhanced VR Development: Insights and Challenges | D21: Marilyn | E21: Exclude | F21: Not about Sycophancy
A22: https://ieeexplore.ieee.org/stamp/stamp.jsp?arnumber=10590666 | B22: 10.1109/HPSC62738.2024.00012 | C22: Studying the Knowledge and Behavior of ChatGPT via Journey to the West | D22: Marilyn | E22: Exclude | F22: Not about Sycophancy
A23: https://ieeexplore.ieee.org/stamp/stamp.jsp?arnumber=11508939 | B23: 10.1109/ICAACE69793.2026.11508939 | C23: Tiny-Critic RAG: Empowering Agentic Fallback with Parameter-Efficient Small Language Models | D23: Jonathan | E23: Exclude | F23: Not about Sycophancy
A24: https://ieeexplore.ieee.org/stamp/stamp.jsp?arnumber=11460702 | B24: 10.1109/ICASSP55912.2026.11460702 | C24: Towards Self-Evaluation of Sycophantic Hallucinations in Mathematical Reasoning | D24: Jonathan | E24: Include
A25: https://ieeexplore.ieee.org/stamp/stamp.jsp?arnumber=11462217 | B25: 10.1109/ICASSP55912.2026.11462217 | C25: FinLumen: A Game-Theoretic Multi-Agent Framework for Rational Portfolio Management | D25: Kaiser | E25: Exclude | F25: Not about Sycophancy
A26: https://ieeexplore.ieee.org/stamp/stamp.jsp?arnumber=5409737 | B26: 10.1109/ICASTECH.2009.5409737 | C26: Tracking a Sycophant Wireless Sensor Network for its seamless integration to mobile Wireless Sensor Networks | D26: Kaiser | E26: Exclude | F26: Not about LLMs
A27: https://ieeexplore.ieee.org/stamp/stamp.jsp?arnumber=6056911 | B27: 10.1109/ICECENG.2011.6056911 | C27: Cohesive subgroups analysis of asynchronous cognitive interactive network in collaborative learning | D27: Jonathan | E27: Exclude | F27: Not about either LLMs or Sycophancy
A28: https://ieeexplore.ieee.org/stamp/stamp.jsp?arnumber=11521627 | B28: 10.1109/ICEIT68991.2026.11521627 | C28: The design of a GAI-supported research topic selection system for novice researchers: From the SECI perspective | D28: Marilyn | E28: Exclude | F28: Not about Sycophancy
A29: https://ieeexplore.ieee.org/stamp/stamp.jsp?arnumber=4299963 | B29: 10.1109/ICSEA.2007.67 | C29: Sycophant: An API for Research in Context-Aware User Interfaces | D29: Jonathan | E29: Exclude | F29: Not about either LLMs or Sycophancy
A30: https://ieeexplore.ieee.org/stamp/stamp.jsp?arnumber=1431446 | B30: 10.1109/IRI.2004.1431446 | C30: Context learning can improve user interaction | D30: Kaiser | E30: Exclude | F30: Not about Sycophancy
A31: https://doi.org/10.1109/ISCA.2016.15 | B31: 10.1109/isca.2016.15 | C31: Morpheus: creating application objects efficiently for heterogeneous computing | D31: Marilyn | E31: Exclude | F31: Not about either LLMs or Sycophancy
A32: https://ieeexplore.ieee.org/stamp/stamp.jsp?arnumber=11269633 | B32: 10.1109/ISTAS65609.2025.11269633 | C32: AI Detection and Risk Estimation in Family Violence: Challenges and Governance | D32: Marilyn | E32: Exclude | F32: Not about either LLMs or Sycophancy
A33: https://ieeexplore.ieee.org/stamp/stamp.jsp?arnumber=4580542 | B33: 10.1109/MIS.2008.55 | C33: A Computational Approach to Etiquette: Operationalizing Brown and Levinson's Politeness Model | D33: Kaiser | E33: Exclude | F33: Not about Sycophancy
A34: https://ieeexplore.ieee.org/stamp/stamp.jsp?arnumber=11345775 | B34: 10.1109/NKCon66957.2025.11345775 | C34: Improving Argumentative Reasoning in LLMs Using Online Debates and Agent-Based Interaction | D34: Jonathan | E34: Exclude | F34: Not about Sycophancy
A35: https://ieeexplore.ieee.org/stamp/stamp.jsp?arnumber=11037824 | B35: 10.1109/OJCS.2025.3580498 | C35: LLMs on a Budget: System-Level Approaches to Power-Efficient and Scalable Fine-Tuning | D35: Kaiser | E35: Exclude | F35: Not about Sycophancy
A36: https://ieeexplore.ieee.org/stamp/stamp.jsp?arnumber=11424465 | B36: 10.1109/RAMS50514.2026.11424465 | C36: Autonomous AI-Driven FMEA Optimization For Safety And Reliability In Healthcare | D36: Marilyn | E36: Exclude | F36: Not about LLMs
A37: https://doi.org/10.1109/SCW63240.2024.00017 | B37: 10.1109/SCW63240.2024.00017 | C37: SciTrust: Evaluating the Trustworthiness of Large Language Models for Science | D37: Jonathan | E37: Exclude | F37: Not about Sycophancy
A38: https://ieeexplore.ieee.org/stamp/stamp.jsp?arnumber=10820709 | B38: 10.1109/SCW63240.2024.00017 | C38: SciTrust: Evaluating the Trustworthiness of Large Language Models for Science | D38: Marilyn | E38: Include
A39: https://ieeexplore.ieee.org/stamp/stamp.jsp?arnumber=11531012 | B39: 10.1109/TDSC.2026.3695553 | C39: MCPXKIT: the Unified Toolkit for Analyzing Model Context Protocol Security | D39: Kaiser | E39: Exclude | F39: Not about Sycophancy
A40: https://ieeexplore.ieee.org/stamp/stamp.jsp?arnumber=5427110 | B40: 10.1109/TEVC.2009.2021466 | C40: XCS for Personalizing Desktop Interfaces | D40: Marilyn | E40: Exclude | F40: Not about either LLMs or Sycophancy
A41: https://doi.org/10.1109/TNET.2017.2669215 | B41: 10.1109/tnet.2017.2669215 | C41: CubicRing: Exploiting Network Proximity for Distributed In-Memory Key-Value Store | D41: Marilyn | E41: Exclude | F41: Not about either LLMs or Sycophancy
A42: https://ieeexplore.ieee.org/stamp/stamp.jsp?arnumber=11029593 | B42: 10.1109/TTS.2025.3573875 | C42: Emulated Empathy: Can Risks Be Countered by a Soft-Law Standard? | D42: Marilyn | E42: Exclude | F42: Not about Sycophancy | G42: Rather indirect (emulated empathy)
A43: https://ieeexplore.ieee.org/stamp/stamp.jsp?arnumber=11189226 | B43: 10.1109/UV63228.2024.11189226 | C43: Hallucination in Large Language Models: From Mechanistic Understanding to Novel Control Frameworks | D43: Marilyn | E43: Exclude | F43: Not about Sycophancy
A44: https://doi.org/10.1145/1037911.1037917 | B44: 10.1145/1037911.1037917 | C44: Fits and starts | D44: Marilyn | E44: Exclude | F44: Not a research paper
A45: https://doi.org/10.1145/1045264.1045265 | B45: 10.1145/1045264.1045265 | C45: Computer power and human reason | D45: Kaiser | E45: Exclude | F45: Not a research paper
A46: https://doi.org/10.1145/1088222.1088226 | B46: 10.1145/1088222.1088226 | C46: Some aspects of symbolic integration via predicate logic programming | D46: Kaiser | E46: Exclude | F46: Not about either LLMs or Sycophancy
A47: https://doi.org/10.1145/1120212.1120419 | B47: 10.1145/1120212.1120419 | C47: How users reciprocate to computers: an experiment that demonstrates behavior change | D47: Marilyn | E47: Exclude | F47: Not about either LLMs or Sycophancy
A48: https://doi.org/10.1145/1141880.1523452 | B48: 10.1145/1141880.1523452 | C48: Richard F. Hespos Interview: August 18-19 | D48: Jonathan | E48: Exclude | F48: Not a research paper
A49: https://doi.org/10.1145/1216295.1216357 | B49: 10.1145/1216295.1216357 | C49: User-context for adaptive user interfaces | D49: Marilyn | E49: Exclude | F49: Not about either LLMs or Sycophancy
A50: https://doi.org/10.1145/122153.122159 | B50: 10.1145/122153.122159 | C50: The senior seminar in computer science | D50: Jonathan | E50: Exclude | F50: Not about either LLMs or Sycophancy
A51: https://doi.org/10.1145/122153.122160 | B51: 10.1145/122153.122160 | C51: The arcade laboratory: an environment to help teach algorithms | D51: Jonathan | E51: Exclude | F51: Not about either LLMs or Sycophancy
A52: https://doi.org/10.1145/1274000.1274062 | B52: 10.1145/1274000.1274062 | C52: Cascaded generic XCS to learn about reminding preferences | D52: Jonathan | E52: Exclude | F52: Not about either LLMs or Sycophancy
A53: https://doi.org/10.1145/1276958.1277335 | B53: 10.1145/1276958.1277335 | C53: XCS for adaptive user-interfaces | D53: Marilyn | E53: Exclude | F53: Not about either LLMs or Sycophancy
A54: https://doi.org/10.1145/1394669.1394689 | B54: 10.1145/1394669.1394689 | C54: Multi projector displays using a 3D compositing window manager | D54: Jonathan | E54: Exclude | F54: Not about either LLMs or Sycophancy
A55: https://doi.org/10.1145/1409360.1409363 | B55: 10.1145/1409360.1409363 | C55: Apple builds great platforms | D55: Kaiser | E55: Exclude | F55: Not a research paper
A56: https://doi.org/10.1145/1450579.1450652 | B56: 10.1145/1450579.1450652 | C56: AVACHAT: a new comic-based chat system for virtual avatars | D56: Jonathan | E56: Exclude | F56: Not a research paper | G56: Poster
A57: https://doi.org/10.1145/1477862.1477879 | B57: 10.1145/1477862.1477879 | C57: A new cognition-based chat system for avatar agents in virtual space | D57: Kaiser | E57: Exclude | F57: Not about either LLMs or Sycophancy
A58: https://doi.org/10.1145/1500175.1500178 | B58: 10.1145/1500175.1500178 | C58: RADCAP: an operational parallel processing facility | D58: Kaiser | E58: Exclude | F58: Not about either LLMs or Sycophancy
A59: https://doi.org/10.1145/1518701.1519021 | B59: 10.1145/1518701.1519021 | C59: I'm sorry | D59: Kaiser | E59: Include
A60: https://doi.org/10.1145/1596685.1596827 | B60: 10.1145/1596685.1596827 | C60: Window pains | D60: Kaiser | E60: Exclude | F60: Not a research paper
A61: https://doi.org/10.1145/1621890.1621914 | B61: 10.1145/1621890.1621914 | C61: Dynamic web service orchestration applied to the device profile for web services in hierarchical networks | D61: Kaiser | E61: Exclude | F61: Not about either LLMs or Sycophancy
A62: https://doi.org/10.1145/1629575.1629577 | B62: 10.1145/1629575.1629577 | C62: FAWN: a fast array of wimpy nodes | D62: Jonathan | E62: Exclude | F62: Not about either LLMs or Sycophancy
A63: https://doi.org/10.1145/1640089.1640127 | B63: 10.1145/1640089.1640127 | C63: Regrowing a language: refactoring tools allow programming languages to evolve | D63: Jonathan | E63: Exclude | F63: Not about either LLMs or Sycophancy
A64: https://doi.org/10.1145/1740390.1740407 | B64: 10.1145/1740390.1740407 | C64: Low-power amdahl-balanced blades for data intensive computing | D64: Kaiser | E64: Exclude | F64: Not a research paper
A65: https://doi.org/10.1145/1740390.1740408 | B65: 10.1145/1740390.1740408 | C65: An energy case for hybrid datacenters | D65: Kaiser | E65: Exclude | F65: Not a research paper
A66: https://doi.org/10.1145/174690.174697 | B66: 10.1145/174690.174697 | C66: On Julius Caesar | D66: Jonathan | E66: Exclude | F66: Not about either LLMs or Sycophancy
A67: https://doi.org/10.1145/175208.175220 | B67: 10.1145/175208.175220 | C67: Israel: of swords and software plowshares | D67: Marilyn | E67: Exclude | F67: Not a research paper
A68: https://doi.org/10.1145/1755913.1755916 | B68: 10.1145/1755913.1755916 | C68: Differential RAID: rethinking RAID for SSD reliability | D68: Kaiser | E68: Exclude | F68: Not about either LLMs or Sycophancy
A69: https://doi.org/10.1145/1791314.1791347 | B69: 10.1145/1791314.1791347 | C69: Energy-efficient cluster computing with FAWN: workloads and implications | D69: Marilyn | E69: Exclude | F69: Not about either LLMs or Sycophancy
A70: https://doi.org/10.1145/1807060.1807061 | B70: 10.1145/1807060.1807061 | C70: Differential RAID: Rethinking RAID for SSD reliability | D70: Kaiser | E70: Exclude | F70: Not about either LLMs or Sycophancy
A71: https://doi.org/10.1145/1807128.1807164 | B71: 10.1145/1807128.1807164 | C71: Robust and flexible power-proportional storage | D71: Marilyn | E71: Exclude | F71: Not about either LLMs or Sycophancy
... A153: https://doi.org/10.1145/3033273 | B153: 10.1145/3033273 | C153: WiscKey: Separating Keys from Values in SSD-Conscious Storage | D153: Marilyn | E153: Exclude | F153: Not about either LLMs or Sycophancy
A154: https://doi.org/10.1145/3041960 | B154: 10.1145/3041960 | C154: Smart Computing and Sensing Technologies for Animal Welfare: A Systematic Review | D154: Jonathan | E154: Exclude | F154: Not a research paper | G154: Survey
A155: https://doi.org/10.1145/3056662.3056667 | B155: 10.1145/3056662.3056667 | C155: Performance and energy efficiency of big data systems: characterization | D155: Kaiser | E155: Exclude | F155: Not about either LLMs or Sycophancy
A156: https://doi.org/10.1145/3078468.3078471 | B156: 10.1145/3078468.3078471 | C156: Freewrite: creating (almost) zero-cost writes to SSD in applications | D156: Kaiser | E156: Exclude | F156: Not a research paper
A157: https://doi.org/10.1145/3085574 | B157: 10.1145/3085574 | C157: How to choose a conference | D157: Marilyn | E157: Exclude | F157: Not about either LLMs or Sycophancy
A158: https://doi.org/10.1145/309831.309929 | B158: 10.1145/309831.309929 | C158: Shifted normal forms of polynomial matrices | D158: Marilyn | E158: Exclude | F158: Not about either LLMs or Sycophancy
A159: https://doi.org/10.1145/3126594.3126640 | B159: 10.1145/3126594.3126640 | C159: More than a Feeling: The MiFace Framework for Defining Facial Communication Mappings | D159: Kaiser | E159: Exclude | F159: Not about either LLMs or Sycophancy
A160: https://doi.org/10.1145/3232162 | B160: 10.1145/3232162 | C160: Scale-Out vs Scale-Up: A Study of ARM-based SoCs on Server-Class Workloads | D160: Marilyn | E160: Exclude | F160: Not about either LLMs or Sycophancy
A161: https://doi.org/10.1145/3241038 | B161: 10.1145/3241038 | C161: A Taxonomy and Future Directions for Sustainable Cloud Computing: 360 Degree View | D161: Kaiser | E161: Exclude | F161: Not about either LLMs or Sycophancy
A162: https://doi.org/10.1145/3267809.3267847 | B162: 10.1145/3267809.3267847 | C162: Cascade Mapping: Optimizing Memory Efficiency for Flash-based Key-value Caching | D162: Jonathan | E162: Exclude | F162: Not about either LLMs or Sycophancy
A163: https://doi.org/10.1145/3273982.3273989 | B163: 10.1145/3273982.3273989 | C163: Morpheus: Exploring the Potential of Near-Data Processing for Creating Application Objects in Heterogeneous Computing | D163: Kaiser | E163: Exclude | F163: Not about either LLMs or Sycophancy
A164: https://doi.org/10.1145/3289604 | B164: 10.1145/3289604 | C164: Leveraging Glocality for Fast Failure Recovery in Distributed RAM Storage | D164: Marilyn | E164: Exclude | F164: Not about either LLMs or Sycophancy
A165: https://doi.org/10.1145/3290607.3312915 | B165: 10.1145/3290607.3312915 | C165: It Sounds Like A Woman: Exploring Gender Stereotypes in South Korean Voice Assistants | D165: Marilyn | E165: Exclude | F165: Not about Sycophancy
A166: https://doi.org/10.1145/3297858.3304022 | B166: 10.1145/3297858.3304022 | C166: LightStore: Software-defined Network-attached Key-value Drives | D166: Kaiser | E166: Exclude | F166: Not about either LLMs or Sycophancy
... A183: https://doi.org/10.1145/3492833 | B183: 10.1145/3492833 | C183: Access Under Duress: Pandemic-Era Lessons on Digital Participation and Datafication in Civic Engagement | D183: Kaiser | E183: Exclude | F183: Not about either LLMs or Sycophancy
A184: https://doi.org/10.1145/3511047.3536406 | B184: 10.1145/3511047.3536406 | C184: Optimizing the User Experience in VR-based Anti-Bullying Education | D184: Jonathan | E184: Exclude | F184: Not a research paper | G184: Extended Abstract
A185: https://doi.org/10.1145/3528381 | B185: 10.1145/3528381 | C185: Government as a Brain: How Can Governments Better Understand | D185: Marilyn | E185: Exclude | F185: Not about either LLMs or Sycophancy
A186: https://doi.org/10.1145/3538225 | B186: 10.1145/3538225 | C186: Energy-Efficient Database Systems: A Systematic Survey | D186: Kaiser | E186: Exclude | F186: Not a research paper
A187: https://doi.org/10.1145/3544549.3582735 | B187: 10.1145/3544549.3582735 | C187: Enough With “Human-AI Collaboration” | D187: Jonathan | E187: Exclude | F187: Not a research paper | G187: Extended Abstract
A188: https://doi.org/10.1145/3544793.3560382 | B188: 10.1145/3544793.3560382 | C188: Experience is the Best Teacher: Personalized Vocabulary Building Within the Context of Instagram Posts and Sentences from GPT-3 | D188: Kaiser | E188: Exclude | F188: Not about Sycophancy
A189: https://doi.org/10.1145/3555153 | B189: 10.1145/3555153 | C189: Acting Out Queer Identity: The Embodied Visibility in Social Virtual Reality | D189: Marilyn | E189: Exclude | F189: Not about either LLMs or Sycophancy
A190: https://doi.org/10.1145/3563456 | B190: 10.1145/3563456 | C190: TH-iSSD: Design and Implementation of a Generic and Reconfigurable Near-Data Processing Framework | D190: Marilyn | E190: Exclude | F190: Not about either LLMs or Sycophancy
A191: https://doi.org/10.1145/358027.358046 | B191: 10.1145/358027.358046 | C191: Languages: three interviews | D191: Marilyn | E191: Exclude | F191: Not a research paper
A192: https://doi.org/10.1145/3582515.3609571 | B192: 10.1145/3582515.3609571 | C192: The 8th Continent: Echoing the Unheard Sounds of Pollution | D192: Jonathan | E192: Exclude | F192: Not about either LLMs or Sycophancy
A193: https://doi.org/10.1145/3603269.3604880 | B193: 10.1145/3603269.3604880 | C193: LEED: A Low-Power | D193: Jonathan | E193: Exclude | F193: Not about either LLMs or Sycophancy
A194: https://doi.org/10.1145/3605764.3623985 | B194: 10.1145/3605764.3623985 | C194: Not What You've Signed Up For: Compromising Real-World LLM-Integrated Applications with Indirect Prompt Injection | D194: Jonathan | E194: Exclude | F194: Not about Sycophancy
A195: https://doi.org/10.1145/3610027 | B195: 10.1145/3610027 | C195: Creepy Towards My Avatar Body Creepy Towards My Body: How Women Experience and Manage Harassment Risks in Social Virtual Reality | D195: Marilyn | E195: Exclude | F195: Not about either LLMs or Sycophancy
A196: https://doi.org/10.1145/3610073 | B196: 10.1145/3610073 | C196: It Takes Two to Avoid Pregnancy: Addressing Conflicting Perceptions of Birth Control Pill Responsibility in Romantic Relationships | D196: Kaiser | E196: Exclude | F196: Not about either LLMs or Sycophancy
A197: https://doi.org/10.1145/3613904.3642038 | B197: 10.1145/3613904.3642038 | C197: Giving Robots a Voice: Human-in-the-Loop Voice Creation and open-ended Labeling | D197: Jonathan | E197: Exclude | F197: Not about either LLMs or Sycophancy
...

Sheet INCEXC B
A1: URL | B1: key | D1: Evaluator Name | E1: Included/Excluded | F1: Excluded Reason | G1: Other
A2: https://doi.org/10.1007/978-3-642-24322-6_15 | B2: 10.1007/978-3-642-24322-6_15 | C2: The search for energy-efficient building blocks for the data center | D2: Taylor | E2: Exclude | F2: Not about either LLMs or Sycophancy
A3: https://doi.org/10.1007/978-3-642-24322-6_16 | B3: 10.1007/978-3-642-24322-6_16 | C3: KnightShift: shifting the I/O burden in datacenters to management processor for energy efficiency | D3: Taylor | E3: Exclude | F3: Not about either LLMs or Sycophancy
A4: https://doi.org/10.1007/978-3-642-24322-6_19 | B4: 10.1007/978-3-642-24322-6_19 | C4: Achieving power-efficiency in clusters without distributed file system complexity | D4: Taylor | E4: Exclude | F4: Not about either LLMs or Sycophancy
A5: https://ieeexplore.ieee.org/stamp/stamp.jsp?arnumber=8372225 | B5: 10.1049/cp.2016.1548 | C5: A SOFC based autonomous microgrid performance analysis using adaptive PI and PI controller | D5: Danni | E5: Exclude | F5: Not about either LLMs or Sycophancy
A6: https://ieeexplore.ieee.org/stamp/stamp.jsp?arnumber=735370 | B6: 10.1109/47.735370 | C6: The letter of submission: avoiding the promotional genre | D6: Ceren | E6: Exclude | F6: Not about either LLMs or Sycophancy
A7: https://ieeexplore.ieee.org/stamp/stamp.jsp?arnumber=11467909 | B7: 10.1109/ACDSA67686.2026.11467909 | C7: Evaluating LLM-Induced Investment Biases via Persona Design and Prompt Analysis: A Quantitative Study of Post-Retirement Asset Depletion Risk Through Social Simulation | D7: Ceren | E7: Include
A8: https://ieeexplore.ieee.org/stamp/stamp.jsp?arnumber=10771051 | B8: 10.1109/AIxSET62544.2024.00047 | C8: Towards Transparent Artificial Intelligence: Exploring Modern Approaches and Future Directions | D8: Danni | E8: Exclude | F8: Not about Sycophancy
A9: https://ieeexplore.ieee.org/stamp/stamp.jsp?arnumber=11449950 | B9: 10.1109/AIxVR67263.2026.00026 | C9: Too Positive to Be True? Sentiment Analysis of AI-Guided vs. Human-Led Debriefings in Virtual Reality Counseling Training | D9: Taylor | E9: Include
A10: https://ieeexplore.ieee.org/stamp/stamp.jsp?arnumber=11334577 | B10: 10.1109/ASE63991.2025.00043 | C10: Why AI Agents Still Need You: Findings from Developer-Agent Collaborations in the Wild | D10: Taylor | E10: Exclude | G10: Touches on it
A11: https://doi.org/10.1109/ASONAM49781.2020.9381292 | B11: 10.1109/asonam49781.2020.9381292 | C11: Aspect based abusive sentiment detection in nepali social media texts | D11: Danni | E11: Exclude | F11: Not about either LLMs or Sycophancy
A12: https://ieeexplore.ieee.org/stamp/stamp.jsp?arnumber=9381292 | B12: 10.1109/ASONAM49781.2020.9381292 | C12: Aspect Based Abusive Sentiment Detection in Nepali Social Media Texts | D12: Taylor | E12: Exclude | F12: Not about either LLMs or Sycophancy
A13: https://ieeexplore.ieee.org/stamp/stamp.jsp?arnumber=10825538 | B13: 10.1109/BigData62323.2024.10825538 | C13: Mitigating Sycophancy in Large Language Models via Direct Preference Optimization | D13: Taylor | E13: Include
A14: https://ieeexplore.ieee.org/stamp/stamp.jsp?arnumber=11400739 | B14: 10.1109/BigData66926.2025.11400739 | C14: Towards Uncertainty-Aware Low-Bit Quantized LLMs for On-Device Inference | D14: Ceren | E14: Exclude | F14: Not about Sycophancy
A15: https://doi.org/10.1109/CCGrid.2012.84 | B15: 10.1109/ccgrid.2012.84 | C15: Energy- and Cost-Efficiency Analysis of ARM-Based Clusters | D15: Ceren | E15: Exclude | F15: Not about either LLMs or Sycophancy
A16: https://doi.org/10.1109/CCGrid.2015.115 | B16: 10.1109/ccgrid.2015.115 | C16: Quantitative musings on the feasibility of smartphone clouds | D16: Taylor | E16: Exclude | F16: Not about either LLMs or Sycophancy
A17: https://doi.org/10.1109/CCGrid.2015.150 | B17: 10.1109/ccgrid.2015.150 | C17: Deferred lightweight indexing for log-structured key-value stores | D17: Danni | E17: Exclude | F17: Not about either LLMs or Sycophancy
A18: https://doi.org/10.1109/CCGRID.2017.49 | B18: 10.1109/ccgrid.2017.49 | C18: High-Performance Key-Value Store On OpenSHMEM | D18: Taylor | E18: Exclude | F18: Not about either LLMs or Sycophancy
A19: https://ieeexplore.ieee.org/stamp/stamp.jsp?arnumber=1554950 | B19: 10.1109/CEC.2005.1554950 | C19: Learning classifier systems for user context learning | D19: Taylor | E19: Exclude | F19: Not about either LLMs or Sycophancy
A20: https://ieeexplore.ieee.org/stamp/stamp.jsp?arnumber=11519295 | B20: 10.1109/GAIIS69281.2026.11519295 | C20: PI-Embedding: Scientific Idea Representation Learning via Citation Intent and Paper Provenance | D20: Ceren | E20: Exclude | F20: Not about Sycophancy
A21: https://ieeexplore.ieee.org/stamp/stamp.jsp?arnumber=10585495 | B21: 10.1109/GEM61861.2024.10585495 | C21: Leveraging Large Language Models for Enhanced VR Development: Insights and Challenges | D21: Taylor | E21: Exclude | F21: Not about Sycophancy
A22: https://ieeexplore.ieee.org/stamp/stamp.jsp?arnumber=10590666 | B22: 10.1109/HPSC62738.2024.00012 | C22: Studying the Knowledge and Behavior of ChatGPT via Journey to the West | D22: Ceren | E22: Exclude | F22: Not about Sycophancy
A23: https://ieeexplore.ieee.org/stamp/stamp.jsp?arnumber=11508939 | B23: 10.1109/ICAACE69793.2026.11508939 | C23: Tiny-Critic RAG: Empowering Agentic Fallback with Parameter-Efficient Small Language Models | D23: Taylor | E23: Exclude | F23: Not about Sycophancy
A24: https://ieeexplore.ieee.org/stamp/stamp.jsp?arnumber=11460702 | B24: 10.1109/ICASSP55912.2026.11460702 | C24: Towards Self-Evaluation of Sycophantic Hallucinations in Mathematical Reasoning | D24: Danni | E24: Include
A25: https://ieeexplore.ieee.org/stamp/stamp.jsp?arnumber=11462217 | B25: 10.1109/ICASSP55912.2026.11462217 | C25: FinLumen: A Game-Theoretic Multi-Agent Framework for Rational Portfolio Management | D25: Ceren | E25: Exclude | F25: Not about Sycophancy
A26: https://ieeexplore.ieee.org/stamp/stamp.jsp?arnumber=5409737 | B26: 10.1109/ICASTECH.2009.5409737 | C26: Tracking a Sycophant Wireless Sensor Network for its seamless integration to mobile Wireless Sensor Networks | D26: Danni | E26: Exclude | F26: Not about either LLMs or Sycophancy
A27: https://ieeexplore.ieee.org/stamp/stamp.jsp?arnumber=6056911 | B27: 10.1109/ICECENG.2011.6056911 | C27: Cohesive subgroups analysis of asynchronous cognitive interactive network in collaborative learning | D27: Danni | E27: Exclude | F27: Not about either LLMs or Sycophancy
A28: https://ieeexplore.ieee.org/stamp/stamp.jsp?arnumber=11521627 | B28: 10.1109/ICEIT68991.2026.11521627 | C28: The design of a GAI-supported research topic selection system for novice researchers: From the SECI perspective | D28: Danni | E28: Exclude | F28: Not about Sycophancy
A29: https://ieeexplore.ieee.org/stamp/stamp.jsp?arnumber=4299963 | B29: 10.1109/ICSEA.2007.67 | C29: Sycophant: An API for Research in Context-Aware User Interfaces | D29: Danni | E29: Exclude | F29: Not about either LLMs or Sycophancy
A30: https://ieeexplore.ieee.org/stamp/stamp.jsp?arnumber=1431446 | B30: 10.1109/IRI.2004.1431446 | C30: Context learning can improve user interaction | D30: Danni | E30: Exclude | F30: Other (Explanation ->) | G30: Page not found
A31: https://doi.org/10.1109/ISCA.2016.15 | B31: 10.1109/isca.2016.15 | C31: Morpheus: creating application objects efficiently for heterogeneous computing | D31: Danni | E31: Exclude | F31: Not about either LLMs or Sycophancy
A32: https://ieeexplore.ieee.org/stamp/stamp.jsp?arnumber=11269633 | B32: 10.1109/ISTAS65609.2025.11269633 | C32: AI Detection and Risk Estimation in Family Violence: Challenges and Governance | D32: Danni | E32: Exclude | F32: Not about Sycophancy
A33: https://ieeexplore.ieee.org/stamp/stamp.jsp?arnumber=4580542 | B33: 10.1109/MIS.2008.55 | C33: A Computational Approach to Etiquette: Operationalizing Brown and Levinson's Politeness Model | D33: Danni | E33: Exclude | F33: Not about either LLMs or Sycophancy
A34: https://ieeexplore.ieee.org/stamp/stamp.jsp?arnumber=11345775 | B34: 10.1109/NKCon66957.2025.11345775 | C34: Improving Argumentative Reasoning in LLMs Using Online Debates and Agent-Based Interaction | D34: Danni | E34: Exclude | F34: Not about Sycophancy
A35: https://ieeexplore.ieee.org/stamp/stamp.jsp?arnumber=11037824 | B35: 10.1109/OJCS.2025.3580498 | C35: LLMs on a Budget: System-Level Approaches to Power-Efficient and Scalable Fine-Tuning | D35: Ceren | E35: Exclude | F35: Not about Sycophancy
A36: https://ieeexplore.ieee.org/stamp/stamp.jsp?arnumber=11424465 | B36: 10.1109/RAMS50514.2026.11424465 | C36: Autonomous AI-Driven FMEA Optimization For Safety And Reliability In Healthcare | D36: Taylor | E36: Include
A37: https://doi.org/10.1109/SCW63240.2024.00017 | B37: 10.1109/SCW63240.2024.00017 | C37: SciTrust: Evaluating the Trustworthiness of Large Language Models for Science | D37: Danni | E37: Exclude | F37: Not about Sycophancy
A38: https://ieeexplore.ieee.org/stamp/stamp.jsp?arnumber=10820709 | B38: 10.1109/SCW63240.2024.00017 | C38: SciTrust: Evaluating the Trustworthiness of Large Language Models for Science | D38: Ceren | E38: Include
A39: https://ieeexplore.ieee.org/stamp/stamp.jsp?arnumber=11531012 | B39: 10.1109/TDSC.2026.3695553 | C39: MCPXKIT: the Unified Toolkit for Analyzing Model Context Protocol Security | D39: Ceren | E39: Exclude | F39: Not about Sycophancy
A40: https://ieeexplore.ieee.org/stamp/stamp.jsp?arnumber=5427110 | B40: 10.1109/TEVC.2009.2021466 | C40: XCS for Personalizing Desktop Interfaces | D40: Ceren | E40: Exclude | F40: Not about either LLMs or Sycophancy
A41: https://doi.org/10.1109/TNET.2017.2669215 | B41: 10.1109/tnet.2017.2669215 | C41: CubicRing: Exploiting Network Proximity for Distributed In-Memory Key-Value Store | D41: Ceren | E41: Exclude | F41: Not about either LLMs or Sycophancy
A42: https://ieeexplore.ieee.org/stamp/stamp.jsp?arnumber=11029593 | B42: 10.1109/TTS.2025.3573875 | C42: Emulated Empathy: Can Risks Be Countered by a Soft-Law Standard? | D42: Ceren | E42: Exclude | F42: Not about either LLMs or Sycophancy
A43: https://ieeexplore.ieee.org/stamp/stamp.jsp?arnumber=11189226 | B43: 10.1109/UV63228.2024.11189226 | C43: Hallucination in Large Language Models: From Mechanistic Understanding to Novel Control Frameworks | D43: Danni | E43: Exclude | F43: Not about Sycophancy
A44: https://doi.org/10.1145/1037911.1037917 | B44: 10.1145/1037911.1037917 | C44: Fits and starts | D44: Ceren | E44: Exclude | F44: Not about either LLMs or Sycophancy
A45: https://doi.org/10.1145/1045264.1045265 | B45: 10.1145/1045264.1045265 | C45: Computer power and human reason | D45: Danni | E45: Exclude | F45: Not a research paper
A46: https://doi.org/10.1145/1088222.1088226 | B46: 10.1145/1088222.1088226 | C46: Some aspects of symbolic integration via predicate logic programming | D46: Ceren | E46: Exclude | F46: Not about either LLMs or Sycophancy
A47: https://doi.org/10.1145/1120212.1120419 | B47: 10.1145/1120212.1120419 | C47: How users reciprocate to computers: an experiment that demonstrates behavior change | D47: Ceren | E47: Exclude | F47: Not about either LLMs or Sycophancy
A48: https://doi.org/10.1145/1141880.1523452 | B48: 10.1145/1141880.1523452 | C48: Richard F. Hespos Interview: August 18-19 | D48: Taylor | E48: Exclude | F48: Not a research paper
A49: https://doi.org/10.1145/1216295.1216357 | B49: 10.1145/1216295.1216357 | C49: User-context for adaptive user interfaces | D49: Danni | E49: Exclude | F49: Not about either LLMs or Sycophancy
A50: https://doi.org/10.1145/122153.122159 | B50: 10.1145/122153.122159 | C50: The senior seminar in computer science | D50: Danni | E50: Exclude | F50: Not about either LLMs or Sycophancy
... A54: https://doi.org/10.1145/1394669.1394689 | B54: 10.1145/1394669.1394689 | C54: Multi projector displays using a 3D compositing window manager | D54: Danni | E54: Exclude | F54: Not about either LLMs or Sycophancy
A55: https://doi.org/10.1145/1409360.1409363 | B55: 10.1145/1409360.1409363 | C55: Apple builds great platforms | D55: Taylor | E55: Exclude | F55: Not a research paper | G55: No abstract
A56: https://doi.org/10.1145/1450579.1450652 | B56: 10.1145/1450579.1450652 | C56: AVACHAT: a new comic-based chat system for virtual avatars | D56: Ceren | E56: Exclude | F56: Not about either LLMs or Sycophancy
A57: https://doi.org/10.1145/1477862.1477879 | B57: 10.1145/1477862.1477879 | C57: A new cognition-based chat system for avatar agents in virtual space | D57: Danni | E57: Exclude | F57: Not about either LLMs or Sycophancy
A58: https://doi.org/10.1145/1500175.1500178 | B58: 10.1145/1500175.1500178 | C58: RADCAP: an operational parallel processing facility | D58: Danni | E58: Exclude | F58: Not about either LLMs or Sycophancy
A59: https://doi.org/10.1145/1518701.1519021 | B59: 10.1145/1518701.1519021 | C59: I'm sorry | D59: Taylor | E59: Include
A60: https://doi.org/10.1145/1596685.1596827 | B60: 10.1145/1596685.1596827 | C60: Window pains | D60: Danni | E60: Exclude | F60: Not about either LLMs or Sycophancy
A61: https://doi.org/10.1145/1621890.1621914 | B61: 10.1145/1621890.1621914 | C61: Dynamic web service orchestration applied to the device profile for web services in hierarchical networks | D61: Danni | E61: Exclude | F61: Not about either LLMs or Sycophancy
A62: https://doi.org/10.1145/1629575.1629577 | B62: 10.1145/1629575.1629577 | C62: FAWN: a fast array of wimpy nodes | D62: Danni | E62: Exclude | F62: Not about either LLMs or Sycophancy
A63: https://doi.org/10.1145/1640089.1640127 | B63: 10.1145/1640089.1640127 | C63: Regrowing a language: refactoring tools allow programming languages to evolve | D63: Taylor | E63: Exclude | F63: Not about either LLMs or Sycophancy
A64: https://doi.org/10.1145/1740390.1740407 | B64: 10.1145/1740390.1740407 | C64: Low-power amdahl-balanced blades for data intensive computing | D64: Ceren | E64: Exclude | F64: Not about either LLMs or Sycophancy
A65: https://doi.org/10.1145/1740390.1740408 | B65: 10.1145/1740390.1740408 | C65: An energy case for hybrid datacenters | D65: Danni | E65: Exclude | F65: Not about either LLMs or Sycophancy
A66: https://doi.org/10.1145/174690.174697 | B66: 10.1145/174690.174697 | C66: On Julius Caesar | D66: Danni | E66: Exclude | F66: Not about either LLMs or Sycophancy
A67: https://doi.org/10.1145/175208.175220 | B67: 10.1145/175208.175220 | C67: Israel: of swords and software plowshares | D67: Taylor | E67: Exclude | F67: Not about either LLMs or Sycophancy | G67: Also genuinely what did i just see
A68: https://doi.org/10.1145/1755913.1755916 | B68: 10.1145/1755913.1755916 | C68: Differential RAID: rethinking RAID for SSD reliability | D68: Taylor | E68: Exclude | F68: Not about either LLMs or Sycophancy
A69: https://doi.org/10.1145/1791314.1791347 | B69: 10.1145/1791314.1791347 | C69: Energy-efficient cluster computing with FAWN: workloads and implications | D69: Danni | E69: Exclude | F69: Not about either LLMs or Sycophancy
A70: https://doi.org/10.1145/1807060.1807061 | B70: 10.1145/1807060.1807061 | C70: Differential RAID: Rethinking RAID for SSD reliability | D70: Danni | E70: Exclude | F70: Not about either LLMs or Sycophancy
A71: https://doi.org/10.1145/1807128.1807164 | B71: 10.1145/1807128.1807164 | C71: Robust and flexible power-proportional storage | D71: Taylor | E71: Exclude | F71: Not about either LLMs or Sycophancy
A72: https://doi.org/10.1145/1807167.1807194 | B72: 10.1145/1807167.1807194 | C72: Analyzing the energy efficiency of a database server | D72: Danni | E72: Exclude | F72: Not about either LLMs or Sycophancy
A73: https://doi.org/10.1145/1807167.1807324 | B73: 10.1145/1807167.1807324 | C73: Performing sound flash device measurements: some lessons from uFLIP | D73: Taylor | E73: Exclude | F73: Not about either LLMs or Sycophancy
A74: https://doi.org/10.1145/1809980.1810034 | B74: 10.1145/1809980.1810034 | C74: Um sistema web para acompanhar o crescimento e desenvolvimento do algodão | D74: Taylor | E74: Exclude | F74: Not about either LLMs or Sycophancy
A75: https://doi.org/10.1145/1815961.1816002 | B75: 10.1145/1815961.1816002 | C75: Web search using mobile cores: quantifying and mitigating the price of efficiency | D75: Danni | E75: Exclude | F75: Not about either LLMs or Sycophancy
A76: https://doi.org/10.1145/1823838.1823840 | B76: 10.1145/1823838.1823840 | C76: Storage research in industry and universities | D76: Taylor | E76: Exclude | F76: Not about either LLMs or Sycophancy
A77: https://doi.org/10.1145/1837915.1837918 | B77: 10.1145/1837915.1837918 | C77: Optimizing energy and performance for server-class file system workloads | D77: Ceren | E77: Exclude | F77: Not about either LLMs or Sycophancy
A78: https://doi.org/10.1145/1839676.1839692 | B78: 10.1145/1839676.1839692 | C78: Keeping bits safe: how hard can it be? | D78: Taylor | E78: Exclude | F78: Not about either LLMs or Sycophancy
A79: https://doi.org/10.1145/1866029.1866078 | B79: 10.1145/1866029.1866078 | C79: Soylent: a word processor with a crowd inside | D79: Ceren | E79: Exclude | F79: Not about either LLMs or Sycophancy
... A83: https://doi.org/10.1145/1945023.1945029 | B83: 10.1145/1945023.1945029 | C83: Challenges and opportunities for efficient computing with FAWN | D83: Danni | E83: Exclude | F83: Not about either LLMs or Sycophancy
A84: https://doi.org/10.1145/1965724.1965746 | B84: 10.1145/1965724.1965746 | C84: FAWN: a fast array of wimpy nodes: technical perspective | D84: Taylor | E84: Exclude | F84: Other (Explanation ->) | G84: No abstract
A85: https://doi.org/10.1145/1965724.1965747 | B85: 10.1145/1965724.1965747 | C85: FAWN: a fast array of wimpy nodes | D85: Ceren | E85: Exclude | F85: Not about either LLMs or Sycophancy
A86: https://doi.org/10.1145/196734.196738 | B86: 10.1145/196734.196738 | C86: Finding a happy medium: explaining the negative effects of electronic communication on social life at work | D86: Ceren | E86: Exclude | F86: Not about either LLMs or Sycophancy
A87: https://doi.org/10.1145/1978942.1979209 | B87: 10.1145/1978942.1979209 | C87: Evaluating longitudinal projects combining technology with temporal arts | D87: Ceren | E87: Exclude | F87: Not about either LLMs or Sycophancy
A88: https://doi.org/10.1145/1989323.1989327 | B88: 10.1145/1989323.1989327 | C88: SkimpyStash: RAM space skimpy key-value store on flash-based storage | D88: Danni | E88: Exclude | F88: Not about either LLMs or Sycophancy
A89: https://doi.org/10.1145/1989323.1989461 | B89: 10.1145/1989323.1989461 | C89: WattDB: an energy-proportional cluster of wimpy nodes | D89: Taylor | E89: Exclude | F89: Not about either LLMs or Sycophancy
A90: https://doi.org/10.1145/1995896.1995926 | B90: 10.1145/1995896.1995926 | C90: Optimizing the datacenter for data-centric workloads | D90: Ceren | E90: Exclude | F90: Not about either LLMs or Sycophancy
A91: https://doi.org/10.1145/199688.199776 | B91: 10.1145/199688.199776 | C91: Inexpensive advanced graphics applications for the C.S. majors graphics class | D91: Danni | E91: Exclude | F91: Not about either LLMs or Sycophancy
A92: https://doi.org/10.1145/2003690.2003693 | B92: 10.1145/2003690.2003693 | C92: Mobile processors for energy-efficient web search | D92: Ceren | E92: Exclude | F92: Not about either LLMs or Sycophancy
A93: https://doi.org/10.1145/2018584.2018596 | B93: 10.1145/2018584.2018596 | C93: A reality check for content centric networking | D93: Taylor | E93: Exclude | F93: Not about either LLMs or Sycophancy
A94: https://doi.org/10.1145/2038916.2038917 | B94: 10.1145/2038916.2038917 | C94: An efficient multi-tier tablet server storage architecture | D94: Taylor | E94: Exclude | F94: Not about either LLMs or Sycophancy
A95: https://doi.org/10.1145/2038916.2038939 | B95: 10.1145/2038916.2038939 | C95: Small cache | D95: Ceren | E95: Exclude | F95: Not about either LLMs or Sycophancy
A96: https://doi.org/10.1145/2043556.2043558 | B96: 10.1145/2043556.2043558 | C96: SILT: a memory-efficient | D96: Ceren | E96: Exclude | F96: Not about either LLMs or Sycophancy
... A201: https://doi.org/10.1145/3639372 | B201: 10.1145/3639372 | C201: Explainability for Large Language Models: A Survey | D201: Ceren | E201: Exclude | F201: Not about Sycophancy
A202: https://doi.org/10.1145/3640352 | B202: 10.1145/3640352 | C202: Thirsty Fabs | D202: Taylor | E202: Exclude | F202: Other (Explanation ->) | G202: Genuinely what is this
A203: https://doi.org/10.1145/3640543.3645148 | B203: 10.1145/3640543.3645148 | C203: Understanding Users’ Dissatisfaction with ChatGPT Responses: Types | D203: Danni | E203: Exclude | F203: Not about Sycophancy
A204: https://doi.org/10.1145/3642979.3642984 | B204: 10.1145/3642979.3642984 | C204: Evaluating Parrots and Sociopathic Liars: A keynote at ICTIR 2023 | D204: Ceren | E204: Exclude | F204: Not a research paper
A205: https://doi.org/10.1145/3643834.3661525 | B205: 10.1145/3643834.3661525 | C205: Imagining a Future of Designing with AI: Dynamic Grounding | D205: Danni | E205: Exclude | F205: Not about Sycophancy
A206: https://doi.org/10.1145/3648188.3678216 | B206: 10.1145/3648188.3678216 | C206: Computer | D206: Danni | E206: Exclude | F206: Not about either LLMs or Sycophancy
A207: https://doi.org/10.1145/3655103.3655107 | B207: 10.1145/3655103.3655107 | C207: Storage Systems: Organization | D207: Danni | E207: Exclude | F207: Not about either LLMs or Sycophancy
A208: https://doi.org/10.1145/3657604.3662042 | B208: 10.1145/3657604.3662042 | C208: Supporting Self-Reflection at Scale with Large Language Models: Insights from Randomized Field Experiments in Classrooms | D208: Ceren | E208: Exclude | F208: Not about Sycophancy
A209: https://doi.org/10.1145/3658644.3691638 | B209: 10.1145/3658644.3691638 | C209: Modern problems require modern solutions: Community-Developed Techniques for Online Exam Proctoring Evasion | D209: Taylor | E209: Exclude | F209: Not about either LLMs or Sycophancy
A210: https://doi.org/10.1145/3660650.3660656 | B210: 10.1145/3660650.3660656 | C210: Faceless Adversary | D210: Taylor | E210: Include
...

Sheet Query Validation
A1: Check | B1: Evaluator | C1: Sycophantic Papers? | D1: Title 1 | E1: Title 2 | F1: In All Papers | G1: Included in INC/EXC Disc
A2: SESSION: AI & Data Visualization | B2: Tina | C2: No
A3: SESSION: AI & Timing Matters | B3: Tina | C3: No
A4: SESSION: AI Collaboration in Practice | B4: Tina | C4: No
A5: SESSION: AI Explanations and Decision Support in Healthcare | B5: Tina | C5: No
A6: SESSION: AI Governance and Accountability | B6: Tina | C6: No
A7: SESSION: AI Governance and Safety | B7: Tina | C7: No
A8: SESSION: AI Literacy, Ethics, and Critical AI Understanding | B8: Tina | C8: No
A9: SESSION: AI Personality | B9: Tina | C9: No
A10: SESSION: AI Risks | B10: Tina | C10: No
A11: SESSION: AI Systems for Human Goals | B11: Tina | C11: No
A12: SESSION: AI Tutors and Learning Support Systems | B12: Tina | C12: No
A13: SESSION: AI for Language Learning & Communication Skills | B13: Tina | C13: No
... A17: SESSION: AI in Family, Dating and Private Life | B17: Tina | C17: No
A18: SESSION: AI in Practice | B18: Tina | C18: Yes | D18: Personal Validation Effect in LLMs: Positive AI Responses Bias Perceptions of Validity, Reliability, Personalization, and Usefulness of Fictitious Predictions | F18: Yes | G18: Yes
A19: SESSION: AI in Work and Expertise | B19: Tina | C19: No
A20: SESSION: AI, Learning and Inclusion in Education | B20: Tina | C20: No
A21: SESSION: AI, Motivation and Learning | B21: Tina | C21: No
A22: SESSION: AI-Assisted Clinical Diagnosis and Reasoning | B22: Tina | C22: No
A23: SESSION: AI-Driven Creativity & Design Methods | B23: Tina | C23: No
A24: SESSION: Accessibility in Everyday Life | B24: Tina | C24: No
A25: SESSION: Affective Agents & Reflective Data | B25: Tina | C25: No
A26: SESSION: Aging and Later Life | B26: Tina | C26: No
A27: SESSION: Algorithmic Power, Justice and Repression | B27: Tina | C27: No
A28: SESSION: Alternative Perspectives | B28: Tina | C28: No
A29: SESSION: Animals & Nature | B29: Tina | C29: No
A30: SESSION: Assistive Tech and Professional Inclusion | B30: Tina | C30: No
... A54: SESSION: Conversational AI | B54: Tina | C54: No
A55: SESSION: Conversational AI, Agency and Control | B55: Tina | C55: Yes | D55: Polite But Boring? Trade-offs Between Engagement and Psychological Reactance to Chatbot Feedback Styles | F55: Yes | G55: No
A56: SESSION: Creating with AI | B56: Tina | C56: No
A57: SESSION: Creativity and Innovation | B57: Tina | C57: No
A58: SESSION: Critical Reflections on AI | B58: Tina | C58: No
A59: SESSION: Dark Patterns, Deception, and Manipulative Interfaces | B59: Tina | C59: No
A60: SESSION: Data Visualization Designs and Tools | B60: Tina | C60: No
A61: SESSION: Data Work | B61: Tina | C61: No
A62: SESSION: Design Methods and Frameworks | B62: Tina | C62: No
A63: SESSION: Designing Care Futures | B63: Tina | C63: No
A64: SESSION: Designing Creative GenAI Tools | B64: Tina | C64: No
A65: SESSION: Designing Data Visualizations | B65: Tina | C65: No
A66: SESSION: Designing Player Experience | B66: Tina | C66: No
A67: SESSION: Designing XR Interaction | B67: Tina | C67: No
... A113: SESSION: Heritage, Memory, & Speculative Narratives | B113: Cindy | C113: No
A114: SESSION: Human Behavior with AI Systems | B114: Cindy | C114: Yes | D114: Interaction Context Often Increases Sycophancy in LLMs | F114: Yes | G114: Yes
A115: SESSION: Human Steering and Interaction with AI | B115: Cindy | C115: No
A116: SESSION: Human-AI Decision Making | B116: Cindy | C116: Yes | D116: Does Sycophancy Change Decisions? Effect of LLM Sycophancy on AI-Assisted Decision-Making | F116: Yes | G116: Yes
A117: SESSION: Human-AI Interaction & GenAI | B117: Cindy | C117: No
A118: SESSION: Human-Robot Interaction | B118: Cindy | C118: No
A119: SESSION: Human-Robot Interaction & Embodied Sensing | B119: Cindy | C119: No
A120: SESSION: Human-in-the-Loop Machine Learning Interfaces | B120: Cindy | C120: No
A121: SESSION: Identity, Culture, and Games for Social Impact | B121: Cindy | C121: No
A122: SESSION: Immersive Play and Spatial Computing | B122: Cindy | C122: No
A123: SESSION: Immersive and Spatial Visualization | B123: Cindy | C123: No
A124: SESSION: Inferring Human State | B124: Cindy | C124: No
A125: SESSION: Intelligent Feedback & Learning Design | B125: Cindy | C125: No
A126: SESSION: Interactive Design Systems for Fabrication | B126: Cindy | C126: No
A127: SESSION: Interactive Prompting, Chaining, and LLM Orchestration Tools | B127: Cindy | C127: No
A128: SESSION: Interactive Systems for Teaching, Learning, and Concept Formation | B128: Cindy | C128: No
... A180: SESSION: Reflecting on Haptics | B180: Rudranil | C180: No
A181: SESSION: Relationships with AI | B181: Rudranil | C181: Yes | D181: Be Friendly and Not Friend: How LLM Sycophancy tend to shape or structure the trust of users | F181: Yes | G181: Yes
A182: SESSION: Religion, Spirituality, and Design | B182: Rudranil | C182: No
A183: SESSION: Research Methodology & UX | B183: Rudranil | C183: No
A184: SESSION: Responsible AI, Policy, & Dark Patterns | B184: Rudranil | C184: No
A185: SESSION: Role Play, Creativity and AI | B185: Rudranil | C185: No
A186: SESSION: Romance and Relationships in the Age of AI | B186: Rudranil | C186: No
A187: SESSION: Safe Driving | B187: Rudranil | C187: No
A188: SESSION: Safety, Identity & Relatedness | B188: Rudranil | C188: No
A189: SESSION: Scam Experiences | B189: Rudranil | C189: No
A190: SESSION: Security Operations and Governance | B190: Rudranil | C190: No
A191: SESSION: Security and Privacy Behavior | B191: Rudranil | C191: No
A192: SESSION: Self-Tracking and Personal Health Informatics | B192: Rudranil | C192: No
A193: SESSION: Sensemaking | B193: Rudranil | C193: No
... A221: SESSION: Toxicity and Moderation in Online Games | B221: Rudranil | C221: No
A222: SESSION: Trust and Perception in AI Systems | B222: Rudranil | C222: Yes | D222: The Impact of AI companions sycophancy on user well-being | F222: No | G222: No
A223: SESSION: Trust and Transparency in Everyday Life | B223: Rudranil | C223: No
A224: SESSION: VR AR XR | B224: Rudranil | C224: No
A225: SESSION: VR and Immersive Technologies for Mental Health | B225: Rudranil | C225: No
A226: SESSION: Video Presentations | B226: Rudranil | C226: No
A227: SESSION: Virtual Reality | B227: Rudranil | C227: No
A228: SESSION: Wearable, Audio and Novel Interactive Devices | B228: Rudranil | C228: No
A229: SESSION: Women's Health and Safety | B229: Rudranil | C229: No
A230: SESSION: XR Navigation | B230: Rudranil | C230: No
A231: SESSION: XR Selection | B231: Rudranil | C231: No
A232: SESSION: XR and Environmental Adaptation/Integration | B232: Rudranil | C232: No
A233: SESSION: Youth, Families, and Safe Play | B233: Rudranil | C233: No

Sheet INCEXC Disc
C1: Matching | D1: Key | E1: Title | F1: Coder A | G1: Coder B | H1: Code A | I1: Code B | J1: Match | K1: Agreed include
A2: ='INCEXC A'!A2 -> https://doi.org/10.1007/978-3-642-24322-6_15 | B2: ='INCEXC B'!A2 -> https://doi.org/10.1007/978-3-642-24322-6_15 | C2: =A2=B2 -> TRUE | D2: ='INCEXC A'!B2 -> 10.1007/978-3-642-24322-6_15 | E2: ='INCEXC A'!C2 -> The search for energy-efficient building blocks for the data center | F2: ='INCEXC A'!D2 -> Jonathan | G2: ='INCEXC B'!D2 -> Taylor | H2: ='INCEXC A'!E2 -> Exclude | I2: ='INCEXC B'!E2 -> Exclude | J2: =H2=I2 -> TRUE | K2: =AND(H2="Include",J2) -> FALSE
A3: ='INCEXC A'!A3 -> https://doi.org/10.1007/978-3-642-24322-6_16 | B3: ='INCEXC B'!A3 -> https://doi.org/10.1007/978-3-642-24322-6_16 | C3: =A3=B3 -> TRUE | D3: ='INCEXC A'!B3 -> 10.1007/978-3-642-24322-6_16 | E3: ='INCEXC A'!C3 -> KnightShift: shifting the I/O burden in datacenters to management processor for energy efficiency | F3: ='INCEXC A'!D3 -> Marilyn | G3: ='INCEXC B'!D3 -> Taylor | H3: ='INCEXC A'!E3 -> Exclude | I3: ='INCEXC B'!E3 -> Exclude | J3: =H3=I3 -> TRUE | K3: =AND(H3="Include",J3) -> FALSE | L3: ='INCEXC A'!L3 | M3: ='INCEXC B'!L3 | O3: ='INCEXC A'!M3 | P3: ='INCEXC A'!N3 | Q3: ='INCEXC A'!O3 | R3: ='INCEXC B'!O3 | S3: ='INCEXC A'!P3 | T3: ='INCEXC B'!P3 | U3: =S3=T3 -> TRUE | V3: =AND(S3="Include",U3) -> FALSE
A4: ='INCEXC A'!A4 -> https://doi.org/10.1007/978-3-642-24322-6_19 | B4: ='INCEXC B'!A4 -> https://doi.org/10.1007/978-3-642-24322-6_19 | C4: =A4=B4 -> TRUE | D4: ='INCEXC A'!B4 -> 10.1007/978-3-642-24322-6_19 | E4: ='INCEXC A'!C4 -> Achieving power-efficiency in clusters without distributed file system complexity | F4: ='INCEXC A'!D4 -> Marilyn | G4: ='INCEXC B'!D4 -> Taylor | H4: ='INCEXC A'!E4 -> Exclude | I4: ='INCEXC B'!E4 -> Exclude | J4: =H4=I4 -> TRUE | K4: =AND(H4="Include",J4) -> FALSE | L4: ='INCEXC A'!L4 | M4: ='INCEXC B'!L4 | O4: ='INCEXC A'!M4 | P4: ='INCEXC A'!N4 | Q4: ='INCEXC A'!O4 | R4: ='INCEXC B'!O4 | S4: ='INCEXC A'!P4 | T4: ='INCEXC B'!P4 | U4: =S4=T4 -> TRUE | V4: =AND(S4="Include",U4) -> FALSE
A5: ='INCEXC A'!A5 -> https://ieeexplore.ieee.org/stamp/stamp.jsp?arnumber=8372225 | B5: ='INCEXC B'!A5 -> https://ieeexplore.ieee.org/stamp/stamp.jsp?arnumber=8372225 | C5: =A5=B5 -> TRUE | D5: ='INCEXC A'!B5 -> 10.1049/cp.2016.1548 | E5: ='INCEXC A'!C5 -> A SOFC based autonomous microgrid performance analysis using adaptive PI and PI controller | F5: ='INCEXC A'!D5 -> Marilyn | G5: ='INCEXC B'!D5 -> Danni | H5: ='INCEXC A'!E5 -> Exclude | I5: ='INCEXC B'!E5 -> Exclude | J5: =H5=I5 -> TRUE | K5: =AND(H5="Include",J5) -> FALSE | L5: ='INCEXC A'!L5 | M5: ='INCEXC B'!L5 | O5: ='INCEXC A'!M5 | P5: ='INCEXC A'!N5 | Q5: ='INCEXC A'!O5 | R5: ='INCEXC B'!O5 | S5: ='INCEXC A'!P5 | T5: ='INCEXC B'!P5 | U5: =S5=T5 -> TRUE | V5: =AND(S5="Include",U5) -> FALSE
A6: ='INCEXC A'!A6 -> https://ieeexplore.ieee.org/stamp/stamp.jsp?arnumber=735370 | B6: ='INCEXC B'!A6 -> https://ieeexplore.ieee.org/stamp/stamp.jsp?arnumber=735370 | C6: =A6=B6 -> TRUE | D6: ='INCEXC A'!B6 -> 10.1109/47.735370 | E6: ='INCEXC A'!C6 -> The letter of submission: avoiding the promotional genre | F6: ='INCEXC A'!D6 -> Jonathan | G6: ='INCEXC B'!D6 -> Ceren | H6: ='INCEXC A'!E6 -> Exclude | I6: ='INCEXC B'!E6 -> Exclude | J6: =H6=I6 -> TRUE | K6: =AND(H6="Include",J6) -> FALSE | L6: ='INCEXC A'!L6 | M6: ='INCEXC B'!L6 | O6: ='INCEXC A'!M6 | P6: ='INCEXC A'!N6 | Q6: ='INCEXC A'!O6 | R6: ='INCEXC B'!O6 | S6: ='INCEXC A'!P6 | T6: ='INCEXC B'!P6 | U6: =S6=T6 -> TRUE | V6: =AND(S6="Include",U6) -> FALSE
A7: ='INCEXC A'!A7 -> https://ieeexplore.ieee.org/stamp/stamp.jsp?arnumber=11467909 | B7: ='INCEXC B'!A7 -> https://ieeexplore.ieee.org/stamp/stamp.jsp?arnumber=11467909 | C7: =A7=B7 -> TRUE | D7: ='INCEXC A'!B7 -> 10.1109/ACDSA67686.2026.11467909 | E7: ='INCEXC A'!C7 -> Evaluating LLM-Induced Investment Biases via Persona Design and Prompt Analysis: A Quantitative Study of Post-Retirement Asset Depletion Risk Through Social Simulation | F7: ='INCEXC A'!D7 -> Marilyn | G7: ='INCEXC B'!D7 -> Ceren | H7: ='INCEXC A'!E7 -> Include | I7: ='INCEXC B'!E7 -> Include | J7: =H7=I7 -> TRUE | K7: =AND(H7="Include",J7) -> TRUE | L7: ='INCEXC A'!L7 | M7: ='INCEXC B'!L7 | O7: ='INCEXC A'!M7 | P7: ='INCEXC A'!N7 | Q7: ='INCEXC A'!O7 | R7: ='INCEXC B'!O7 | S7: ='INCEXC A'!P7 | T7: ='INCEXC B'!P7 | U7: =S7=T7 -> TRUE | V7: =AND(S7="Include",U7) -> FALSE
A8: ='INCEXC A'!A8 -> https://ieeexplore.ieee.org/stamp/stamp.jsp?arnumber=10771051 | B8: ='INCEXC B'!A8 -> https://ieeexplore.ieee.org/stamp/stamp.jsp?arnumber=10771051 | C8: =A8=B8 -> TRUE | D8: ='INCEXC A'!B8 -> 10.1109/AIxSET62544.2024.00047 | E8: ='INCEXC A'!C8 -> Towards Transparent Artificial Intelligence: Exploring Modern Approaches and Future Directions | F8: ='INCEXC A'!D8 -> Kaiser | G8: ='INCEXC B'!D8 -> Danni | H8: ='INCEXC A'!E8 -> Exclude | I8: ='INCEXC B'!E8 -> Exclude | J8: =H8=I8 -> TRUE | K8: =AND(H8="Include",J8) -> FALSE | L8: ='INCEXC A'!L8 | M8: ='INCEXC B'!L8 | O8: ='INCEXC A'!M8 | P8: ='INCEXC A'!N8 | Q8: ='INCEXC A'!O8 | R8: ='INCEXC B'!O8 | S8: ='INCEXC A'!P8 | T8: ='INCEXC B'!P8 | U8: =S8=T8 -> TRUE | V8: =AND(S8="Include",U8) -> FALSE
A9: ='INCEXC A'!A9 -> https://ieeexplore.ieee.org/stamp/stamp.jsp?arnumber=11449950 | B9: ='INCEXC B'!A9 -> https://ieeexplore.ieee.org/stamp/stamp.jsp?arnumber=11449950 | C9: =A9=B9 -> TRUE | D9: ='INCEXC A'!B9 -> 10.1109/AIxVR67263.2026.00026 | E9: ='INCEXC A'!C9 -> Too Positive to Be True? Sentiment Analysis of AI-Guided vs. Human-Led Debriefings in Virtual Reality Counseling Training | F9: ='INCEXC A'!D9 -> Kaiser | G9: ='INCEXC B'!D9 -> Taylor | H9: ='INCEXC A'!E9 -> Include | I9: ='INCEXC B'!E9 -> Include | J9: =H9=I9 -> TRUE | K9: =AND(H9="Include",J9) -> TRUE | L9: ='INCEXC A'!L9 | M9: ='INCEXC B'!L9 | O9: ='INCEXC A'!M9 | P9: ='INCEXC A'!N9 | Q9: ='INCEXC A'!O9 | R9: ='INCEXC B'!O9 | S9: ='INCEXC A'!P9 | T9: ='INCEXC B'!P9 | U9: =S9=T9 -> TRUE | V9: =AND(S9="Include",U9) -> FALSE
A10: ='INCEXC A'!A10 -> https://ieeexplore.ieee.org/stamp/stamp.jsp?arnumber=11334577 | B10: ='INCEXC B'!A10 -> https://ieeexplore.ieee.org/stamp/stamp.jsp?arnumber=11334577 | C10: =A10=B10 -> TRUE | D10: ='INCEXC A'!B10 -> 10.1109/ASE63991.2025.00043 | E10: ='INCEXC A'!C10 -> Why AI Agents Still Need You: Findings from Developer-Agent Collaborations in the Wild | F10: ='INCEXC A'!D10 -> Kaiser | G10: ='INCEXC B'!D10 -> Taylor | H10: ='INCEXC A'!E10 -> Exclude | I10: ='INCEXC B'!E10 -> Exclude | J10: =H10=I10 -> TRUE | K10: =AND(H10="Include",J10) -> FALSE | L10: ='INCEXC A'!L10 | M10: ='INCEXC B'!L10 | O10: ='INCEXC A'!M10 | P10: ='INCEXC A'!N10 | Q10: ='INCEXC A'!O10 | R10: ='INCEXC B'!O10 | S10: ='INCEXC A'!P10 | T10: ='INCEXC B'!P10 | U10: =S10=T10 -> TRUE | V10: =AND(S10="Include",U10) -> FALSE
A11: ='INCEXC A'!A11 -> https://ieeexplore.ieee.org/stamp/stamp.jsp?arnumber=9381292 | B11: ='INCEXC B'!A11 -> https://doi.org/10.1109/ASONAM49781.2020.9381292 | C11: =A11=B11 -> FALSE | D11: ='INCEXC A'!B11 -> 10.1109/ASONAM49781.2020.9381292 | E11: ='INCEXC A'!C11 -> Aspect Based Abusive Sentiment Detection in Nepali Social Media Texts | F11: ='INCEXC A'!D11 -> Jonathan | G11: ='INCEXC B'!D11 -> Danni | H11: ='INCEXC A'!E11 -> Exclude | I11: ='INCEXC B'!E11 -> Exclude | J11: =H11=I11 -> TRUE | K11: =AND(H11="Include",J11) -> FALSE | L11: ='INCEXC A'!L11 | M11: ='INCEXC B'!L11 | O11: ='INCEXC A'!M11 | P11: ='INCEXC A'!N11 | Q11: ='INCEXC A'!O11 | R11: ='INCEXC B'!O11 | S11: ='INCEXC A'!P11 | T11: ='INCEXC B'!P11 | U11: =S11=T11 -> TRUE | V11: =AND(S11="Include",U11) -> FALSE
A12: ='INCEXC A'!A12 -> https://doi.org/10.1109/ASONAM49781.2020.9381292 | B12: ='INCEXC B'!A12 -> https://ieeexplore.ieee.org/stamp/stamp.jsp?arnumber=9381292 | C12: =A12=B12 -> FALSE | D12: ='INCEXC A'!B12 -> 10.1109/asonam49781.2020.9381292 | E12: ='INCEXC A'!C12 -> Aspect based abusive sentiment detection in nepali social media texts | F12: ='INCEXC A'!D12 -> Marilyn | G12: ='INCEXC B'!D12 -> Taylor | H12: ='INCEXC A'!E12 -> Exclude | I12: ='INCEXC B'!E12 -> Exclude | J12: =H12=I12 -> TRUE | K12: =AND(H12="Include",J12) -> FALSE | L12: ='INCEXC A'!L12 | M12: ='INCEXC B'!L12 | O12: ='INCEXC A'!M12 | P12: ='INCEXC A'!N12 | Q12: ='INCEXC A'!O12 | R12: ='INCEXC B'!O12 | S12: ='INCEXC A'!P12 | T12: ='INCEXC B'!P12 | U12: =S12=T12 -> TRUE | V12: =AND(S12="Include",U12) -> FALSE
A13: ='INCEXC A'!A13 -> https://ieeexplore.ieee.org/stamp/stamp.jsp?arnumber=10825538 | B13: ='INCEXC B'!A13 -> https://ieeexplore.ieee.org/stamp/stamp.jsp?arnumber=10825538 | C13: =A13=B13 -> TRUE | D13: ='INCEXC A'!B13 -> 10.1109/BigData62323.2024.10825538 | E13: ='INCEXC A'!C13 -> Mitigating Sycophancy in Large Language Models via Direct Preference Optimization | F13: ='INCEXC A'!D13 -> Kaiser | G13: ='INCEXC B'!D13 -> Taylor | H13: ='INCEXC A'!E13 -> Include | I13: ='INCEXC B'!E13 -> Include | J13: =H13=I13 -> TRUE | K13: =AND(H13="Include",J13) -> TRUE | L13: ='INCEXC A'!L13 | M13: ='INCEXC B'!L13 | O13: ='INCEXC A'!M13 | P13: ='INCEXC A'!N13 | Q13: ='INCEXC A'!O13 | R13: ='INCEXC B'!O13 | S13: ='INCEXC A'!P13 | T13: ='INCEXC B'!P13 | U13: =S13=T13 -> TRUE | V13: =AND(S13="Include",U13) -> FALSE
A14: ='INCEXC A'!A14 -> https://ieeexplore.ieee.org/stamp/stamp.jsp?arnumber=11400739 | B14: ='INCEXC B'!A14 -> https://ieeexplore.ieee.org/stamp/stamp.jsp?arnumber=11400739 | C14: =A14=B14 -> TRUE | D14: ='INCEXC A'!B14 -> 10.1109/BigData66926.2025.11400739 | E14: ='INCEXC A'!C14 -> Towards Uncertainty-Aware Low-Bit Quantized LLMs for On-Device Inference | F14: ='INCEXC A'!D14 -> Kaiser | G14: ='INCEXC B'!D14 -> Ceren | H14: ='INCEXC A'!E14 -> Exclude | I14: ='INCEXC B'!E14 -> Exclude | J14: =H14=I14 -> TRUE | K14: =AND(H14="Include",J14) -> FALSE | L14: ='INCEXC A'!L14 | M14: ='INCEXC B'!L14 | O14: ='INCEXC A'!M14 | P14: ='INCEXC A'!N14 | Q14: ='INCEXC A'!O14 | R14: ='INCEXC B'!O14 | S14: ='INCEXC A'!P14 | T14: ='INCEXC B'!P14 | U14: =S14=T14 -> TRUE | V14: =AND(S14="Include",U14) -> FALSE
... A396: ='INCEXC A'!A396 -> https://ieeexplore.ieee.org/stamp/stamp.jsp?arnumber=6921105 | B396: ='INCEXC B'!A396 -> https://ieeexplore.ieee.org/xpl/ebooks/bookPdfWithBanner.jsp?fileName=8646901.pdf&bkn=8646803&pdfType=chapter | C396: =A396=B396 -> FALSE | D396: ='INCEXC A'!B396 -> X | E396: ='INCEXC A'!C396 -> Exploring the national role and position of international technology diffusion: A technological embeddedness perspective | F396: ='INCEXC A'!D396 -> Kaiser | G396: ='INCEXC B'!D396 -> Taylor | H396: ='INCEXC A'!E396 -> Exclude | I396: ='INCEXC B'!E396 -> Exclude | J396: =H396=I396 -> TRUE | K396: =AND(H396="Include",J396) -> FALSE | L396: ='INCEXC A'!L396 | M396: ='INCEXC B'!L396 | O396: ='INCEXC A'!M396 | P396: ='INCEXC A'!N396 | Q396: ='INCEXC A'!O396 | R396: ='INCEXC B'!O396 | S396: ='INCEXC A'!P396 | T396: ='INCEXC B'!P396 | U396: =S396=T396 -> TRUE | V396: =AND(S396="Include",U396) -> FALSE

Sheet Mapping A
A1: URL | B1: Key | C1: Title | D1: Coder | E1: Mapped | F1: Population (Whos is doing the judging of sycophancy?) | K1: Definition of Sycophancy (what exactly do they mean by sycophancy) | P1: Outcomes (Are they measuring the impact of sycophancy on something else?)
E2: At least one X in each category | F2: Human - general | G2: Human - Student | H2: Human - Specialist | I2: Human - Authors | J2: AI - prompted | K2: Hallucination Agreement | L2: Bias Agreement | M2: Obsequiousness | N2: Stance Change | O2: Failure to challenge/trying to get along | P2: None | Q2: User opinion | R2: User action | S2: System performance | T2: User performance
F3: A human judge with no specific expertise | G3: Specifically having students judge | H3: Having someone with expertise (psychologist, conversation expert, etc) judge | I3: Authors judging | J3: Some sort of prompted AI doing the judging | K3: Saying something objectively wrong/harmful becuase the user wants it to be so | L3: The LLM choosing something that isn't objectively wrong, but siding towards the version that it believes user would want | M3: Fawning or overly positive language | N3: Getting the LLM to change opinions/stance/viewpoint to please/mirror user | O3: LLM failing to push back or challenge user or just going along with user's suggestion despite potential problems | P3: Just measuing sycophancy directly with no impact | Q3: Measuring how users feel/react in some way | R3: Measuring something about how users behave while/after interacting with sycophantic LLMS | S3: Some measure of how sycophantic LLMs perform on some task | T3: Some measure of how well the user is able to accomplish a task with sycophantic/non-sycophantic agents
A4: https://ieeexplore.ieee.org/stamp/stamp.jsp?arnumber=11467909 | B4: 10.1109/ACDSA67686.2026.11467909 | C4: Evaluating LLM-Induced Investment Biases via Persona Design and Prompt Analysis: A Quantitative Study of Post-Retirement Asset Depletion Risk Through Social Simulation | D4: Ceren | E4: =IF(AND(COUNTIF(F4:J4,"X")>0,COUNTIF(K4:O4,"X")>0,COUNTIF(P4:T4,"X")>0),"X","")
A5: https://ieeexplore.ieee.org/stamp/stamp.jsp?arnumber=11449950 | B5: 10.1109/AIxVR67263.2026.00026 | C5: Too Positive to Be True? Sentiment Analysis of AI-Guided vs. Human-Led Debriefings in Virtual Reality Counseling Training | D5: Ceren | E5: =IF(AND(COUNTIF(F5:J5,"X")>0,COUNTIF(K5:O5,"X")>0,COUNTIF(P5:T5,"X")>0),"X","") -> X | J5: X | M5: X | O5: X | R5: X
A6: https://ieeexplore.ieee.org/stamp/stamp.jsp?arnumber=10825538 | B6: 10.1109/BigData62323.2024.10825538 | C6: Mitigating Sycophancy in Large Language Models via Direct Preference Optimization | D6: Ceren | E6: =IF(AND(COUNTIF(F6:J6,"X")>0,COUNTIF(K6:O6,"X")>0,COUNTIF(P6:T6,"X")>0),"X","") -> X | J6: X | N6: X | O6: X | S6: X
A7: https://ieeexplore.ieee.org/stamp/stamp.jsp?arnumber=11460702 | B7: 10.1109/ICASSP55912.2026.11460702 | C7: Towards Self-Evaluation of Sycophantic Hallucinations in Mathematical Reasoning | D7: Ceren | E7: =IF(AND(COUNTIF(F7:J7,"X")>0,COUNTIF(K7:O7,"X")>0,COUNTIF(P7:T7,"X")>0),"X","") -> X | J7: X | K7: X | N7: X | O7: X | S7: X
A8: https://ieeexplore.ieee.org/stamp/stamp.jsp?arnumber=11424465 | B8: 10.1109/RAMS50514.2026.11424465 | C8: Autonomous AI-Driven FMEA Optimization For Safety And Reliability In Healthcare | D8: Ceren | E8: =IF(AND(COUNTIF(F8:J8,"X")>0,COUNTIF(K8:O8,"X")>0,COUNTIF(P8:T8,"X")>0),"X","")
A9: https://ieeexplore.ieee.org/stamp/stamp.jsp?arnumber=10820709 | B9: 10.1109/SCW63240.2024.00017 | C9: SciTrust: Evaluating the Trustworthiness of Large Language Models for Science | D9: Ceren | E9: =IF(AND(COUNTIF(F9:J9,"X")>0,COUNTIF(K9:O9,"X")>0,COUNTIF(P9:T9,"X")>0),"X","") -> X | I9: X | J9: X | K9: X | S9: X
A10: https://doi.org/10.1145/1518701.1519021 | B10: 10.1145/1518701.1519021 | C10: I'm sorry | D10: Ceren | E10: =IF(AND(COUNTIF(F10:J10,"X")>0,COUNTIF(K10:O10,"X")>0,COUNTIF(P10:T10,"X")>0),"X","") -> X | F10: X | O10: X | Q10: X | R10: X
A11: https://doi.org/10.1145/3660650.3660656 | B11: 10.1145/3660650.3660656 | C11: Faceless Adversary | D11: Cindy | E11: =IF(AND(COUNTIF(F11:J11,"X")>0,COUNTIF(K11:O11,"X")>0,COUNTIF(P11:T11,"X")>0),"X","") -> X | H11: X | M11: X | O11: X | P11: X
A12: https://doi.org/10.1145/3663547.3746319 | B12: 10.1145/3663547.3746319 | C12: Probing the Gaps in ChatGPT's Live Video Chat for Real-World Assistance for People who are Blind or Visually Impaired | D12: Cindy | E12: =IF(AND(COUNTIF(F12:J12,"X")>0,COUNTIF(K12:O12,"X")>0,COUNTIF(P12:T12,"X")>0),"X","") -> X | I12: X | O12: X | Q12: X | R12: X
A13: https://doi.org/10.1145/3703155 | B13: 10.1145/3703155 | C13: A Survey on Hallucination in Large Language Models: Principles | D13: Cindy | E13: =IF(AND(COUNTIF(F13:J13,"X")>0,COUNTIF(K13:O13,"X")>0,COUNTIF(P13:T13,"X")>0),"X","") -> X | H13: X | K13: X | O13: X | S13: X
A14: https://doi.org/10.1145/3706599.3719976 | B14: 10.1145/3706599.3719976 | C14: Exploring Older Adults Personality Preferences for LLM-powered Conversational Companions | D14: Cindy | E14: =IF(AND(COUNTIF(F14:J14,"X")>0,COUNTIF(K14:O14,"X")>0,COUNTIF(P14:T14,"X")>0),"X","") -> X | F14: X | L14: X | O14: X | Q14: X
A15: https://doi.org/10.1145/3715275.3732039 | B15: 10.1145/3715275.3732039 | C15: Expressing stigma and inappropriate responses prevents LLMs from safely replacing mental health providers. | D15: Cindy | E15: =IF(AND(COUNTIF(F15:J15,"X")>0,COUNTIF(K15:O15,"X")>0,COUNTIF(P15:T15,"X")>0),"X","") -> X | H15: X | J15: X | O15: X | S15: X
A16: https://doi.org/10.1145/3717511.3747073 | B16: 10.1145/3717511.3747073 | C16: Interactive Social Agent Behaviors of Politeness and Compromise in Collaborative Decision-making | D16: Cindy | E16: =IF(AND(COUNTIF(F16:J16,"X")>0,COUNTIF(K16:O16,"X")>0,COUNTIF(P16:T16,"X")>0),"X","") -> X | F16: X | L16: X | O16: X | T16: X
A17: https://doi.org/10.1145/3719160.3736618 | B17: 10.1145/3719160.3736618 | C17: Navigating the Fog: How University Students Recalibrate Sensemaking Practices to Address Plausible Falsehoods in LLM Outputs | D17: Cindy | E17: =IF(AND(COUNTIF(F17:J17,"X")>0,COUNTIF(K17:O17,"X")>0,COUNTIF(P17:T17,"X")>0),"X","") -> X | G17: X | N17: X | Q17: X | R17: X
A18: https://doi.org/10.1145/3742413.3789120 | B18: 10.1145/3742413.3789120 | C18: Neural Transparency: Mechanistic Interpretability Interfaces for Anticipating Model Behaviors for Personalized AI | D18: Danni | E18: =IF(AND(COUNTIF(F18:J18,"X")>0,COUNTIF(K18:O18,"X")>0,COUNTIF(P18:T18,"X")>0),"X","") -> X | F18: X | J18: X | O18: X | R18: X | T18: X
A19: https://doi.org/10.1145/3744169.3744194 | B19: 10.1145/3744169.3744194 | C19: Reading the Praise/Prompt Machine: An Interface Criticism Approach to ChatGPT | D19: Danni | E19: =IF(AND(COUNTIF(F19:J19,"X")>0,COUNTIF(K19:O19,"X")>0,COUNTIF(P19:T19,"X")>0),"X","") -> X | I19: X | M19: X | O19: X | P19: X
A20: https://doi.org/10.1145/3746027.3755778 | B20: 10.1145/3746027.3755778 | C20: Evaluating and Mitigating Sycophancy in Large Vision-Language Models | D20: Danni | E20: =IF(AND(COUNTIF(F20:J20,"X")>0,COUNTIF(K20:O20,"X")>0,COUNTIF(P20:T20,"X")>0),"X","") -> X | I20: X | K20: X | N20: X | S20: X
A21: https://doi.org/10.1145/3772318.3790332 | B21: 10.1145/3772318.3790332 | C21: Behavioral Indicators of Overreliance During Interaction with Conversational Language Models | D21: Danni | E21: =IF(AND(COUNTIF(F21:J21,"X")>0,COUNTIF(K21:O21,"X")>0,COUNTIF(P21:T21,"X")>0),"X","") -> X | G21: X | K21: X | R21: X | T21: X
A22: https://doi.org/10.1145/3772318.3790385 | B22: 10.1145/3772318.3790385 | C22: Understanding Compliance and Conversion Dynamics in Multi-Agent Collectives | D22: Danni | E22: =IF(AND(COUNTIF(F22:J22,"X")>0,COUNTIF(K22:O22,"X")>0,COUNTIF(P22:T22,"X")>0),"X","") -> X | F22: X | N22: X | O22: X | Q22: X | R22: X
A23: https://doi.org/10.1145/3772318.3790934 | B23: 10.1145/3772318.3790934 | C23: Does Sycophancy Change Decisions? Effect of LLM Sycophancy on AI-Assisted Decision-Making | D23: Danni | E23: =IF(AND(COUNTIF(F23:J23,"X")>0,COUNTIF(K23:O23,"X")>0,COUNTIF(P23:T23,"X")>0),"X","") -> X | F23: X | L23: X | M23: X | Q23: X | R23: X | T23: X
A24: https://doi.org/10.1145/3772318.3791079 | B24: 10.1145/3772318.3791079 | C24: Be Friendly | D24: Danni | E24: =IF(AND(COUNTIF(F24:J24,"X")>0,COUNTIF(K24:O24,"X")>0,COUNTIF(P24:T24,"X")>0),"X","") -> X | F24: X | M24: X | N24: X | Q24: X
A25: https://doi.org/10.1145/3772318.3791149 | B25: 10.1145/3772318.3791149 | C25: The Siren Song of LLMs: How Users Perceive and Respond to Dark Patterns in Large Language Models | D25: Jonathan | E25: =IF(AND(COUNTIF(F25:J25,"X")>0,COUNTIF(K25:O25,"X")>0,COUNTIF(P25:T25,"X")>0),"X","") -> X | F25: X | L25: X | M25: X | Q25: X | R25: X
A26: https://doi.org/10.1145/3772318.3791233 | B26: 10.1145/3772318.3791233 | C26: When AI Gives Advice: Evaluating AI and Human Responses to Online Advice-Seeking for Well-Being | D26: Jonathan | E26: =IF(AND(COUNTIF(F26:J26,"X")>0,COUNTIF(K26:O26,"X")>0,COUNTIF(P26:T26,"X")>0),"X","") -> X | G26: X | H26: X | L26: X | Q26: X | S26: X
A27: https://doi.org/10.1145/3772318.3791300 | B27: 10.1145/3772318.3791300 | C27: All Accept | D27: Jonathan | E27: =IF(AND(COUNTIF(F27:J27,"X")>0,COUNTIF(K27:O27,"X")>0,COUNTIF(P27:T27,"X")>0),"X","") -> X | H27: X | L27: X | S27: X
A28: https://doi.org/10.1145/3772318.3791365 | B28: 10.1145/3772318.3791365 | C28: Invisible Saboteurs: Sycophantic LLMs Mislead Novices in Problem-Solving Tasks | D28: Jonathan | E28: =IF(AND(COUNTIF(F28:J28,"X")>0,COUNTIF(K28:O28,"X")>0,COUNTIF(P28:T28,"X")>0),"X","") -> X | G28: X | O28: X | T28: X
A29: https://doi.org/10.1145/3772318.3791851 | B29: 10.1145/3772318.3791851 | C29: Personal Validation Effect in LLMs: Positive AI Responses Bias Perceptions of Validity | D29: Jonathan | E29: =IF(AND(COUNTIF(F29:J29,"X")>0,COUNTIF(K29:O29,"X")>0,COUNTIF(P29:T29,"X")>0),"X","") -> X | F29: X | L29: X | Q29: X
A30: https://doi.org/10.1145/3772318.3791915 | B30: 10.1145/3772318.3791915 | C30: Interaction Context Often Increases Sycophancy in LLMs | D30: Jonathan | E30: =IF(AND(COUNTIF(F30:J30,"X")>0,COUNTIF(K30:O30,"X")>0,COUNTIF(P30:T30,"X")>0),"X","") -> X | G30: X | L30: X | P30: X
A31: https://doi.org/10.1145/3772363.3798705 | B31: 10.1145/3772363.3798705 | C31: When AI Agrees | D31: Jonathan | E31: =IF(AND(COUNTIF(F31:J31,"X")>0,COUNTIF(K31:O31,"X")>0,COUNTIF(P31:T31,"X")>0),"X","") -> X | F31: X | L31: X | Q31: X
A32: https://doi.org/10.1145/3772363.3799334 | B32: 10.1145/3772363.3799334 | C32: Maintaining Stable Personas? Examining Temporal Stability in LLM-Based Human Simulation | D32: Kaiser | E32: =IF(AND(COUNTIF(F32:J32,"X")>0,COUNTIF(K32:O32,"X")>0,COUNTIF(P32:T32,"X")>0),"X","") -> X | I32: X | O32: X | S32: X
A33: https://doi.org/10.1145/3774904.3792506 | B33: 10.1145/3774904.3792506 | C33: Acting Flatterers via LLMs Sycophancy: Combating Clickbait with LLMs Opposing-Stance Reasoning | D33: Kaiser | E33: =IF(AND(COUNTIF(F33:J33,"X")>0,COUNTIF(K33:O33,"X")>0,COUNTIF(P33:T33,"X")>0),"X","") -> X | J33: X | L33: X | N33: X | S33: X
A34: https://doi.org/10.1145/3776734.3794532 | B34: 10.1145/3776734.3794532 | C34: Robotic Sycophancy: A Scoping Review | D34: Kaiser | E34: =IF(AND(COUNTIF(F34:J34,"X")>0,COUNTIF(K34:O34,"X")>0,COUNTIF(P34:T34,"X")>0),"X","") -> X | I34: X | L34: X | M34: X | O34: X | P34: X
A35: https://doi.org/10.1145/3786304.3787879 | B35: 10.1145/3786304.3787879 | C35: Confirmation | D35: Kaiser | E35: =IF(AND(COUNTIF(F35:J35,"X")>0,COUNTIF(K35:O35,"X")>0,COUNTIF(P35:T35,"X")>0),"X","") -> X | I35: X | L35: X | P35: X
A36: https://doi.org/10.1145/3786335.3813137 | B36: 10.1145/3786335.3813137 | C36: The Cost of Consensus: Isolated Self-Correction Prevails Over Unguided Homogeneous Multi-Agent Debate | D36: Kaiser | E36: =IF(AND(COUNTIF(F36:J36,"X")>0,COUNTIF(K36:O36,"X")>0,COUNTIF(P36:T36,"X")>0),"X","") -> X | I36: X | N36: X | S36: X
A37: https://doi.org/10.1145/3788646.3789536 | B37: 10.1145/3788646.3789536 | C37: AI-Assisted Moot Courts: Simulating Justice-Specific Questioning in Oral Arguments | D37: Kaiser | E37: =IF(AND(COUNTIF(F37:J37,"X")>0,COUNTIF(K37:O37,"X")>0,COUNTIF(P37:T37,"X")>0),"X","") -> X | G37: X | J37: X | L37: X | O37: X | S37: X

Sheet Mapping B
A1: URL | B1: Key | C1: Title | D1: Coder | E1: Mapped | F1: Population (Whos is doing the judging of sycophancy?) | K1: Definition of Sycophancy (what exactly do they mean by sycophancy) | P1: Outcomes (Are they measuring the impact of sycophancy on something else?)
E2: At least one X in each category | F2: Human - general | G2: Human - Student | H2: Human - Specialist | I2: Human - Authors | J2: AI - prompted | K2: Hallucination Agreement | L2: Bias Agreement | M2: Obsequiousness | N2: Stance Change | O2: Failure to challenge/trying to get along | P2: None | Q2: User opinion | R2: User action | S2: System performance | T2: User performance
F3: A human judge with no specific expertise | G3: Specifically having students judge | H3: Having someone with expertise (psychologist, conversation expert, etc) judge | I3: Authors judging | J3: Some sort of prompted AI doing the judging | K3: Saying something objectively wrong/harmful becuase the user wants it to be so | L3: The LLM choosing something that isn't objectively wrong, but siding towards the version that it believes user would want | M3: Fawning or overly positive language | N3: Getting the LLM to change opinions/stance/viewpoint to please/mirror user | O3: LLM failing to push back or challenge user or just going along with user's suggestion despite potential problems | P3: Just measuing sycophancy directly with no impact | Q3: Measuring how users feel/react in some way | R3: Measuring something about how users behave while/after interacting with sycophantic LLMS | S3: Some measure of how sycophantic LLMs perform on some task | T3: Some measure of how well the user is able to accomplish a task with sycophantic/non-sycophantic agents
A4: https://ieeexplore.ieee.org/stamp/stamp.jsp?arnumber=11467909 | B4: 10.1109/ACDSA67686.2026.11467909 | C4: Evaluating LLM-Induced Investment Biases via Persona Design and Prompt Analysis: A Quantitative Study of Post-Retirement Asset Depletion Risk Through Social Simulation | D4: Tina | E4: =IF(AND(COUNTIF(F4:J4,"X")>0,COUNTIF(K4:O4,"X")>0,COUNTIF(P4:T4,"X")>0),"X","")
A5: https://ieeexplore.ieee.org/stamp/stamp.jsp?arnumber=11449950 | B5: 10.1109/AIxVR67263.2026.00026 | C5: Too Positive to Be True? Sentiment Analysis of AI-Guided vs. Human-Led Debriefings in Virtual Reality Counseling Training | D5: Marilyn | E5: =IF(AND(COUNTIF(F5:J5,"X")>0,COUNTIF(K5:O5,"X")>0,COUNTIF(P5:T5,"X")>0),"X","") -> X | J5: X | M5: X | O5: X | R5: X
A6: https://ieeexplore.ieee.org/stamp/stamp.jsp?arnumber=10825538 | B6: 10.1109/BigData62323.2024.10825538 | C6: Mitigating Sycophancy in Large Language Models via Direct Preference Optimization | D6: Danni | E6: =IF(AND(COUNTIF(F6:J6,"X")>0,COUNTIF(K6:O6,"X")>0,COUNTIF(P6:T6,"X")>0),"X","") -> X | J6: X | N6: X | O6: X | S6: X
A7: https://ieeexplore.ieee.org/stamp/stamp.jsp?arnumber=11460702 | B7: 10.1109/ICASSP55912.2026.11460702 | C7: Towards Self-Evaluation of Sycophantic Hallucinations in Mathematical Reasoning | D7: Marilyn | E7: =IF(AND(COUNTIF(F7:J7,"X")>0,COUNTIF(K7:O7,"X")>0,COUNTIF(P7:T7,"X")>0),"X","") -> X | J7: X | K7: X | N7: X | O7: X | S7: X
A8: https://ieeexplore.ieee.org/stamp/stamp.jsp?arnumber=11424465 | B8: 10.1109/RAMS50514.2026.11424465 | C8: Autonomous AI-Driven FMEA Optimization For Safety And Reliability In Healthcare | D8: Tina | E8: =IF(AND(COUNTIF(F8:J8,"X")>0,COUNTIF(K8:O8,"X")>0,COUNTIF(P8:T8,"X")>0),"X","")
A9: https://ieeexplore.ieee.org/stamp/stamp.jsp?arnumber=10820709 | B9: 10.1109/SCW63240.2024.00017 | C9: SciTrust: Evaluating the Trustworthiness of Large Language Models for Science | D9: Marilyn | E9: =IF(AND(COUNTIF(F9:J9,"X")>0,COUNTIF(K9:O9,"X")>0,COUNTIF(P9:T9,"X")>0),"X","") -> X | I9: X | J9: X | K9: X | S9: X
A10: https://doi.org/10.1145/1518701.1519021 | B10: 10.1145/1518701.1519021 | C10: I'm sorry | D10: Tina | E10: =IF(AND(COUNTIF(F10:J10,"X")>0,COUNTIF(K10:O10,"X")>0,COUNTIF(P10:T10,"X")>0),"X","") -> X | F10: X | O10: X | Q10: X | R10: X
A11: https://doi.org/10.1145/3660650.3660656 | B11: 10.1145/3660650.3660656 | C11: Faceless Adversary | D11: Marilyn | E11: =IF(AND(COUNTIF(F11:J11,"X")>0,COUNTIF(K11:O11,"X")>0,COUNTIF(P11:T11,"X")>0),"X","") -> X | H11: X | M11: X | O11: X | P11: X
A12: https://doi.org/10.1145/3663547.3746319 | B12: 10.1145/3663547.3746319 | C12: Probing the Gaps in ChatGPT's Live Video Chat for Real-World Assistance for People who are Blind or Visually Impaired | D12: Marilyn | E12: =IF(AND(COUNTIF(F12:J12,"X")>0,COUNTIF(K12:O12,"X")>0,COUNTIF(P12:T12,"X")>0),"X","") -> X | I12: X | O12: X | Q12: X | R12: X
A13: https://doi.org/10.1145/3703155 | B13: 10.1145/3703155 | C13: A Survey on Hallucination in Large Language Models: Principles | D13: Marilyn | E13: =IF(AND(COUNTIF(F13:J13,"X")>0,COUNTIF(K13:O13,"X")>0,COUNTIF(P13:T13,"X")>0),"X","") -> X | H13: X | K13: X | O13: X | S13: X
A14: https://doi.org/10.1145/3706599.3719976 | B14: 10.1145/3706599.3719976 | C14: Exploring Older Adults Personality Preferences for LLM-powered Conversational Companions | D14: Kaiser | E14: =IF(AND(COUNTIF(F14:J14,"X")>0,COUNTIF(K14:O14,"X")>0,COUNTIF(P14:T14,"X")>0),"X","") -> X | F14: X | L14: X | O14: X | Q14: X
A15: https://doi.org/10.1145/3715275.3732039 | B15: 10.1145/3715275.3732039 | C15: Expressing stigma and inappropriate responses prevents LLMs from safely replacing mental health providers. | D15: Marilyn | E15: =IF(AND(COUNTIF(F15:J15,"X")>0,COUNTIF(K15:O15,"X")>0,COUNTIF(P15:T15,"X")>0),"X","") -> X | H15: X | J15: X | O15: X | S15: X
A16: https://doi.org/10.1145/3717511.3747073 | B16: 10.1145/3717511.3747073 | C16: Interactive Social Agent Behaviors of Politeness and Compromise in Collaborative Decision-making | D16: Ceren | E16: =IF(AND(COUNTIF(F16:J16,"X")>0,COUNTIF(K16:O16,"X")>0,COUNTIF(P16:T16,"X")>0),"X","") -> X | F16: X | L16: X | O16: X | T16: X
A17: https://doi.org/10.1145/3719160.3736618 | B17: 10.1145/3719160.3736618 | C17: Navigating the Fog: How University Students Recalibrate Sensemaking Practices to Address Plausible Falsehoods in LLM Outputs | D17: Marilyn | E17: =IF(AND(COUNTIF(F17:J17,"X")>0,COUNTIF(K17:O17,"X")>0,COUNTIF(P17:T17,"X")>0),"X","") -> X | G17: X | N17: X | Q17: X | R17: X
A18: https://doi.org/10.1145/3742413.3789120 | B18: 10.1145/3742413.3789120 | C18: Neural Transparency: Mechanistic Interpretability Interfaces for Anticipating Model Behaviors for Personalized AI | D18: Ceren | E18: =IF(AND(COUNTIF(F18:J18,"X")>0,COUNTIF(K18:O18,"X")>0,COUNTIF(P18:T18,"X")>0),"X","") -> X | F18: X | J18: X | O18: X | R18: X | T18: X
A19: https://doi.org/10.1145/3744169.3744194 | B19: 10.1145/3744169.3744194 | C19: Reading the Praise/Prompt Machine: An Interface Criticism Approach to ChatGPT | D19: Tina | E19: =IF(AND(COUNTIF(F19:J19,"X")>0,COUNTIF(K19:O19,"X")>0,COUNTIF(P19:T19,"X")>0),"X","") -> X | I19: X | M19: X | O19: X | P19: X
A20: https://doi.org/10.1145/3746027.3755778 | B20: 10.1145/3746027.3755778 | C20: Evaluating and Mitigating Sycophancy in Large Vision-Language Models | D20: Marilyn | E20: =IF(AND(COUNTIF(F20:J20,"X")>0,COUNTIF(K20:O20,"X")>0,COUNTIF(P20:T20,"X")>0),"X","") -> X | I20: X | K20: X | N20: X | S20: X
A21: https://doi.org/10.1145/3772318.3790332 | B21: 10.1145/3772318.3790332 | C21: Behavioral Indicators of Overreliance During Interaction with Conversational Language Models | D21: Tina | E21: =IF(AND(COUNTIF(F21:J21,"X")>0,COUNTIF(K21:O21,"X")>0,COUNTIF(P21:T21,"X")>0),"X","") | R21: X | T21: X
A22: https://doi.org/10.1145/3772318.3790385 | B22: 10.1145/3772318.3790385 | C22: Understanding Compliance and Conversion Dynamics in Multi-Agent Collectives | D22: Tina | E22: =IF(AND(COUNTIF(F22:J22,"X")>0,COUNTIF(K22:O22,"X")>0,COUNTIF(P22:T22,"X")>0),"X","") -> X | F22: X | N22: X | O22: X | Q22: X | R22: X
A23: https://doi.org/10.1145/3772318.3790934 | B23: 10.1145/3772318.3790934 | C23: Does Sycophancy Change Decisions? Effect of LLM Sycophancy on AI-Assisted Decision-Making | D23: Tina | E23: =IF(AND(COUNTIF(F23:J23,"X")>0,COUNTIF(K23:O23,"X")>0,COUNTIF(P23:T23,"X")>0),"X","") -> X | F23: X | L23: X | M23: X | Q23: X | R23: X | T23: X
A24: https://doi.org/10.1145/3772318.3791079 | B24: 10.1145/3772318.3791079 | C24: Be Friendly | D24: Marilyn | E24: =IF(AND(COUNTIF(F24:J24,"X")>0,COUNTIF(K24:O24,"X")>0,COUNTIF(P24:T24,"X")>0),"X","") -> X | F24: X | M24: X | N24: X | Q24: X
A25: https://doi.org/10.1145/3772318.3791149 | B25: 10.1145/3772318.3791149 | C25: The Siren Song of LLMs: How Users Perceive and Respond to Dark Patterns in Large Language Models | D25: Cindy | E25: =IF(AND(COUNTIF(F25:J25,"X")>0,COUNTIF(K25:O25,"X")>0,COUNTIF(P25:T25,"X")>0),"X","") -> X | F25: X | L25: X | M25: X | Q25: X | R25: X
A26: https://doi.org/10.1145/3772318.3791233 | B26: 10.1145/3772318.3791233 | C26: When AI Gives Advice: Evaluating AI and Human Responses to Online Advice-Seeking for Well-Being | D26: Kaiser | E26: =IF(AND(COUNTIF(F26:J26,"X")>0,COUNTIF(K26:O26,"X")>0,COUNTIF(P26:T26,"X")>0),"X","") -> X | G26: X | H26: X | L26: X | Q26: X | S26: X
A27: https://doi.org/10.1145/3772318.3791300 | B27: 10.1145/3772318.3791300 | C27: All Accept | D27: Ceren | E27: =IF(AND(COUNTIF(F27:J27,"X")>0,COUNTIF(K27:O27,"X")>0,COUNTIF(P27:T27,"X")>0),"X","") -> X | H27: X | L27: X | S27: X
A28: https://doi.org/10.1145/3772318.3791365 | B28: 10.1145/3772318.3791365 | C28: Invisible Saboteurs: Sycophantic LLMs Mislead Novices in Problem-Solving Tasks | D28: Danni | E28: =IF(AND(COUNTIF(F28:J28,"X")>0,COUNTIF(K28:O28,"X")>0,COUNTIF(P28:T28,"X")>0),"X","") -> X | G28: X | O28: X | T28: X
A29: https://doi.org/10.1145/3772318.3791851 | B29: 10.1145/3772318.3791851 | C29: Personal Validation Effect in LLMs: Positive AI Responses Bias Perceptions of Validity | D29: Marilyn | E29: =IF(AND(COUNTIF(F29:J29,"X")>0,COUNTIF(K29:O29,"X")>0,COUNTIF(P29:T29,"X")>0),"X","") -> X | F29: X | L29: X | Q29: X
A30: https://doi.org/10.1145/3772318.3791915 | B30: 10.1145/3772318.3791915 | C30: Interaction Context Often Increases Sycophancy in LLMs | D30: Tina | E30: X | G30: X | L30: X | P30: X
A31: https://doi.org/10.1145/3772363.3798705 | B31: 10.1145/3772363.3798705 | C31: When AI Agrees | D31: Tina | E31: =IF(AND(COUNTIF(F31:J31,"X")>0,COUNTIF(K31:O31,"X")>0,COUNTIF(P31:T31,"X")>0),"X","") -> X | F31: X | L31: X | Q31: X
A32: https://doi.org/10.1145/3772363.3799334 | B32: 10.1145/3772363.3799334 | C32: Maintaining Stable Personas? Examining Temporal Stability in LLM-Based Human Simulation | D32: Jonathan | E32: =IF(AND(COUNTIF(F32:J32,"X")>0,COUNTIF(K32:O32,"X")>0,COUNTIF(P32:T32,"X")>0),"X","") -> X | I32: X | O32: X | S32: X
A33: https://doi.org/10.1145/3774904.3792506 | B33: 10.1145/3774904.3792506 | C33: Acting Flatterers via LLMs Sycophancy: Combating Clickbait with LLMs Opposing-Stance Reasoning | D33: Tina | E33: X | J33: X | L33: X | N33: X | S33: X
A34: https://doi.org/10.1145/3776734.3794532 | B34: 10.1145/3776734.3794532 | C34: Robotic Sycophancy: A Scoping Review | D34: Tina | E34: =IF(AND(COUNTIF(F34:J34,"X")>0,COUNTIF(K34:O34,"X")>0,COUNTIF(P34:T34,"X")>0),"X","") -> X | I34: X | L34: X | M34: X | O34: X | P34: X
A35: https://doi.org/10.1145/3786304.3787879 | B35: 10.1145/3786304.3787879 | C35: Confirmation | D35: Jonathan | E35: =IF(AND(COUNTIF(F35:J35,"X")>0,COUNTIF(K35:O35,"X")>0,COUNTIF(P35:T35,"X")>0),"X","") -> X | I35: X | L35: X | P35: X
A36: https://doi.org/10.1145/3786335.3813137 | B36: 10.1145/3786335.3813137 | C36: The Cost of Consensus: Isolated Self-Correction Prevails Over Unguided Homogeneous Multi-Agent Debate | D36: Marilyn | E36: =IF(AND(COUNTIF(F36:J36,"X")>0,COUNTIF(K36:O36,"X")>0,COUNTIF(P36:T36,"X")>0),"X","") -> X | I36: X | N36: X | S36: X
A37: https://doi.org/10.1145/3788646.3789536 | B37: 10.1145/3788646.3789536 | C37: AI-Assisted Moot Courts: Simulating Justice-Specific Questioning in Oral Arguments | D37: Cindy | E37: =IF(AND(COUNTIF(F37:J37,"X")>0,COUNTIF(K37:O37,"X")>0,COUNTIF(P37:T37,"X")>0),"X","") -> X | G37: X | J37: X | L37: X | O37: X | S37: X

Sheet Mapping Test
A1: URL | B1: Key | C1: Title | D1: Coder | E1: Population (Whos is doing the judging of sycophancy?) | K1: Definition of Sycophancy (what exactly do they mean by sycophancy) | Q1: Outcomes (Are they measuring the impact of sycophancy on something else?)
E2: Human - general | F2: Human - Student | G2: Human - Specialist | H2: Human - Authors | I2: AI - prompted | J2: Other | K2: Hallucination Agreement | L2: Bias Agreement | M2: Obsequiousness | N2: Stance Change | O2: Failure to challenge/trying to get along | P2: Other (Describe) | Q2: None | R2: User opinion | S2: User action | T2: System performance | U2: User performance | V2: Other (Describe)
E3: A human judge with no specific expertise | F3: Specifically having students judge | G3: Having someone with expertise (psychologist, conversation expert, etc) judge | H3: Authors judging | I3: Some sort of prompted AI doing the judging | J3: Describe | K3: Saying something objectively wrong/harmful becuase the user wants it to be so | L3: The LLM choosing something that isn't objectively wrong, but siding towards the version that it believes user would want | M3: Fawning or overly positive language | N3: Getting the LLM to change opinions/stance/viewpoint to please/mirror user | O3: LLM failing to push back or challenge user or just going along with user's suggestion despite potential problems | Q3: Just measuing sycophancy directly with no impact | R3: Measuring how users feel/react in some way | S3: Measuring something about how users behave while/after interacting with sycophantic LLMS | T3: Some measure of how sycophantic LLMs perform on some task | U3: Some measure of how well the user is able to accomplish a task with sycophantic/non-sycophantic agents
A4: https://doi.org/10.1145/3772318.3790332 | B4: 10.1145/3772318.3790332 | C4: Behavioral Indicators of Overreliance During Interaction with Conversational Language Models | D4: Ceren | E4: X | K4: X | M4: X | S4: X
A5: https://doi.org/10.1145/3772318.3790385 | B5: 10.1145/3772318.3790385 | C5: Understanding Compliance and Conversion Dynamics in Multi-Agent Collectives | D5: Ceren | E5: X | N5: X | R5: X | S5: X
A6: https://doi.org/10.1145/3772318.3790934 | B6: 10.1145/3772318.3790934 | C6: Does Sycophancy Change Decisions? Effect of LLM Sycophancy on AI-Assisted Decision-Making | D6: Cindy | E6: X | F6: X | M6: X | N6: X | R6: X | S6: X
A7: https://doi.org/10.1145/3772318.3791079 | B7: 10.1145/3772318.3791079 | C7: Be Friendly | D7: Cindy | E7: X | M7: X | N7: X | R7: X
A8: https://doi.org/10.1145/3772318.3791149 | B8: 10.1145/3772318.3791149 | C8: The Siren Song of LLMs: How Users Perceive and Respond to Dark Patterns in Large Language Models | D8: Danni | E8: X | K8: X | O8: X | R8: X
A9: https://doi.org/10.1145/3772318.3791233 | B9: 10.1145/3772318.3791233 | C9: When AI Gives Advice: Evaluating AI and Human Responses to Online Advice-Seeking for Well-Being | D9: Danni | G9: X | M9: X | O9: X | R9: X
A10: https://doi.org/10.1145/3772318.3791300 | B10: 10.1145/3772318.3791300 | C10: All Accept | D10: Jonathan | G10: X | L10: X | T10: X
A11: https://doi.org/10.1145/3772318.3791365 | B11: 10.1145/3772318.3791365 | C11: Invisible Saboteurs: Sycophantic LLMs Mislead Novices in Problem-Solving Tasks | D11: Jonathan | F11: X | L11: X | O11: X | U11: X
A12: https://doi.org/10.1145/3772318.3791600 | B12: 10.1145/3772318.3791600 | C12: Feedback by Design: Understanding and Overcoming User Feedback Barriers in Conversational Agents | D12: Kaiser
A13: https://doi.org/10.1145/3772318.3791851 | B13: 10.1145/3772318.3791851 | C13: Personal Validation Effect in LLMs: Positive AI Responses Bias Perceptions of Validity | D13: Kaiser | H13: X | M13: X | S13: X
A14: https://doi.org/10.1145/3772318.3791915 | B14: 10.1145/3772318.3791915 | C14: Interaction Context Often Increases Sycophancy in LLMs | D14: Marilyn | F14: X | I14: X | J14: (Participants judge perspective sycophancy, and LLM-judge used for agreement sycophancy) | M14: X | P14: Also mentions Perspective sycophancy: excessively mirroring a user’s perspective or viewpoint in responses | Q14: X
A15: https://doi.org/10.1145/3772363.3798705 | B15: 10.1145/3772363.3798705 | C15: When AI Agrees | D15: Marilyn | H15: X | M15: X | R15: X
A16: https://doi.org/10.1145/3772363.3799334 | B16: 10.1145/3772363.3799334 | C16: Maintaining Stable Personas? Examining Temporal Stability in LLM-Based Human Simulation | D16: Rudranil
A17: https://doi.org/10.1145/3774904.3792506 | B17: 10.1145/3774904.3792506 | C17: Acting Flatterers via LLMs Sycophancy: Combating Clickbait with LLMs Opposing-Stance Reasoning | D17: Rudranil
A18: https://doi.org/10.1145/3776734.3794532 | B18: 10.1145/3776734.3794532 | C18: Robotic Sycophancy: A Scoping Review | D18: Taylor | H18: X | K18: X | M18: X | N18: X | Q18: X
A19: https://doi.org/10.1145/3786304.3787879 | B19: 10.1145/3786304.3787879 | C19: Confirmation | D19: Taylor | G19: X | H19: X | K19: X | O19: X | Q19: X | U19: X
A20: https://doi.org/10.1145/3786335.3813137 | B20: 10.1145/3786335.3813137 | C20: The Cost of Consensus: Isolated Self-Correction Prevails Over Unguided Homogeneous Multi-Agent Debate | D20: Tina | I20: X | K20: X | L20: X | N20: X | T20: X
A21: https://doi.org/10.1145/3788646.3789536 | B21: 10.1145/3788646.3789536 | C21: AI-Assisted Moot Courts: Simulating Justice-Specific Questioning in Oral Arguments | D21: Tina | G21: X | I21: X | M21: X | O21: X | T21: X | U21: X

Sheet Category Clustering
A1: URL | B1: Key | C1: Title | D1: Coder | E1: Aspect of sycophancy | F1: Method of evaluation | G1: Circumstance | H1: Impact
E2: (What exactly are they measuring) | F2: (How are they measuring it) | G2: (Where/with whom are they measuring it) | H2: (Are they measuring the imact of sycophancy on something else)
A3: https://ieeexplore.ieee.org/stamp/stamp.jsp?arnumber=11449950 | B3: 10.1109/ICSEA.2007.67 | C3: Too Positive to Be True? Sentiment Analysis of AI-Guided vs. Human-Led Debriefings in Virtual Reality Counseling Training | D3: Kaiser | E3: How AI-guided debriefings differ from human debriefings in the context of VR counseling training | F3: Comparing the AI debriefings to human debriefings | G3: Google's BERT; Conversational Agents | H3: Somewhat talks about sycophancy in human debriefings
A4: https://ieeexplore.ieee.org/stamp/stamp.jsp?arnumber=10825538 | B4: 10.1145/3786335.3813137 | C4: Mitigating Sycophancy in Large Language Models via Direct Preference Optimization | D4: Kaiser | E4: Preference-driven sycophancy (when an LLM adapts its responses to align with the user’s expressed preferences or beliefs) and Persona-based sycophancy occurs when an LLM tailors its responses based on the perceived persona or identity of the user) | F4: LLMs are fine-tuned using a dataset specifically crafted to expose and mitigate sycophantic behavior, then Direct Preference Optimization (DPO) is applied to penalize incorrect and biased responses, reducing their likelihood during training | G4: LLMs (model not specified) | H4: N/A
A5: https://doi.org/10.1145/3703155 | B5: 10.1145/3715275.3732094 | C5: A Survey on Hallucination in Large Language Models: Principles | D5: Danni | E5: Proposes categorization of hallucination into two types (factuality and faithfulness hallucinations) and discusses their causes, detection, and mitigation | F5: Provides an overview of latest knowledge and developments in LLM hallucinations | G5: Survey of existing literature | H5: Mainly talks about hallucinations but briefly relates sycophancy to belief misalignment hallucinations and RLHF
A6: https://doi.org/10.1145/3719160.3736618 | B6: 10.1145/3772318.3791571 | C6: Navigating the Fog: How University Students Recalibrate Sensemaking Practices to Address Plausible Falsehoods in LLM Outputs | D6: Danni | E6: How students navigate LLM hallucinations (or LLM outputs containing plausible falsehoods) when performing academic tasks | F6: Qualitative analysis of students' thinking and actions observed from think-aloud tasks and retrospective interviews | G6: University students use ChatGPT to do research to answer a question and to give a summary and reflection for an article | H6: Somewhat discusses impact in how LLM sycophancy can cause confirmation bias and induce inconsistencies in responses
A7: https://doi.org/10.1145/3746027.3755778 | B7: 10.1109/ccgrid.2017.49 | C7: Evaluating and Mitigating Sycophancy in Large Vision-Language Models | D7: Marilyn
A8: https://doi.org/10.1145/3772318.3790332 | B8: 10.1145/3772318.3790303 | C8: Behavioral Indicators of Overreliance During Interaction with Conversational Language Models | D8: Marilyn
A9: https://doi.org/10.1145/3772318.3791079 | B9: 10.1145/28395.28431 | C9: Be Friendly | D9: Taylor | E9: How users interpret sycophancy | F9: Examining user responses | G9: Opinoned AIs? unsure how to word | H9: Also looks at over-agreeable people?
A10: https://doi.org/10.1145/3772318.3791300 | B10: 10.1145/3643834.3661525 | C10: All Accept | D10: Taylor | E10: How LLMs accept papers as peer reviewers | F10: Comparing to human evaluators | G10: OpenAI LLMs | H10: Not really?
A11: https://doi.org/10.1145/3772318.3791915 | B11: 10.1145/1823838.1823840 | C11: Interaction Context Often Increases Sycophancy in LLMs | D11: Cindy | E11: How user context affects sycophancy | F11: Agreement Sycophancy: use an LLM-judge(GPT-4o) to classify whether responses to the advice scenarios indicate any wrongdoing by the user Perspective Sycophancy: participants compare responses with and without their interation context and rate how closely each reflects their perspective. | G11: LLMs. (Claude, Gemimi, Llama, GPT) | H11: N/A
A12: https://doi.org/10.1145/3772363.3798705 | B12: 10.1145/3742413.3789218 | C12: When AI Agrees | D12: Cindy | E12: How cognitive congruent interventions may increase confidence and reduces depolarization in opinions | F12: Examining changes in confidence after interacting with AI/human agents using congruent, incongruent, or two-sided responses | G12: LLM (Gemini) and human agents | H12: Confidence in initial opinions
A13: https://doi.org/10.1145/3774904.3792506 | B13: 10.1145/3706598.3713408 | C13: Acting Flatterers via LLMs Sycophancy: Combating Clickbait with LLMs Opposing-Stance Reasoning
A14: https://doi.org/10.1145/3776734.3794532 | B14: 10.1145/332040.332406 | C14: Robotic Sycophancy: A Scoping Review

Sheet INCEXC Discrepancies
A1: URL | B1: Key A | C1: Key B | D1: Coder A | E1: Coder B | F1: Decision A | G1: Decision B | H1: Agreement
A2: ='INCEXC A'!A2 -> https://doi.org/10.1007/978-3-642-24322-6_15 | B2: ='INCEXC A'!B2 -> 10.1007/978-3-642-24322-6_15 | C2: ='INC/EXC B'!B2 -> #REF! | D2: ='INCEXC A'!D2 -> Jonathan | E2: ='INC/EXC B'!C2 -> #REF! | F2: ='INCEXC A'!E2 -> Exclude | G2: ='INC/EXC B'!D2 -> #REF! | H2: =G2=F2 -> #REF!
A3: ='INCEXC A'!A3 -> https://doi.org/10.1007/978-3-642-24322-6_16 | B3: ='INCEXC A'!B3 -> 10.1007/978-3-642-24322-6_16 | C3: ='INC/EXC B'!B3 -> #REF! | D3: ='INCEXC A'!D3 -> Marilyn | E3: ='INC/EXC B'!C3 -> #REF! | F3: ='INCEXC A'!E3 -> Exclude | G3: ='INC/EXC B'!D3 -> #REF! | H3: =G3=F3 -> #REF!
A4: ='INCEXC A'!A4 -> https://doi.org/10.1007/978-3-642-24322-6_19 | B4: ='INCEXC A'!B4 -> 10.1007/978-3-642-24322-6_19 | C4: ='INC/EXC B'!B4 -> #REF! | D4: ='INCEXC A'!D4 -> Marilyn | E4: ='INC/EXC B'!C4 -> #REF! | F4: ='INCEXC A'!E4 -> Exclude | G4: ='INC/EXC B'!D4 -> #REF! | H4: =G4=F4 -> #REF!
A5: ='INCEXC A'!A5 -> https://ieeexplore.ieee.org/stamp/stamp.jsp?arnumber=8372225 | B5: ='INCEXC A'!B5 -> 10.1049/cp.2016.1548 | C5: ='INC/EXC B'!B5 -> #REF! | D5: ='INCEXC A'!D5 -> Marilyn | E5: ='INC/EXC B'!C5 -> #REF! | F5: ='INCEXC A'!E5 -> Exclude | G5: ='INC/EXC B'!D5 -> #REF! | H5: =G5=F5 -> #REF!
A6: ='INCEXC A'!A6 -> https://ieeexplore.ieee.org/stamp/stamp.jsp?arnumber=735370 | B6: ='INCEXC A'!B6 -> 10.1109/47.735370 | C6: ='INC/EXC B'!B6 -> #REF! | D6: ='INCEXC A'!D6 -> Jonathan | E6: ='INC/EXC B'!C6 -> #REF! | F6: ='INCEXC A'!E6 -> Exclude | G6: ='INC/EXC B'!D6 -> #REF! | H6: =G6=F6 -> #REF!
A7: ='INCEXC A'!A7 -> https://ieeexplore.ieee.org/stamp/stamp.jsp?arnumber=11467909 | B7: ='INCEXC A'!B7 -> 10.1109/ACDSA67686.2026.11467909 | C7: ='INC/EXC B'!B7 -> #REF! | D7: ='INCEXC A'!D7 -> Marilyn | E7: ='INC/EXC B'!C7 -> #REF! | F7: ='INCEXC A'!E7 -> Include | G7: ='INC/EXC B'!D7 -> #REF! | H7: =G7=F7 -> #REF!
A8: ='INCEXC A'!A8 -> https://ieeexplore.ieee.org/stamp/stamp.jsp?arnumber=10771051 | B8: ='INCEXC A'!B8 -> 10.1109/AIxSET62544.2024.00047 | C8: ='INC/EXC B'!B8 -> #REF! | D8: ='INCEXC A'!D8 -> Kaiser | E8: ='INC/EXC B'!C8 -> #REF! | F8: ='INCEXC A'!E8 -> Exclude | G8: ='INC/EXC B'!D8 -> #REF! | H8: =G8=F8 -> #REF!
A9: ='INCEXC A'!A9 -> https://ieeexplore.ieee.org/stamp/stamp.jsp?arnumber=11449950 | B9: ='INCEXC A'!B9 -> 10.1109/AIxVR67263.2026.00026 | C9: ='INC/EXC B'!B9 -> #REF! | D9: ='INCEXC A'!D9 -> Kaiser | E9: ='INC/EXC B'!C9 -> #REF! | F9: ='INCEXC A'!E9 -> Include | G9: ='INC/EXC B'!D9 -> #REF! | H9: =G9=F9 -> #REF!
A10: ='INCEXC A'!A10 -> https://ieeexplore.ieee.org/stamp/stamp.jsp?arnumber=11334577 | B10: ='INCEXC A'!B10 -> 10.1109/ASE63991.2025.00043 | C10: ='INC/EXC B'!B10 -> #REF! | D10: ='INCEXC A'!D10 -> Kaiser | E10: ='INC/EXC B'!C10 -> #REF! | F10: ='INCEXC A'!E10 -> Exclude | G10: ='INC/EXC B'!D10 -> #REF! | H10: =G10=F10 -> #REF!
A11: ='INCEXC A'!A11 -> https://ieeexplore.ieee.org/stamp/stamp.jsp?arnumber=9381292 | B11: ='INCEXC A'!B11 -> 10.1109/ASONAM49781.2020.9381292 | C11: ='INC/EXC B'!B11 -> #REF! | D11: ='INCEXC A'!D11 -> Jonathan | E11: ='INC/EXC B'!C11 -> #REF! | F11: ='INCEXC A'!E11 -> Exclude | G11: ='INC/EXC B'!D11 -> #REF! | H11: =G11=F11 -> #REF!
A12: ='INCEXC A'!A12 -> https://doi.org/10.1109/ASONAM49781.2020.9381292 | B12: ='INCEXC A'!B12 -> 10.1109/asonam49781.2020.9381292 | C12: ='INC/EXC B'!B12 -> #REF! | D12: ='INCEXC A'!D12 -> Marilyn | E12: ='INC/EXC B'!C12 -> #REF! | F12: ='INCEXC A'!E12 -> Exclude | G12: ='INC/EXC B'!D12 -> #REF! | H12: =G12=F12 -> #REF!
A13: ='INCEXC A'!A13 -> https://ieeexplore.ieee.org/stamp/stamp.jsp?arnumber=10825538 | B13: ='INCEXC A'!B13 -> 10.1109/BigData62323.2024.10825538 | C13: ='INC/EXC B'!B13 -> #REF! | D13: ='INCEXC A'!D13 -> Kaiser | E13: ='INC/EXC B'!C13 -> #REF! | F13: ='INCEXC A'!E13 -> Include | G13: ='INC/EXC B'!D13 -> #REF! | H13: =G13=F13 -> #REF!
... A51: ='INCEXC A'!A51 -> https://doi.org/10.1145/122153.122160 | B51: ='INCEXC A'!B51 -> 10.1145/122153.122160 | C51: ='INC/EXC B'!B51 -> #REF! | D51: ='INCEXC A'!D51 -> Jonathan | E51: ='INC/EXC B'!C51 -> #REF! | F51: ='INCEXC A'!E51 -> Exclude | G51: ='INC/EXC B'!D51 -> #REF! | H51: =G51=F51 -> #REF!

Sheet Copy of INCEXC A
A1: URL | B1: key | D1: Evaluator Name | E1: Included/Excluded | F1: Excluded Reason | G1: Other
A2: https://doi.org/10.1007/978-3-642-24322-6_15 | B2: 10.1007/978-3-642-24322-6_15 | C2: The search for energy-efficient building blocks for the data center | D2: Jonathan
A3: https://doi.org/10.1007/978-3-642-24322-6_16 | B3: 10.1007/978-3-642-24322-6_16 | C3: KnightShift: shifting the I/O burden in datacenters to management processor for energy efficiency | D3: Marilyn | E3: Exclude | F3: Not about either LLMs or Sycophancy
A4: https://doi.org/10.1007/978-3-642-24322-6_19 | B4: 10.1007/978-3-642-24322-6_19 | C4: Achieving power-efficiency in clusters without distributed file system complexity | D4: Marilyn | E4: Exclude | F4: Not about either LLMs or Sycophancy
A5: https://ieeexplore.ieee.org/stamp/stamp.jsp?arnumber=8372225 | B5: 10.1049/cp.2016.1548 | C5: A SOFC based autonomous microgrid performance analysis using adaptive PI and PI controller | D5: Marilyn | E5: Exclude | F5: Not about either LLMs or Sycophancy
A6: https://ieeexplore.ieee.org/stamp/stamp.jsp?arnumber=735370 | B6: 10.1109/47.735370 | C6: The letter of submission: avoiding the promotional genre | D6: Jonathan
A7: https://ieeexplore.ieee.org/stamp/stamp.jsp?arnumber=11467909 | B7: 10.1109/ACDSA67686.2026.11467909 | C7: Evaluating LLM-Induced Investment Biases via Persona Design and Prompt Analysis: A Quantitative Study of Post-Retirement Asset Depletion Risk Through Social Simulation | D7: Marilyn | E7: Include | G7: Syncopancy in context of reinforcing individual investment biases
A8: https://ieeexplore.ieee.org/stamp/stamp.jsp?arnumber=10771051 | B8: 10.1109/AIxSET62544.2024.00047 | C8: Towards Transparent Artificial Intelligence: Exploring Modern Approaches and Future Directions | D8: Kaiser | E8: Exclude | F8: Not about Sycophancy
A9: https://ieeexplore.ieee.org/stamp/stamp.jsp?arnumber=11449950 | B9: 10.1109/AIxVR67263.2026.00026 | C9: Too Positive to Be True? Sentiment Analysis of AI-Guided vs. Human-Led Debriefings in Virtual Reality Counseling Training | D9: Kaiser | E9: Include
A10: https://ieeexplore.ieee.org/stamp/stamp.jsp?arnumber=11334577 | B10: 10.1109/ASE63991.2025.00043 | C10: Why AI Agents Still Need You: Findings from Developer-Agent Collaborations in the Wild | D10: Kaiser | E10: Exclude | F10: Not about Sycophancy
A11: https://ieeexplore.ieee.org/stamp/stamp.jsp?arnumber=9381292 | B11: 10.1109/ASONAM49781.2020.9381292 | C11: Aspect Based Abusive Sentiment Detection in Nepali Social Media Texts | D11: Jonathan
A12: https://doi.org/10.1109/ASONAM49781.2020.9381292 | B12: 10.1109/asonam49781.2020.9381292 | C12: Aspect based abusive sentiment detection in nepali social media texts | D12: Marilyn | E12: Exclude | F12: Not about Sycophancy
A13: https://ieeexplore.ieee.org/stamp/stamp.jsp?arnumber=10825538 | B13: 10.1109/BigData62323.2024.10825538 | C13: Mitigating Sycophancy in Large Language Models via Direct Preference Optimization | D13: Kaiser | E13: Include
A14: https://ieeexplore.ieee.org/stamp/stamp.jsp?arnumber=11400739 | B14: 10.1109/BigData66926.2025.11400739 | C14: Towards Uncertainty-Aware Low-Bit Quantized LLMs for On-Device Inference | D14: Kaiser | E14: Exclude | F14: Not about Sycophancy
A15: https://doi.org/10.1109/CCGrid.2012.84 | B15: 10.1109/ccgrid.2012.84 | C15: Energy- and Cost-Efficiency Analysis of ARM-Based Clusters | D15: Marilyn | E15: Exclude | F15: Not about either LLMs or Sycophancy
A16: https://doi.org/10.1109/CCGrid.2015.115 | B16: 10.1109/ccgrid.2015.115 | C16: Quantitative musings on the feasibility of smartphone clouds | D16: Jonathan
A17: https://doi.org/10.1109/CCGrid.2015.150 | B17: 10.1109/ccgrid.2015.150 | C17: Deferred lightweight indexing for log-structured key-value stores | D17: Jonathan
A18: https://doi.org/10.1109/CCGRID.2017.49 | B18: 10.1109/ccgrid.2017.49 | C18: High-Performance Key-Value Store On OpenSHMEM | D18: Kaiser | E18: Exclude | F18: Not about either LLMs or Sycophancy
A19: https://ieeexplore.ieee.org/stamp/stamp.jsp?arnumber=1554950 | B19: 10.1109/CEC.2005.1554950 | C19: Learning classifier systems for user context learning | D19: Jonathan
A20: https://ieeexplore.ieee.org/stamp/stamp.jsp?arnumber=11519295 | B20: 10.1109/GAIIS69281.2026.11519295 | C20: PI-Embedding: Scientific Idea Representation Learning via Citation Intent and Paper Provenance | D20: Jonathan
A21: https://ieeexplore.ieee.org/stamp/stamp.jsp?arnumber=10585495 | B21: 10.1109/GEM61861.2024.10585495 | C21: Leveraging Large Language Models for Enhanced VR Development: Insights and Challenges | D21: Marilyn | E21: Exclude | F21: Not about Sycophancy
A22: https://ieeexplore.ieee.org/stamp/stamp.jsp?arnumber=10590666 | B22: 10.1109/HPSC62738.2024.00012 | C22: Studying the Knowledge and Behavior of ChatGPT via Journey to the West | D22: Marilyn | E22: Exclude | F22: Not about Sycophancy
A23: https://ieeexplore.ieee.org/stamp/stamp.jsp?arnumber=11508939 | B23: 10.1109/ICAACE69793.2026.11508939 | C23: Tiny-Critic RAG: Empowering Agentic Fallback with Parameter-Efficient Small Language Models | D23: Jonathan
A24: https://ieeexplore.ieee.org/stamp/stamp.jsp?arnumber=11460702 | B24: 10.1109/ICASSP55912.2026.11460702 | C24: Towards Self-Evaluation of Sycophantic Hallucinations in Mathematical Reasoning | D24: Jonathan
A25: https://ieeexplore.ieee.org/stamp/stamp.jsp?arnumber=11462217 | B25: 10.1109/ICASSP55912.2026.11462217 | C25: FinLumen: A Game-Theoretic Multi-Agent Framework for Rational Portfolio Management | D25: Kaiser | E25: Exclude | F25: Not about Sycophancy
A26: https://ieeexplore.ieee.org/stamp/stamp.jsp?arnumber=5409737 | B26: 10.1109/ICASTECH.2009.5409737 | C26: Tracking a Sycophant Wireless Sensor Network for its seamless integration to mobile Wireless Sensor Networks | D26: Kaiser | E26: Exclude | F26: Not about LLMs
A27: https://ieeexplore.ieee.org/stamp/stamp.jsp?arnumber=6056911 | B27: 10.1109/ICECENG.2011.6056911 | C27: Cohesive subgroups analysis of asynchronous cognitive interactive network in collaborative learning | D27: Jonathan
A28: https://ieeexplore.ieee.org/stamp/stamp.jsp?arnumber=11521627 | B28: 10.1109/ICEIT68991.2026.11521627 | C28: The design of a GAI-supported research topic selection system for novice researchers: From the SECI perspective | D28: Marilyn | E28: Exclude | F28: Not about Sycophancy
A29: https://ieeexplore.ieee.org/stamp/stamp.jsp?arnumber=4299963 | B29: 10.1109/ICSEA.2007.67 | C29: Sycophant: An API for Research in Context-Aware User Interfaces | D29: Jonathan
A30: https://ieeexplore.ieee.org/stamp/stamp.jsp?arnumber=1431446 | B30: 10.1109/IRI.2004.1431446 | C30: Context learning can improve user interaction | D30: Kaiser | E30: Exclude | F30: Not about Sycophancy
A31: https://doi.org/10.1109/ISCA.2016.15 | B31: 10.1109/isca.2016.15 | C31: Morpheus: creating application objects efficiently for heterogeneous computing | D31: Marilyn | E31: Exclude | F31: Not about either LLMs or Sycophancy
A32: https://ieeexplore.ieee.org/stamp/stamp.jsp?arnumber=11269633 | B32: 10.1109/ISTAS65609.2025.11269633 | C32: AI Detection and Risk Estimation in Family Violence: Challenges and Governance | D32: Marilyn | E32: Exclude | F32: Not about either LLMs or Sycophancy
A33: https://ieeexplore.ieee.org/stamp/stamp.jsp?arnumber=4580542 | B33: 10.1109/MIS.2008.55 | C33: A Computational Approach to Etiquette: Operationalizing Brown and Levinson's Politeness Model | D33: Kaiser | E33: Exclude | F33: Not about Sycophancy
A34: https://ieeexplore.ieee.org/stamp/stamp.jsp?arnumber=11345775 | B34: 10.1109/NKCon66957.2025.11345775 | C34: Improving Argumentative Reasoning in LLMs Using Online Debates and Agent-Based Interaction | D34: Jonathan
A35: https://ieeexplore.ieee.org/stamp/stamp.jsp?arnumber=11037824 | B35: 10.1109/OJCS.2025.3580498 | C35: LLMs on a Budget: System-Level Approaches to Power-Efficient and Scalable Fine-Tuning | D35: Kaiser | E35: Exclude | F35: Not about Sycophancy
A36: https://ieeexplore.ieee.org/stamp/stamp.jsp?arnumber=11424465 | B36: 10.1109/RAMS50514.2026.11424465 | C36: Autonomous AI-Driven FMEA Optimization For Safety And Reliability In Healthcare | D36: Marilyn | E36: Exclude | F36: Not about either LLMs or Sycophancy
A37: https://doi.org/10.1109/SCW63240.2024.00017 | B37: 10.1109/SCW63240.2024.00017 | C37: SciTrust: Evaluating the Trustworthiness of Large Language Models for Science | D37: Jonathan
A38: https://ieeexplore.ieee.org/stamp/stamp.jsp?arnumber=10820709 | B38: 10.1109/SCW63240.2024.00017 | C38: SciTrust: Evaluating the Trustworthiness of Large Language Models for Science | D38: Marilyn | E38: Exclude | F38: Not about Sycophancy
A39: https://ieeexplore.ieee.org/stamp/stamp.jsp?arnumber=11531012 | B39: 10.1109/TDSC.2026.3695553 | C39: MCPXKIT: the Unified Toolkit for Analyzing Model Context Protocol Security | D39: Kaiser | E39: Exclude | F39: Not about Sycophancy
A40: https://ieeexplore.ieee.org/stamp/stamp.jsp?arnumber=5427110 | B40: 10.1109/TEVC.2009.2021466 | C40: XCS for Personalizing Desktop Interfaces | D40: Marilyn | E40: Exclude | F40: Not about either LLMs or Sycophancy
A41: https://doi.org/10.1109/TNET.2017.2669215 | B41: 10.1109/tnet.2017.2669215 | C41: CubicRing: Exploiting Network Proximity for Distributed In-Memory Key-Value Store | D41: Marilyn | E41: Exclude | F41: Not about either LLMs or Sycophancy
A42: https://ieeexplore.ieee.org/stamp/stamp.jsp?arnumber=11029593 | B42: 10.1109/TTS.2025.3573875 | C42: Emulated Empathy: Can Risks Be Countered by a Soft-Law Standard? | D42: Marilyn | E42: Exclude | F42: Not about Sycophancy | G42: Rather indirect (emulated empathy)
A43: https://ieeexplore.ieee.org/stamp/stamp.jsp?arnumber=11189226 | B43: 10.1109/UV63228.2024.11189226 | C43: Hallucination in Large Language Models: From Mechanistic Understanding to Novel Control Frameworks | D43: Marilyn | E43: Exclude | F43: Not about Sycophancy
A44: https://doi.org/10.1145/1037911.1037917 | B44: 10.1145/1037911.1037917 | C44: Fits and starts | D44: Marilyn | E44: Exclude | F44: Not a research paper
A45: https://doi.org/10.1145/1045264.1045265 | B45: 10.1145/1045264.1045265 | C45: Computer power and human reason | D45: Kaiser | E45: Exclude | F45: Not a research paper
A46: https://doi.org/10.1145/1088222.1088226 | B46: 10.1145/1088222.1088226 | C46: Some aspects of symbolic integration via predicate logic programming | D46: Kaiser | E46: Exclude | F46: Not about either LLMs or Sycophancy
A47: https://doi.org/10.1145/1120212.1120419 | B47: 10.1145/1120212.1120419 | C47: How users reciprocate to computers: an experiment that demonstrates behavior change | D47: Marilyn | E47: Exclude | F47: Not about either LLMs or Sycophancy
A48: https://doi.org/10.1145/1141880.1523452 | B48: 10.1145/1141880.1523452 | C48: Richard F. Hespos Interview: August 18-19 | D48: Jonathan
A49: https://doi.org/10.1145/1216295.1216357 | B49: 10.1145/1216295.1216357 | C49: User-context for adaptive user interfaces | D49: Marilyn | E49: Exclude | F49: Not about either LLMs or Sycophancy
A50: https://doi.org/10.1145/122153.122159 | B50: 10.1145/122153.122159 | C50: The senior seminar in computer science | D50: Jonathan
A51: https://doi.org/10.1145/122153.122160 | B51: 10.1145/122153.122160 | C51: The arcade laboratory: an environment to help teach algorithms | D51: Jonathan
A52: https://doi.org/10.1145/1274000.1274062 | B52: 10.1145/1274000.1274062 | C52: Cascaded generic XCS to learn about reminding preferences | D52: Jonathan
A53: https://doi.org/10.1145/1276958.1277335 | B53: 10.1145/1276958.1277335 | C53: XCS for adaptive user-interfaces | D53: Marilyn | E53: Exclude | F53: Not about either LLMs or Sycophancy
A54: https://doi.org/10.1145/1394669.1394689 | B54: 10.1145/1394669.1394689 | C54: Multi projector displays using a 3D compositing window manager | D54: Jonathan
A55: https://doi.org/10.1145/1409360.1409363 | B55: 10.1145/1409360.1409363 | C55: Apple builds great platforms | D55: Kaiser | E55: Exclude | F55: Not a research paper
A56: https://doi.org/10.1145/1450579.1450652 | B56: 10.1145/1450579.1450652 | C56: AVACHAT: a new comic-based chat system for virtual avatars | D56: Jonathan
A57: https://doi.org/10.1145/1477862.1477879 | B57: 10.1145/1477862.1477879 | C57: A new cognition-based chat system for avatar agents in virtual space | D57: Kaiser | E57: Exclude | F57: Not about either LLMs or Sycophancy
A58: https://doi.org/10.1145/1500175.1500178 | B58: 10.1145/1500175.1500178 | C58: RADCAP: an operational parallel processing facility | D58: Kaiser | E58: Exclude | F58: Not about either LLMs or Sycophancy
A59: https://doi.org/10.1145/1518701.1519021 | B59: 10.1145/1518701.1519021 | C59: I'm sorry | D59: Kaiser | E59: Exclude | F59: Not about Sycophancy
A60: https://doi.org/10.1145/1596685.1596827 | B60: 10.1145/1596685.1596827 | C60: Window pains | D60: Kaiser | E60: Exclude | F60: Not a research paper
A61: https://doi.org/10.1145/1621890.1621914 | B61: 10.1145/1621890.1621914 | C61: Dynamic web service orchestration applied to the device profile for web services in hierarchical networks | D61: Kaiser | E61: Exclude | F61: Not about either LLMs or Sycophancy
A62: https://doi.org/10.1145/1629575.1629577 | B62: 10.1145/1629575.1629577 | C62: FAWN: a fast array of wimpy nodes | D62: Jonathan
A63: https://doi.org/10.1145/1640089.1640127 | B63: 10.1145/1640089.1640127 | C63: Regrowing a language: refactoring tools allow programming languages to evolve | D63: Jonathan
A64: https://doi.org/10.1145/1740390.1740407 | B64: 10.1145/1740390.1740407 | C64: Low-power amdahl-balanced blades for data intensive computing | D64: Kaiser | E64: Exclude | F64: Not a research paper
A65: https://doi.org/10.1145/1740390.1740408 | B65: 10.1145/1740390.1740408 | C65: An energy case for hybrid datacenters | D65: Kaiser | E65: Exclude | F65: Not a research paper
A66: https://doi.org/10.1145/174690.174697 | B66: 10.1145/174690.174697 | C66: On Julius Caesar | D66: Jonathan
A67: https://doi.org/10.1145/175208.175220 | B67: 10.1145/175208.175220 | C67: Israel: of swords and software plowshares | D67: Marilyn | E67: Exclude | F67: Not a research paper
A68: https://doi.org/10.1145/1755913.1755916 | B68: 10.1145/1755913.1755916 | C68: Differential RAID: rethinking RAID for SSD reliability | D68: Kaiser | E68: Exclude | F68: Not about either LLMs or Sycophancy
A69: https://doi.org/10.1145/1791314.1791347 | B69: 10.1145/1791314.1791347 | C69: Energy-efficient cluster computing with FAWN: workloads and implications | D69: Marilyn | E69: Exclude | F69: Not about either LLMs or Sycophancy
A70: https://doi.org/10.1145/1807060.1807061 | B70: 10.1145/1807060.1807061 | C70: Differential RAID: Rethinking RAID for SSD reliability | D70: Kaiser | E70: Exclude | F70: Not about either LLMs or Sycophancy
A71: https://doi.org/10.1145/1807128.1807164 | B71: 10.1145/1807128.1807164 | C71: Robust and flexible power-proportional storage | D71: Marilyn | E71: Exclude | F71: Not about either LLMs or Sycophancy
A72: https://doi.org/10.1145/1807167.1807194 | B72: 10.1145/1807167.1807194 | C72: Analyzing the energy efficiency of a database server | D72: Jonathan
A73: https://doi.org/10.1145/1807167.1807324 | B73: 10.1145/1807167.1807324 | C73: Performing sound flash device measurements: some lessons from uFLIP | D73: Kaiser | E73: Exclude | F73: Not a research paper
A74: https://doi.org/10.1145/1809980.1810034 | B74: 10.1145/1809980.1810034 | C74: Um sistema web para acompanhar o crescimento e desenvolvimento do algodão | D74: Kaiser | E74: Exclude | F74: Not about either LLMs or Sycophancy
A75: https://doi.org/10.1145/1815961.1816002 | B75: 10.1145/1815961.1816002 | C75: Web search using mobile cores: quantifying and mitigating the price of efficiency | D75: Kaiser | E75: Exclude | F75: Not about either LLMs or Sycophancy
A76: https://doi.org/10.1145/1823838.1823840 | B76: 10.1145/1823838.1823840 | C76: Storage research in industry and universities | D76: Marilyn | E76: Exclude | F76: Not about either LLMs or Sycophancy
A77: https://doi.org/10.1145/1837915.1837918 | B77: 10.1145/1837915.1837918 | C77: Optimizing energy and performance for server-class file system workloads | D77: Marilyn | E77: Exclude | F77: Not about either LLMs or Sycophancy
A78: https://doi.org/10.1145/1839676.1839692 | B78: 10.1145/1839676.1839692 | C78: Keeping bits safe: how hard can it be? | D78: Jonathan
A79: https://doi.org/10.1145/1866029.1866078 | B79: 10.1145/1866029.1866078 | C79: Soylent: a word processor with a crowd inside | D79: Kaiser | E79: Exclude | F79: Not about either LLMs or Sycophancy
A80: https://doi.org/10.1145/1866296.1866298 | B80: 10.1145/1866296.1866298 | C80: Keeping Bits Safe: How Hard Can It Be? As storage systems grow larger and larger | D80: Kaiser | E80: Exclude | F80: Not about either LLMs or Sycophancy
A81: https://doi.org/10.1145/1899928.1899942 | B81: 10.1145/1899928.1899942 | C81: Enabling a marketplace of clouds: VMware's vCloud director | D81: Marilyn | E81: Exclude | F81: Not about either LLMs or Sycophancy
A82: https://doi.org/10.1145/1944862.1944886 | B82: 10.1145/1944862.1944886 | C82: SWEEP: evaluating computer system energy efficiency using synthetic workloads | D82: Kaiser | E82: Exclude | F82: Not about either LLMs or Sycophancy
A83: https://doi.org/10.1145/1945023.1945029 | B83: 10.1145/1945023.1945029 | C83: Challenges and opportunities for efficient computing with FAWN | D83: Kaiser | E83: Exclude | F83: Not about Sycophancy
A84: https://doi.org/10.1145/1965724.1965746 | B84: 10.1145/1965724.1965746 | C84: FAWN: a fast array of wimpy nodes: technical perspective | D84: Marilyn | E84: Exclude | F84: Not about either LLMs or Sycophancy
A85: https://doi.org/10.1145/1965724.1965747 | B85: 10.1145/1965724.1965747 | C85: FAWN: a fast array of wimpy nodes | D85: Kaiser | E85: Exclude | F85: Not about either LLMs or Sycophancy
A86: https://doi.org/10.1145/196734.196738 | B86: 10.1145/196734.196738 | C86: Finding a happy medium: explaining the negative effects of electronic communication on social life at work | D86: Marilyn | E86: Exclude | F86: Not about either LLMs or Sycophancy
A87: https://doi.org/10.1145/1978942.1979209 | B87: 10.1145/1978942.1979209 | C87: Evaluating longitudinal projects combining technology with temporal arts | D87: Jonathan
A88: https://doi.org/10.1145/1989323.1989327 | B88: 10.1145/1989323.1989327 | C88: SkimpyStash: RAM space skimpy key-value store on flash-based storage | D88: Kaiser | E88: Exclude | F88: Not about either LLMs or Sycophancy
A89: https://doi.org/10.1145/1989323.1989461 | B89: 10.1145/1989323.1989461 | C89: WattDB: an energy-proportional cluster of wimpy nodes | D89: Kaiser | E89: Exclude | F89: Not a research paper
A90: https://doi.org/10.1145/1995896.1995926 | B90: 10.1145/1995896.1995926 | C90: Optimizing the datacenter for data-centric workloads | D90: Kaiser | E90: Exclude | F90: Not about either LLMs or Sycophancy
A91: https://doi.org/10.1145/199688.199776 | B91: 10.1145/199688.199776 | C91: Inexpensive advanced graphics applications for the C.S. majors graphics class | D91: Marilyn | E91: Exclude | F91: Not about either LLMs or Sycophancy
A92: https://doi.org/10.1145/2003690.2003693 | B92: 10.1145/2003690.2003693 | C92: Mobile processors for energy-efficient web search | D92: Jonathan
A93: https://doi.org/10.1145/2018584.2018596 | B93: 10.1145/2018584.2018596 | C93: A reality check for content centric networking | D93: Kaiser | E93: Exclude | F93: Not about either LLMs or Sycophancy
A94: https://doi.org/10.1145/2038916.2038917 | B94: 10.1145/2038916.2038917 | C94: An efficient multi-tier tablet server storage architecture | D94: Jonathan
A95: https://doi.org/10.1145/2038916.2038939 | B95: 10.1145/2038916.2038939 | C95: Small cache | D95: Jonathan
A96: https://doi.org/10.1145/2043556.2043558 | B96: 10.1145/2043556.2043558 | C96: SILT: a memory-efficient | D96: Jonathan
A97: https://doi.org/10.1145/2043556.2043593 | B97: 10.1145/2043556.2043593 | C97: Don't settle for eventual: scalable causal consistency for wide-area storage with COPS | D97: Jonathan
A98: https://doi.org/10.1145/2107502.2107511 | B98: 10.1145/2107502.2107511 | C98: The hare and the tortoise: taming wireless losses by exploiting wired reliability | D98: Marilyn | E98: Exclude | F98: Not about either LLMs or Sycophancy
A99: https://doi.org/10.1145/2110205.2110209 | B99: 10.1145/2110205.2110209 | C99: Using active NVRAM for I/O staging | D99: Kaiser | E99: Exclude | F99: Not about either LLMs or Sycophancy
A100: https://doi.org/10.1145/2124295.2124300 | B100: 10.1145/2124295.2124300 | C100: Auralist: introducing serendipity into music recommendation | D100: Kaiser | E100: Exclude | F100: Not about either LLMs or Sycophancy
...

Sheet Copy of INCEXC B
A1: URL | B1: =E2 -> Exclude | D1: Evaluator Name | E1: Included/Excluded | F1: Excluded Reason | G1: Other
A2: https://doi.org/10.1007/978-3-642-24322-6_15 | B2: 10.1007/978-3-642-24322-6_15 | C2: The search for energy-efficient building blocks for the data center | D2: Taylor | E2: Exclude | F2: Not about either LLMs or Sycophancy
A3: https://doi.org/10.1007/978-3-642-24322-6_16 | B3: 10.1007/978-3-642-24322-6_16 | C3: KnightShift: shifting the I/O burden in datacenters to management processor for energy efficiency | D3: Taylor | E3: Exclude | F3: Not about either LLMs or Sycophancy
A4: https://doi.org/10.1007/978-3-642-24322-6_19 | B4: 10.1007/978-3-642-24322-6_19 | C4: Achieving power-efficiency in clusters without distributed file system complexity | D4: Taylor | E4: Exclude | F4: Not about either LLMs or Sycophancy
A5: https://ieeexplore.ieee.org/stamp/stamp.jsp?arnumber=8372225 | B5: 10.1049/cp.2016.1548 | C5: A SOFC based autonomous microgrid performance analysis using adaptive PI and PI controller | D5: Danni | E5: Exclude | F5: Not about either LLMs or Sycophancy
A6: https://ieeexplore.ieee.org/stamp/stamp.jsp?arnumber=735370 | B6: 10.1109/47.735370 | C6: The letter of submission: avoiding the promotional genre | D6: Ceren
A7: https://ieeexplore.ieee.org/stamp/stamp.jsp?arnumber=11467909 | B7: 10.1109/ACDSA67686.2026.11467909 | C7: Evaluating LLM-Induced Investment Biases via Persona Design and Prompt Analysis: A Quantitative Study of Post-Retirement Asset Depletion Risk Through Social Simulation | D7: Ceren
A8: https://ieeexplore.ieee.org/stamp/stamp.jsp?arnumber=10771051 | B8: 10.1109/AIxSET62544.2024.00047 | C8: Towards Transparent Artificial Intelligence: Exploring Modern Approaches and Future Directions | D8: Danni | E8: Exclude | F8: Not about Sycophancy
A9: https://ieeexplore.ieee.org/stamp/stamp.jsp?arnumber=11449950 | B9: 10.1109/AIxVR67263.2026.00026 | C9: Too Positive to Be True? Sentiment Analysis of AI-Guided vs. Human-Led Debriefings in Virtual Reality Counseling Training | D9: Taylor | E9: Include
A10: https://ieeexplore.ieee.org/stamp/stamp.jsp?arnumber=11334577 | B10: 10.1109/ASE63991.2025.00043 | C10: Why AI Agents Still Need You: Findings from Developer-Agent Collaborations in the Wild | D10: Taylor | E10: Include | G10: Touches on it
A11: https://doi.org/10.1109/ASONAM49781.2020.9381292 | B11: 10.1109/asonam49781.2020.9381292 | C11: Aspect based abusive sentiment detection in nepali social media texts | D11: Danni | E11: Exclude | F11: Not about either LLMs or Sycophancy
A12: https://ieeexplore.ieee.org/stamp/stamp.jsp?arnumber=9381292 | B12: 10.1109/ASONAM49781.2020.9381292 | C12: Aspect Based Abusive Sentiment Detection in Nepali Social Media Texts | D12: Taylor | E12: Exclude | F12: Not about either LLMs or Sycophancy
A13: https://ieeexplore.ieee.org/stamp/stamp.jsp?arnumber=10825538 | B13: 10.1109/BigData62323.2024.10825538 | C13: Mitigating Sycophancy in Large Language Models via Direct Preference Optimization | D13: Taylor | E13: Include
A14: https://ieeexplore.ieee.org/stamp/stamp.jsp?arnumber=11400739 | B14: 10.1109/BigData66926.2025.11400739 | C14: Towards Uncertainty-Aware Low-Bit Quantized LLMs for On-Device Inference | D14: Ceren
A15: https://doi.org/10.1109/CCGrid.2012.84 | B15: 10.1109/ccgrid.2012.84 | C15: Energy- and Cost-Efficiency Analysis of ARM-Based Clusters | D15: Ceren
A16: https://doi.org/10.1109/CCGrid.2015.115 | B16: 10.1109/ccgrid.2015.115 | C16: Quantitative musings on the feasibility of smartphone clouds | D16: Taylor | E16: Exclude | F16: Not about either LLMs or Sycophancy
A17: https://doi.org/10.1109/CCGrid.2015.150 | B17: 10.1109/ccgrid.2015.150 | C17: Deferred lightweight indexing for log-structured key-value stores | D17: Danni | E17: Exclude | F17: Not about either LLMs or Sycophancy
A18: https://doi.org/10.1109/CCGRID.2017.49 | B18: 10.1109/ccgrid.2017.49 | C18: High-Performance Key-Value Store On OpenSHMEM | D18: Taylor | E18: Exclude | F18: Not about either LLMs or Sycophancy
A19: https://ieeexplore.ieee.org/stamp/stamp.jsp?arnumber=1554950 | B19: 10.1109/CEC.2005.1554950 | C19: Learning classifier systems for user context learning | D19: Taylor | E19: Exclude | F19: Not about either LLMs or Sycophancy
A20: https://ieeexplore.ieee.org/stamp/stamp.jsp?arnumber=11519295 | B20: 10.1109/GAIIS69281.2026.11519295 | C20: PI-Embedding: Scientific Idea Representation Learning via Citation Intent and Paper Provenance | D20: Ceren
A21: https://ieeexplore.ieee.org/stamp/stamp.jsp?arnumber=10585495 | B21: 10.1109/GEM61861.2024.10585495 | C21: Leveraging Large Language Models for Enhanced VR Development: Insights and Challenges | D21: Taylor | E21: Exclude | F21: Not about Sycophancy
A22: https://ieeexplore.ieee.org/stamp/stamp.jsp?arnumber=10590666 | B22: 10.1109/HPSC62738.2024.00012 | C22: Studying the Knowledge and Behavior of ChatGPT via Journey to the West | D22: Ceren
A23: https://ieeexplore.ieee.org/stamp/stamp.jsp?arnumber=11508939 | B23: 10.1109/ICAACE69793.2026.11508939 | C23: Tiny-Critic RAG: Empowering Agentic Fallback with Parameter-Efficient Small Language Models | D23: Taylor | E23: Exclude | F23: Not about Sycophancy
A24: https://ieeexplore.ieee.org/stamp/stamp.jsp?arnumber=11460702 | B24: 10.1109/ICASSP55912.2026.11460702 | C24: Towards Self-Evaluation of Sycophantic Hallucinations in Mathematical Reasoning | D24: Danni | E24: Include
A25: https://ieeexplore.ieee.org/stamp/stamp.jsp?arnumber=11462217 | B25: 10.1109/ICASSP55912.2026.11462217 | C25: FinLumen: A Game-Theoretic Multi-Agent Framework for Rational Portfolio Management | D25: Ceren
A26: https://ieeexplore.ieee.org/stamp/stamp.jsp?arnumber=5409737 | B26: 10.1109/ICASTECH.2009.5409737 | C26: Tracking a Sycophant Wireless Sensor Network for its seamless integration to mobile Wireless Sensor Networks | D26: Danni | E26: Exclude | F26: Not about either LLMs or Sycophancy
A27: https://ieeexplore.ieee.org/stamp/stamp.jsp?arnumber=6056911 | B27: 10.1109/ICECENG.2011.6056911 | C27: Cohesive subgroups analysis of asynchronous cognitive interactive network in collaborative learning | D27: Danni | E27: Exclude | F27: Not about either LLMs or Sycophancy
A28: https://ieeexplore.ieee.org/stamp/stamp.jsp?arnumber=11521627 | B28: 10.1109/ICEIT68991.2026.11521627 | C28: The design of a GAI-supported research topic selection system for novice researchers: From the SECI perspective | D28: Danni | E28: Exclude | F28: Not about Sycophancy
A29: https://ieeexplore.ieee.org/stamp/stamp.jsp?arnumber=4299963 | B29: 10.1109/ICSEA.2007.67 | C29: Sycophant: An API for Research in Context-Aware User Interfaces | D29: Danni | E29: Exclude | F29: Not about either LLMs or Sycophancy
A30: https://ieeexplore.ieee.org/stamp/stamp.jsp?arnumber=1431446 | B30: 10.1109/IRI.2004.1431446 | C30: Context learning can improve user interaction | D30: Danni | E30: Exclude | F30: Other (Explanation ->) | G30: Page not found
A31: https://doi.org/10.1109/ISCA.2016.15 | B31: 10.1109/isca.2016.15 | C31: Morpheus: creating application objects efficiently for heterogeneous computing | D31: Danni | E31: Exclude | F31: Not about either LLMs or Sycophancy
A32: https://ieeexplore.ieee.org/stamp/stamp.jsp?arnumber=11269633 | B32: 10.1109/ISTAS65609.2025.11269633 | C32: AI Detection and Risk Estimation in Family Violence: Challenges and Governance | D32: Danni | E32: Exclude | F32: Not about Sycophancy
A33: https://ieeexplore.ieee.org/stamp/stamp.jsp?arnumber=4580542 | B33: 10.1109/MIS.2008.55 | C33: A Computational Approach to Etiquette: Operationalizing Brown and Levinson's Politeness Model | D33: Danni | E33: Exclude | F33: Not about either LLMs or Sycophancy
A34: https://ieeexplore.ieee.org/stamp/stamp.jsp?arnumber=11345775 | B34: 10.1109/NKCon66957.2025.11345775 | C34: Improving Argumentative Reasoning in LLMs Using Online Debates and Agent-Based Interaction | D34: Danni | E34: Exclude | F34: Not about Sycophancy
A35: https://ieeexplore.ieee.org/stamp/stamp.jsp?arnumber=11037824 | B35: 10.1109/OJCS.2025.3580498 | C35: LLMs on a Budget: System-Level Approaches to Power-Efficient and Scalable Fine-Tuning | D35: Ceren
A36: https://ieeexplore.ieee.org/stamp/stamp.jsp?arnumber=11424465 | B36: 10.1109/RAMS50514.2026.11424465 | C36: Autonomous AI-Driven FMEA Optimization For Safety And Reliability In Healthcare | D36: Taylor | E36: Include
A37: https://doi.org/10.1109/SCW63240.2024.00017 | B37: 10.1109/SCW63240.2024.00017 | C37: SciTrust: Evaluating the Trustworthiness of Large Language Models for Science | D37: Danni | E37: Include
A38: https://ieeexplore.ieee.org/stamp/stamp.jsp?arnumber=10820709 | B38: 10.1109/SCW63240.2024.00017 | C38: SciTrust: Evaluating the Trustworthiness of Large Language Models for Science | D38: Ceren
A39: https://ieeexplore.ieee.org/stamp/stamp.jsp?arnumber=11531012 | B39: 10.1109/TDSC.2026.3695553 | C39: MCPXKIT: the Unified Toolkit for Analyzing Model Context Protocol Security | D39: Ceren
A40: https://ieeexplore.ieee.org/stamp/stamp.jsp?arnumber=5427110 | B40: 10.1109/TEVC.2009.2021466 | C40: XCS for Personalizing Desktop Interfaces | D40: Ceren | E40: Exclude | F40: Not about either LLMs or Sycophancy
A41: https://doi.org/10.1109/TNET.2017.2669215 | B41: 10.1109/tnet.2017.2669215 | C41: CubicRing: Exploiting Network Proximity for Distributed In-Memory Key-Value Store | D41: Ceren | E41: Exclude | F41: Not about either LLMs or Sycophancy
A42: https://ieeexplore.ieee.org/stamp/stamp.jsp?arnumber=11029593 | B42: 10.1109/TTS.2025.3573875 | C42: Emulated Empathy: Can Risks Be Countered by a Soft-Law Standard? | D42: Ceren
A43: https://ieeexplore.ieee.org/stamp/stamp.jsp?arnumber=11189226 | B43: 10.1109/UV63228.2024.11189226 | C43: Hallucination in Large Language Models: From Mechanistic Understanding to Novel Control Frameworks | D43: Danni | E43: Exclude | F43: Not about Sycophancy
A44: https://doi.org/10.1145/1037911.1037917 | B44: 10.1145/1037911.1037917 | C44: Fits and starts | D44: Ceren
A45: https://doi.org/10.1145/1045264.1045265 | B45: 10.1145/1045264.1045265 | C45: Computer power and human reason | D45: Danni | E45: Exclude | F45: Not a research paper
A46: https://doi.org/10.1145/1088222.1088226 | B46: 10.1145/1088222.1088226 | C46: Some aspects of symbolic integration via predicate logic programming | D46: Ceren
A47: https://doi.org/10.1145/1120212.1120419 | B47: 10.1145/1120212.1120419 | C47: How users reciprocate to computers: an experiment that demonstrates behavior change | D47: Ceren
A48: https://doi.org/10.1145/1141880.1523452 | B48: 10.1145/1141880.1523452 | C48: Richard F. Hespos Interview: August 18-19 | D48: Taylor | E48: Exclude | F48: Not a research paper
A49: https://doi.org/10.1145/1216295.1216357 | B49: 10.1145/1216295.1216357 | C49: User-context for adaptive user interfaces | D49: Danni | E49: Exclude | F49: Not about either LLMs or Sycophancy
A50: https://doi.org/10.1145/122153.122159 | B50: 10.1145/122153.122159 | C50: The senior seminar in computer science | D50: Danni | E50: Exclude | F50: Not about either LLMs or Sycophancy
A51: https://doi.org/10.1145/122153.122160 | B51: 10.1145/122153.122160 | C51: The arcade laboratory: an environment to help teach algorithms | D51: Danni | E51: Exclude | F51: Not about either LLMs or Sycophancy
A52: https://doi.org/10.1145/1274000.1274062 | B52: 10.1145/1274000.1274062 | C52: Cascaded generic XCS to learn about reminding preferences | D52: Taylor | E52: Exclude | F52: Not about either LLMs or Sycophancy
A53: https://doi.org/10.1145/1276958.1277335 | B53: 10.1145/1276958.1277335 | C53: XCS for adaptive user-interfaces | D53: Taylor | E53: Exclude | F53: Not about either LLMs or Sycophancy
A54: https://doi.org/10.1145/1394669.1394689 | B54: 10.1145/1394669.1394689 | C54: Multi projector displays using a 3D compositing window manager | D54: Danni | E54: Exclude | F54: Not about either LLMs or Sycophancy
A55: https://doi.org/10.1145/1409360.1409363 | B55: 10.1145/1409360.1409363 | C55: Apple builds great platforms | D55: Taylor | E55: Exclude | F55: Not a research paper | G55: No abstract
A56: https://doi.org/10.1145/1450579.1450652 | B56: 10.1145/1450579.1450652 | C56: AVACHAT: a new comic-based chat system for virtual avatars | D56: Ceren
A57: https://doi.org/10.1145/1477862.1477879 | B57: 10.1145/1477862.1477879 | C57: A new cognition-based chat system for avatar agents in virtual space | D57: Danni | E57: Exclude | F57: Not about either LLMs or Sycophancy
A58: https://doi.org/10.1145/1500175.1500178 | B58: 10.1145/1500175.1500178 | C58: RADCAP: an operational parallel processing facility | D58: Danni | E58: Exclude | F58: Not about either LLMs or Sycophancy
A59: https://doi.org/10.1145/1518701.1519021 | B59: 10.1145/1518701.1519021 | C59: I'm sorry | D59: Taylor | E59: Include
A60: https://doi.org/10.1145/1596685.1596827 | B60: 10.1145/1596685.1596827 | C60: Window pains | D60: Danni | E60: Exclude | F60: Not about either LLMs or Sycophancy
A61: https://doi.org/10.1145/1621890.1621914 | B61: 10.1145/1621890.1621914 | C61: Dynamic web service orchestration applied to the device profile for web services in hierarchical networks | D61: Danni | E61: Exclude | F61: Not about either LLMs or Sycophancy
A62: https://doi.org/10.1145/1629575.1629577 | B62: 10.1145/1629575.1629577 | C62: FAWN: a fast array of wimpy nodes | D62: Danni | E62: Exclude | F62: Not about either LLMs or Sycophancy
A63: https://doi.org/10.1145/1640089.1640127 | B63: 10.1145/1640089.1640127 | C63: Regrowing a language: refactoring tools allow programming languages to evolve | D63: Taylor | E63: Exclude | F63: Not about either LLMs or Sycophancy
A64: https://doi.org/10.1145/1740390.1740407 | B64: 10.1145/1740390.1740407 | C64: Low-power amdahl-balanced blades for data intensive computing | D64: Ceren
A65: https://doi.org/10.1145/1740390.1740408 | B65: 10.1145/1740390.1740408 | C65: An energy case for hybrid datacenters | D65: Danni | E65: Exclude | F65: Not about either LLMs or Sycophancy
A66: https://doi.org/10.1145/174690.174697 | B66: 10.1145/174690.174697 | C66: On Julius Caesar | D66: Danni | E66: Exclude | F66: Not about either LLMs or Sycophancy
A67: https://doi.org/10.1145/175208.175220 | B67: 10.1145/175208.175220 | C67: Israel: of swords and software plowshares | D67: Taylor | E67: Exclude | F67: Not about either LLMs or Sycophancy | G67: Also genuinely what did i just see
A68: https://doi.org/10.1145/1755913.1755916 | B68: 10.1145/1755913.1755916 | C68: Differential RAID: rethinking RAID for SSD reliability | D68: Taylor | E68: Exclude | F68: Not about either LLMs or Sycophancy
A69: https://doi.org/10.1145/1791314.1791347 | B69: 10.1145/1791314.1791347 | C69: Energy-efficient cluster computing with FAWN: workloads and implications | D69: Danni | E69: Exclude | F69: Not about either LLMs or Sycophancy
A70: https://doi.org/10.1145/1807060.1807061 | B70: 10.1145/1807060.1807061 | C70: Differential RAID: Rethinking RAID for SSD reliability | D70: Danni | E70: Exclude | F70: Not about either LLMs or Sycophancy
A71: https://doi.org/10.1145/1807128.1807164 | B71: 10.1145/1807128.1807164 | C71: Robust and flexible power-proportional storage | D71: Taylor | E71: Exclude | F71: Not about either LLMs or Sycophancy
A72: https://doi.org/10.1145/1807167.1807194 | B72: 10.1145/1807167.1807194 | C72: Analyzing the energy efficiency of a database server | D72: Danni | E72: Exclude | F72: Not about either LLMs or Sycophancy
A73: https://doi.org/10.1145/1807167.1807324 | B73: 10.1145/1807167.1807324 | C73: Performing sound flash device measurements: some lessons from uFLIP | D73: Taylor | E73: Exclude | F73: Not about either LLMs or Sycophancy
A74: https://doi.org/10.1145/1809980.1810034 | B74: 10.1145/1809980.1810034 | C74: Um sistema web para acompanhar o crescimento e desenvolvimento do algodão | D74: Taylor | E74: Exclude | F74: Not about either LLMs or Sycophancy
A75: https://doi.org/10.1145/1815961.1816002 | B75: 10.1145/1815961.1816002 | C75: Web search using mobile cores: quantifying and mitigating the price of efficiency | D75: Danni | E75: Exclude | F75: Not about either LLMs or Sycophancy
A76: https://doi.org/10.1145/1823838.1823840 | B76: 10.1145/1823838.1823840 | C76: Storage research in industry and universities | D76: Taylor | E76: Exclude | F76: Not about either LLMs or Sycophancy
A77: https://doi.org/10.1145/1837915.1837918 | B77: 10.1145/1837915.1837918 | C77: Optimizing energy and performance for server-class file system workloads | D77: Ceren
A78: https://doi.org/10.1145/1839676.1839692 | B78: 10.1145/1839676.1839692 | C78: Keeping bits safe: how hard can it be? | D78: Taylor | E78: Exclude | F78: Not about either LLMs or Sycophancy
A79: https://doi.org/10.1145/1866029.1866078 | B79: 10.1145/1866029.1866078 | C79: Soylent: a word processor with a crowd inside | D79: Ceren
A80: https://doi.org/10.1145/1866296.1866298 | B80: 10.1145/1866296.1866298 | C80: Keeping Bits Safe: How Hard Can It Be? As storage systems grow larger and larger | D80: Ceren
A81: https://doi.org/10.1145/1899928.1899942 | B81: 10.1145/1899928.1899942 | C81: Enabling a marketplace of clouds: VMware's vCloud director | D81: Ceren
A82: https://doi.org/10.1145/1944862.1944886 | B82: 10.1145/1944862.1944886 | C82: SWEEP: evaluating computer system energy efficiency using synthetic workloads | D82: Taylor | E82: Exclude | F82: Not about either LLMs or Sycophancy
A83: https://doi.org/10.1145/1945023.1945029 | B83: 10.1145/1945023.1945029 | C83: Challenges and opportunities for efficient computing with FAWN | D83: Danni | E83: Exclude | F83: Not about either LLMs or Sycophancy
A84: https://doi.org/10.1145/1965724.1965746 | B84: 10.1145/1965724.1965746 | C84: FAWN: a fast array of wimpy nodes: technical perspective | D84: Taylor | E84: Exclude | F84: Other (Explanation ->) | G84: No abstract
A85: https://doi.org/10.1145/1965724.1965747 | B85: 10.1145/1965724.1965747 | C85: FAWN: a fast array of wimpy nodes | D85: Ceren
A86: https://doi.org/10.1145/196734.196738 | B86: 10.1145/196734.196738 | C86: Finding a happy medium: explaining the negative effects of electronic communication on social life at work | D86: Ceren
A87: https://doi.org/10.1145/1978942.1979209 | B87: 10.1145/1978942.1979209 | C87: Evaluating longitudinal projects combining technology with temporal arts | D87: Ceren
A88: https://doi.org/10.1145/1989323.1989327 | B88: 10.1145/1989323.1989327 | C88: SkimpyStash: RAM space skimpy key-value store on flash-based storage | D88: Danni | E88: Exclude | F88: Not about either LLMs or Sycophancy
A89: https://doi.org/10.1145/1989323.1989461 | B89: 10.1145/1989323.1989461 | C89: WattDB: an energy-proportional cluster of wimpy nodes | D89: Taylor | E89: Exclude | F89: Not about either LLMs or Sycophancy
A90: https://doi.org/10.1145/1995896.1995926 | B90: 10.1145/1995896.1995926 | C90: Optimizing the datacenter for data-centric workloads | D90: Ceren
A91: https://doi.org/10.1145/199688.199776 | B91: 10.1145/199688.199776 | C91: Inexpensive advanced graphics applications for the C.S. majors graphics class | D91: Danni | E91: Exclude | F91: Not about either LLMs or Sycophancy
A92: https://doi.org/10.1145/2003690.2003693 | B92: 10.1145/2003690.2003693 | C92: Mobile processors for energy-efficient web search | D92: Ceren
A93: https://doi.org/10.1145/2018584.2018596 | B93: 10.1145/2018584.2018596 | C93: A reality check for content centric networking | D93: Taylor | E93: Exclude | F93: Not about either LLMs or Sycophancy
A94: https://doi.org/10.1145/2038916.2038917 | B94: 10.1145/2038916.2038917 | C94: An efficient multi-tier tablet server storage architecture | D94: Taylor | E94: Exclude | F94: Not about either LLMs or Sycophancy
A95: https://doi.org/10.1145/2038916.2038939 | B95: 10.1145/2038916.2038939 | C95: Small cache | D95: Ceren
A96: https://doi.org/10.1145/2043556.2043558 | B96: 10.1145/2043556.2043558 | C96: SILT: a memory-efficient | D96: Ceren
A97: https://doi.org/10.1145/2043556.2043593 | B97: 10.1145/2043556.2043593 | C97: Don't settle for eventual: scalable causal consistency for wide-area storage with COPS | D97: Ceren
A98: https://doi.org/10.1145/2107502.2107511 | B98: 10.1145/2107502.2107511 | C98: The hare and the tortoise: taming wireless losses by exploiting wired reliability | D98: Ceren
A99: https://doi.org/10.1145/2110205.2110209 | B99: 10.1145/2110205.2110209 | C99: Using active NVRAM for I/O staging | D99: Ceren
A100: https://doi.org/10.1145/2124295.2124300 | B100: 10.1145/2124295.2124300 | C100: Auralist: introducing serendipity into music recommendation | D100: Ceren
...

Sheet Discrepancies Early
C1: Matching | D1: Key | E1: Title | F1: Coder A | G1: Coder B | H1: Code A | I1: Code B | J1: Match | K1: Agreed in
A2: ='Copy of INCEXC A'!A2 -> https://doi.org/10.1007/978-3-642-24322-6_15 | B2: ='Copy of INCEXC B'!A2 -> https://doi.org/10.1007/978-3-642-24322-6_15 | C2: =A2=B2 -> TRUE | E2: ='Copy of INCEXC A'!C2 -> The search for energy-efficient building blocks for the data center | F2: ='Copy of INCEXC A'!D2 -> Jonathan | G2: ='Copy of INCEXC B'!D2 -> Taylor | H2: ='Copy of INCEXC A'!E2 | I2: ='Copy of INCEXC B'!E2 -> Exclude | J2: =H2=I2 -> FALSE | K2: =AND(H2="Include",J2) -> FALSE
A3: ='Copy of INCEXC A'!A3 -> https://doi.org/10.1007/978-3-642-24322-6_16 | B3: ='Copy of INCEXC B'!A3 -> https://doi.org/10.1007/978-3-642-24322-6_16 | C3: =A3=B3 -> TRUE | E3: ='Copy of INCEXC A'!C3 -> KnightShift: shifting the I/O burden in datacenters to management processor for energy efficiency | F3: ='Copy of INCEXC A'!D3 -> Marilyn | G3: ='Copy of INCEXC B'!D3 -> Taylor | H3: ='Copy of INCEXC A'!E3 -> Exclude | I3: ='Copy of INCEXC B'!E3 -> Exclude | J3: =H3=I3 -> TRUE | K3: =AND(H3="Include",J3) -> FALSE
A4: ='Copy of INCEXC A'!A4 -> https://doi.org/10.1007/978-3-642-24322-6_19 | B4: ='Copy of INCEXC B'!A4 -> https://doi.org/10.1007/978-3-642-24322-6_19 | C4: =A4=B4 -> TRUE | E4: ='Copy of INCEXC A'!C4 -> Achieving power-efficiency in clusters without distributed file system complexity | F4: ='Copy of INCEXC A'!D4 -> Marilyn | G4: ='Copy of INCEXC B'!D4 -> Taylor | H4: ='Copy of INCEXC A'!E4 -> Exclude | I4: ='Copy of INCEXC B'!E4 -> Exclude | J4: =H4=I4 -> TRUE | K4: =AND(H4="Include",J4) -> FALSE
A5: ='Copy of INCEXC A'!A5 -> https://ieeexplore.ieee.org/stamp/stamp.jsp?arnumber=8372225 | B5: ='Copy of INCEXC B'!A5 -> https://ieeexplore.ieee.org/stamp/stamp.jsp?arnumber=8372225 | C5: =A5=B5 -> TRUE | E5: ='Copy of INCEXC A'!C5 -> A SOFC based autonomous microgrid performance analysis using adaptive PI and PI controller | F5: ='Copy of INCEXC A'!D5 -> Marilyn | G5: ='Copy of INCEXC B'!D5 -> Danni | H5: ='Copy of INCEXC A'!E5 -> Exclude | I5: ='Copy of INCEXC B'!E5 -> Exclude | J5: =H5=I5 -> TRUE | K5: =AND(H5="Include",J5) -> FALSE
A6: ='Copy of INCEXC A'!A6 -> https://ieeexplore.ieee.org/stamp/stamp.jsp?arnumber=735370 | B6: ='Copy of INCEXC B'!A6 -> https://ieeexplore.ieee.org/stamp/stamp.jsp?arnumber=735370 | C6: =A6=B6 -> TRUE | E6: ='Copy of INCEXC A'!C6 -> The letter of submission: avoiding the promotional genre | F6: ='Copy of INCEXC A'!D6 -> Jonathan | G6: ='Copy of INCEXC B'!D6 -> Ceren | H6: ='Copy of INCEXC A'!E6 | I6: ='Copy of INCEXC B'!E6 | J6: =H6=I6 -> TRUE | K6: =AND(H6="Include",J6) -> FALSE
A7: ='Copy of INCEXC A'!A7 -> https://ieeexplore.ieee.org/stamp/stamp.jsp?arnumber=11467909 | B7: ='Copy of INCEXC B'!A7 -> https://ieeexplore.ieee.org/stamp/stamp.jsp?arnumber=11467909 | C7: =A7=B7 -> TRUE | E7: ='Copy of INCEXC A'!C7 -> Evaluating LLM-Induced Investment Biases via Persona Design and Prompt Analysis: A Quantitative Study of Post-Retirement Asset Depletion Risk Through Social Simulation | F7: ='Copy of INCEXC A'!D7 -> Marilyn | G7: ='Copy of INCEXC B'!D7 -> Ceren | H7: ='Copy of INCEXC A'!E7 -> Include | I7: ='Copy of INCEXC B'!E7 | J7: =H7=I7 -> FALSE | K7: =AND(H7="Include",J7) -> FALSE
A8: ='Copy of INCEXC A'!A8 -> https://ieeexplore.ieee.org/stamp/stamp.jsp?arnumber=10771051 | B8: ='Copy of INCEXC B'!A8 -> https://ieeexplore.ieee.org/stamp/stamp.jsp?arnumber=10771051 | C8: =A8=B8 -> TRUE | E8: ='Copy of INCEXC A'!C8 -> Towards Transparent Artificial Intelligence: Exploring Modern Approaches and Future Directions | F8: ='Copy of INCEXC A'!D8 -> Kaiser | G8: ='Copy of INCEXC B'!D8 -> Danni | H8: ='Copy of INCEXC A'!E8 -> Exclude | I8: ='Copy of INCEXC B'!E8 -> Exclude | J8: =H8=I8 -> TRUE | K8: =AND(H8="Include",J8) -> FALSE
A9: ='Copy of INCEXC A'!A9 -> https://ieeexplore.ieee.org/stamp/stamp.jsp?arnumber=11449950 | B9: ='Copy of INCEXC B'!A9 -> https://ieeexplore.ieee.org/stamp/stamp.jsp?arnumber=11449950 | C9: =A9=B9 -> TRUE | D9: ='INCEXC A'!B2 -> 10.1007/978-3-642-24322-6_15 | E9: ='Copy of INCEXC A'!C9 -> Too Positive to Be True? Sentiment Analysis of AI-Guided vs. Human-Led Debriefings in Virtual Reality Counseling Training | F9: ='Copy of INCEXC A'!D9 -> Kaiser | G9: ='Copy of INCEXC B'!D9 -> Taylor | H9: ='Copy of INCEXC A'!E9 -> Include | I9: ='Copy of INCEXC B'!E9 -> Include | J9: =H9=I9 -> TRUE | K9: =AND(H9="Include",J9) -> TRUE
A10: ='Copy of INCEXC A'!A10 -> https://ieeexplore.ieee.org/stamp/stamp.jsp?arnumber=11334577 | B10: ='Copy of INCEXC B'!A10 -> https://ieeexplore.ieee.org/stamp/stamp.jsp?arnumber=11334577 | C10: =A10=B10 -> TRUE | E10: ='Copy of INCEXC A'!C10 -> Why AI Agents Still Need You: Findings from Developer-Agent Collaborations in the Wild | F10: ='Copy of INCEXC A'!D10 -> Kaiser | G10: ='Copy of INCEXC B'!D10 -> Taylor | H10: ='Copy of INCEXC A'!E10 -> Exclude | I10: ='Copy of INCEXC B'!E10 -> Include | J10: =H10=I10 -> FALSE | K10: =AND(H10="Include",J10) -> FALSE
A11: ='Copy of INCEXC A'!A11 -> https://ieeexplore.ieee.org/stamp/stamp.jsp?arnumber=9381292 | B11: ='Copy of INCEXC B'!A11 -> https://doi.org/10.1109/ASONAM49781.2020.9381292 | C11: =A11=B11 -> FALSE | E11: ='Copy of INCEXC A'!C11 -> Aspect Based Abusive Sentiment Detection in Nepali Social Media Texts | F11: ='Copy of INCEXC A'!D11 -> Jonathan | G11: ='Copy of INCEXC B'!D11 -> Danni | H11: ='Copy of INCEXC A'!E11 | I11: ='Copy of INCEXC B'!E11 -> Exclude | J11: =H11=I11 -> FALSE | K11: =AND(H11="Include",J11) -> FALSE
A12: ='Copy of INCEXC A'!A12 -> https://doi.org/10.1109/ASONAM49781.2020.9381292 | B12: ='Copy of INCEXC B'!A12 -> https://ieeexplore.ieee.org/stamp/stamp.jsp?arnumber=9381292 | C12: =A12=B12 -> FALSE | E12: ='Copy of INCEXC A'!C12 -> Aspect based abusive sentiment detection in nepali social media texts | F12: ='Copy of INCEXC A'!D12 -> Marilyn | G12: ='Copy of INCEXC B'!D12 -> Taylor | H12: ='Copy of INCEXC A'!E12 -> Exclude | I12: ='Copy of INCEXC B'!E12 -> Exclude | J12: =H12=I12 -> TRUE | K12: =AND(H12="Include",J12) -> FALSE
A13: ='Copy of INCEXC A'!A13 -> https://ieeexplore.ieee.org/stamp/stamp.jsp?arnumber=10825538 | B13: ='Copy of INCEXC B'!A13 -> https://ieeexplore.ieee.org/stamp/stamp.jsp?arnumber=10825538 | C13: =A13=B13 -> TRUE | D13: ='INCEXC A'!B6 -> 10.1109/47.735370 | E13: ='Copy of INCEXC A'!C13 -> Mitigating Sycophancy in Large Language Models via Direct Preference Optimization | F13: ='Copy of INCEXC A'!D13 -> Kaiser | G13: ='Copy of INCEXC B'!D13 -> Taylor | H13: ='Copy of INCEXC A'!E13 -> Include | I13: ='Copy of INCEXC B'!E13 -> Include | J13: =H13=I13 -> TRUE | K13: =AND(H13="Include",J13) -> TRUE
A14: ='Copy of INCEXC A'!A14 -> https://ieeexplore.ieee.org/stamp/stamp.jsp?arnumber=11400739 | B14: ='Copy of INCEXC B'!A14 -> https://ieeexplore.ieee.org/stamp/stamp.jsp?arnumber=11400739 | C14: =A14=B14 -> TRUE | E14: ='Copy of INCEXC A'!C14 -> Towards Uncertainty-Aware Low-Bit Quantized LLMs for On-Device Inference | F14: ='Copy of INCEXC A'!D14 -> Kaiser | G14: ='Copy of INCEXC B'!D14 -> Ceren | H14: ='Copy of INCEXC A'!E14 -> Exclude | I14: ='Copy of INCEXC B'!E14 | J14: =H14=I14 -> FALSE | K14: =AND(H14="Include",J14) -> FALSE
A15: ='Copy of INCEXC A'!A15 -> https://doi.org/10.1109/CCGrid.2012.84 | B15: ='Copy of INCEXC B'!A15 -> https://doi.org/10.1109/CCGrid.2012.84 | C15: =A15=B15 -> TRUE | E15: ='Copy of INCEXC A'!C15 -> Energy- and Cost-Efficiency Analysis of ARM-Based Clusters | F15: ='Copy of INCEXC A'!D15 -> Marilyn | G15: ='Copy of INCEXC B'!D15 -> Ceren | H15: ='Copy of INCEXC A'!E15 -> Exclude | I15: ='Copy of INCEXC B'!E15 | J15: =H15=I15 -> FALSE | K15: =AND(H15="Include",J15) -> FALSE
A16: ='Copy of INCEXC A'!A16 -> https://doi.org/10.1109/CCGrid.2015.115 | B16: ='Copy of INCEXC B'!A16 -> https://doi.org/10.1109/CCGrid.2015.115 | C16: =A16=B16 -> TRUE | E16: ='Copy of INCEXC A'!C16 -> Quantitative musings on the feasibility of smartphone clouds | F16: ='Copy of INCEXC A'!D16 -> Jonathan | G16: ='Copy of INCEXC B'!D16 -> Taylor | H16: ='Copy of INCEXC A'!E16 | I16: ='Copy of INCEXC B'!E16 -> Exclude | J16: =H16=I16 -> FALSE | K16: =AND(H16="Include",J16) -> FALSE
A17: ='Copy of INCEXC A'!A17 -> https://doi.org/10.1109/CCGrid.2015.150 | B17: ='Copy of INCEXC B'!A17 -> https://doi.org/10.1109/CCGrid.2015.150 | C17: =A17=B17 -> TRUE | E17: ='Copy of INCEXC A'!C17 -> Deferred lightweight indexing for log-structured key-value stores | F17: ='Copy of INCEXC A'!D17 -> Jonathan | G17: ='Copy of INCEXC B'!D17 -> Danni | H17: ='Copy of INCEXC A'!E17 | I17: ='Copy of INCEXC B'!E17 -> Exclude | J17: =H17=I17 -> FALSE | K17: =AND(H17="Include",J17) -> FALSE
A18: ='Copy of INCEXC A'!A18 -> https://doi.org/10.1109/CCGRID.2017.49 | B18: ='Copy of INCEXC B'!A18 -> https://doi.org/10.1109/CCGRID.2017.49 | C18: =A18=B18 -> TRUE | E18: ='Copy of INCEXC A'!C18 -> High-Performance Key-Value Store On OpenSHMEM | F18: ='Copy of INCEXC A'!D18 -> Kaiser | G18: ='Copy of INCEXC B'!D18 -> Taylor | H18: ='Copy of INCEXC A'!E18 -> Exclude | I18: ='Copy of INCEXC B'!E18 -> Exclude | J18: =H18=I18 -> TRUE | K18: =AND(H18="Include",J18) -> FALSE
A19: ='Copy of INCEXC A'!A19 -> https://ieeexplore.ieee.org/stamp/stamp.jsp?arnumber=1554950 | B19: ='Copy of INCEXC B'!A19 -> https://ieeexplore.ieee.org/stamp/stamp.jsp?arnumber=1554950 | C19: =A19=B19 -> TRUE | E19: ='Copy of INCEXC A'!C19 -> Learning classifier systems for user context learning | F19: ='Copy of INCEXC A'!D19 -> Jonathan | G19: ='Copy of INCEXC B'!D19 -> Taylor | H19: ='Copy of INCEXC A'!E19 | I19: ='Copy of INCEXC B'!E19 -> Exclude | J19: =H19=I19 -> FALSE | K19: =AND(H19="Include",J19) -> FALSE
A20: ='Copy of INCEXC A'!A20 -> https://ieeexplore.ieee.org/stamp/stamp.jsp?arnumber=11519295 | B20: ='Copy of INCEXC B'!A20 -> https://ieeexplore.ieee.org/stamp/stamp.jsp?arnumber=11519295 | C20: =A20=B20 -> TRUE | E20: ='Copy of INCEXC A'!C20 -> PI-Embedding: Scientific Idea Representation Learning via Citation Intent and Paper Provenance | F20: ='Copy of INCEXC A'!D20 -> Jonathan | G20: ='Copy of INCEXC B'!D20 -> Ceren | H20: ='Copy of INCEXC A'!E20 | I20: ='Copy of INCEXC B'!E20 | J20: =H20=I20 -> TRUE | K20: =AND(H20="Include",J20) -> FALSE
A21: ='Copy of INCEXC A'!A21 -> https://ieeexplore.ieee.org/stamp/stamp.jsp?arnumber=10585495 | B21: ='Copy of INCEXC B'!A21 -> https://ieeexplore.ieee.org/stamp/stamp.jsp?arnumber=10585495 | C21: =A21=B21 -> TRUE | E21: ='Copy of INCEXC A'!C21 -> Leveraging Large Language Models for Enhanced VR Development: Insights and Challenges | F21: ='Copy of INCEXC A'!D21 -> Marilyn | G21: ='Copy of INCEXC B'!D21 -> Taylor | H21: ='Copy of INCEXC A'!E21 -> Exclude | I21: ='Copy of INCEXC B'!E21 -> Exclude | J21: =H21=I21 -> TRUE | K21: =AND(H21="Include",J21) -> FALSE
A22: ='Copy of INCEXC A'!A22 -> https://ieeexplore.ieee.org/stamp/stamp.jsp?arnumber=10590666 | B22: ='Copy of INCEXC B'!A22 -> https://ieeexplore.ieee.org/stamp/stamp.jsp?arnumber=10590666 | C22: =A22=B22 -> TRUE | E22: ='Copy of INCEXC A'!C22 -> Studying the Knowledge and Behavior of ChatGPT via Journey to the West | F22: ='Copy of INCEXC A'!D22 -> Marilyn | G22: ='Copy of INCEXC B'!D22 -> Ceren | H22: ='Copy of INCEXC A'!E22 -> Exclude | I22: ='Copy of INCEXC B'!E22 | J22: =H22=I22 -> FALSE | K22: =AND(H22="Include",J22) -> FALSE
A23: ='Copy of INCEXC A'!A23 -> https://ieeexplore.ieee.org/stamp/stamp.jsp?arnumber=11508939 | B23: ='Copy of INCEXC B'!A23 -> https://ieeexplore.ieee.org/stamp/stamp.jsp?arnumber=11508939 | C23: =A23=B23 -> TRUE | E23: ='Copy of INCEXC A'!C23 -> Tiny-Critic RAG: Empowering Agentic Fallback with Parameter-Efficient Small Language Models | F23: ='Copy of INCEXC A'!D23 -> Jonathan | G23: ='Copy of INCEXC B'!D23 -> Taylor | H23: ='Copy of INCEXC A'!E23 | I23: ='Copy of INCEXC B'!E23 -> Exclude | J23: =H23=I23 -> FALSE | K23: =AND(H23="Include",J23) -> FALSE
A24: ='Copy of INCEXC A'!A24 -> https://ieeexplore.ieee.org/stamp/stamp.jsp?arnumber=11460702 | B24: ='Copy of INCEXC B'!A24 -> https://ieeexplore.ieee.org/stamp/stamp.jsp?arnumber=11460702 | C24: =A24=B24 -> TRUE | E24: ='Copy of INCEXC A'!C24 -> Towards Self-Evaluation of Sycophantic Hallucinations in Mathematical Reasoning | F24: ='Copy of INCEXC A'!D24 -> Jonathan | G24: ='Copy of INCEXC B'!D24 -> Danni | H24: ='Copy of INCEXC A'!E24 | I24: ='Copy of INCEXC B'!E24 -> Include | J24: =H24=I24 -> FALSE | K24: =AND(H24="Include",J24) -> FALSE
A25: ='Copy of INCEXC A'!A25 -> https://ieeexplore.ieee.org/stamp/stamp.jsp?arnumber=11462217 | B25: ='Copy of INCEXC B'!A25 -> https://ieeexplore.ieee.org/stamp/stamp.jsp?arnumber=11462217 | C25: =A25=B25 -> TRUE | E25: ='Copy of INCEXC A'!C25 -> FinLumen: A Game-Theoretic Multi-Agent Framework for Rational Portfolio Management | F25: ='Copy of INCEXC A'!D25 -> Kaiser | G25: ='Copy of INCEXC B'!D25 -> Ceren | H25: ='Copy of INCEXC A'!E25 -> Exclude | I25: ='Copy of INCEXC B'!E25 | J25: =H25=I25 -> FALSE | K25: =AND(H25="Include",J25) -> FALSE
... A216: ='Copy of INCEXC A'!A216 -> https://doi.org/10.1145/3701188 | B216: ='Copy of INCEXC B'!A216 -> https://doi.org/10.1145/3701188 | C216: =A216=B216 -> TRUE | E216: ='Copy of INCEXC A'!C216 -> Conversate: Supporting Reflective Learning in Interview Practice Through Interactive Simulation and Dialogic Feedback | F216: ='Copy of INCEXC A'!D216 -> Marilyn | G216: ='Copy of INCEXC B'!D216 -> Taylor | H216: ='Copy of INCEXC A'!E216 -> Exclude | I216: ='Copy of INCEXC B'!E216 -> Exclude | J216: =H216=I216 -> TRUE | K216: =AND(H216="Include",J216) -> FALSE
A217: ='Copy of INCEXC A'!A217 -> https://doi.org/10.1145/3703155 | B217: ='Copy of INCEXC B'!A217 -> https://doi.org/10.1145/3703155 | C217: =A217=B217 -> TRUE | D217: ='INCEXC A'!B210 -> 10.1145/3660650.3660656 | E217: ='Copy of INCEXC A'!C217 -> A Survey on Hallucination in Large Language Models: Principles | F217: ='Copy of INCEXC A'!D217 -> Kaiser | G217: ='Copy of INCEXC B'!D217 -> Taylor | H217: ='Copy of INCEXC A'!E217 -> Include | I217: ='Copy of INCEXC B'!E217 -> Include | J217: =H217=I217 -> TRUE | K217: =AND(H217="Include",J217) -> TRUE
A218: ='Copy of INCEXC A'!A218 -> https://doi.org/10.1145/3703454 | B218: ='Copy of INCEXC B'!A218 -> https://doi.org/10.1145/3703454 | C218: =A218=B218 -> TRUE | E218: ='Copy of INCEXC A'!C218 -> Open-Ethical AI: Advancements in Open-Source Human-Centric Neural Language Models | F218: ='Copy of INCEXC A'!D218 -> Jonathan | G218: ='Copy of INCEXC B'!D218 -> Taylor | H218: ='Copy of INCEXC A'!E218 | I218: ='Copy of INCEXC B'!E218 -> Include | J218: =H218=I218 -> FALSE | K218: =AND(H218="Include",J218) -> FALSE
A219: ='Copy of INCEXC A'!A219 -> https://doi.org/10.1145/3705294 | B219: ='Copy of INCEXC B'!A219 -> https://doi.org/10.1145/3705294 | C219: =A219=B219 -> TRUE | E219: ='Copy of INCEXC A'!C219 -> The AI Alignment Paradox | F219: ='Copy of INCEXC A'!D219 -> Jonathan | G219: ='Copy of INCEXC B'!D219 -> Ceren | H219: ='Copy of INCEXC A'!E219 | I219: ='Copy of INCEXC B'!E219 | J219: =H219=I219 -> TRUE | K219: =AND(H219="Include",J219) -> FALSE
A220: ='Copy of INCEXC A'!A220 -> https://doi.org/10.1145/3706468.3706564 | B220: ='Copy of INCEXC B'!A220 -> https://doi.org/10.1145/3706468.3706564 | C220: =A220=B220 -> TRUE | E220: ='Copy of INCEXC A'!C220 -> When the Prompt becomes the Codebook: Grounded Prompt Engineering (GROPROE) and its application to Belonging Analytics | F220: ='Copy of INCEXC A'!D220 -> Marilyn | G220: ='Copy of INCEXC B'!D220 -> Taylor | H220: ='Copy of INCEXC A'!E220 -> Exclude | I220: ='Copy of INCEXC B'!E220 -> Exclude | J220: =H220=I220 -> TRUE | K220: =AND(H220="Include",J220) -> FALSE
A221: ='Copy of INCEXC A'!A221 -> https://doi.org/10.1145/3706598.3713220 | B221: ='Copy of INCEXC B'!A221 -> https://doi.org/10.1145/3706598.3713220 | C221: =A221=B221 -> TRUE | E221: ='Copy of INCEXC A'!C221 -> Simulacrum of Stories: Examining Large Language Models as Qualitative Research Participants | F221: ='Copy of INCEXC A'!D221 -> Kaiser | G221: ='Copy of INCEXC B'!D221 -> Taylor | H221: ='Copy of INCEXC A'!E221 -> Exclude | I221: ='Copy of INCEXC B'!E221 -> Include | J221: =H221=I221 -> FALSE | K221: =AND(H221="Include",J221) -> FALSE
A222: ='Copy of INCEXC A'!A222 -> https://doi.org/10.1145/3706598.3713406 | B222: ='Copy of INCEXC B'!A222 -> https://doi.org/10.1145/3706598.3713406 | C222: =A222=B222 -> TRUE | E222: ='Copy of INCEXC A'!C222 -> Abstraction Alignment: Comparing Model-Learned and Human-Encoded Conceptual Relationships | F222: ='Copy of INCEXC A'!D222 -> Kaiser | G222: ='Copy of INCEXC B'!D222 -> Taylor | H222: ='Copy of INCEXC A'!E222 -> Include | I222: ='Copy of INCEXC B'!E222 -> Exclude | J222: =H222=I222 -> FALSE | K222: =AND(H222="Include",J222) -> FALSE
A223: ='Copy of INCEXC A'!A223 -> https://doi.org/10.1145/3706598.3713408 | B223: ='Copy of INCEXC B'!A223 -> https://doi.org/10.1145/3706598.3713408 | C223: =A223=B223 -> TRUE | E223: ='Copy of INCEXC A'!C223 -> Deceptive Explanations by Large Language Models Lead People to Change their Beliefs About Misinformation More Often than Honest Explanations | F223: ='Copy of INCEXC A'!D223 -> Marilyn | G223: ='Copy of INCEXC B'!D223 -> Danni | H223: ='Copy of INCEXC A'!E223 -> Exclude | I223: ='Copy of INCEXC B'!E223 -> Exclude | J223: =H223=I223 -> TRUE | K223: =AND(H223="Include",J223) -> FALSE
A224: ='Copy of INCEXC A'!A224 -> https://doi.org/10.1145/3706598.3713675 | B224: ='Copy of INCEXC B'!A224 -> https://doi.org/10.1145/3706598.3713675 | C224: =A224=B224 -> TRUE | E224: ='Copy of INCEXC A'!C224 -> Plurals: A System for Guiding LLMs via Simulated Social Ensembles | F224: ='Copy of INCEXC A'!D224 -> Jonathan | G224: ='Copy of INCEXC B'!D224 -> Taylor | H224: ='Copy of INCEXC A'!E224 | I224: ='Copy of INCEXC B'!E224 -> Exclude | J224: =H224=I224 -> FALSE | K224: =AND(H224="Include",J224) -> FALSE
A225: ='Copy of INCEXC A'!A225 -> https://doi.org/10.1145/3706599.3719976 | B225: ='Copy of INCEXC B'!A225 -> https://doi.org/10.1145/3706599.3719976 | C225: =A225=B225 -> TRUE | E225: ='Copy of INCEXC A'!C225 -> Exploring Older Adults Personality Preferences for LLM-powered Conversational Companions | F225: ='Copy of INCEXC A'!D225 -> Marilyn | G225: ='Copy of INCEXC B'!D225 -> Taylor | H225: ='Copy of INCEXC A'!E225 -> Exclude | I225: ='Copy of INCEXC B'!E225 -> Include | J225: =H225=I225 -> FALSE | K225: =AND(H225="Include",J225) -> FALSE
A226: ='Copy of INCEXC A'!A226 -> https://doi.org/10.1145/3708359.3712104 | B226: ='Copy of INCEXC B'!A226 -> https://doi.org/10.1145/3708359.3712104 | C226: =A226=B226 -> TRUE | E226: ='Copy of INCEXC A'!C226 -> Exploring the Design Space of Cognitive Engagement Techniques with AI-Generated Code for Enhanced Learning | F226: ='Copy of INCEXC A'!D226 -> Jonathan | G226: ='Copy of INCEXC B'!D226 -> Ceren | H226: ='Copy of INCEXC A'!E226 | I226: ='Copy of INCEXC B'!E226 | J226: =H226=I226 -> TRUE | K226: =AND(H226="Include",J226) -> FALSE
A227: ='Copy of INCEXC A'!A227 -> https://doi.org/10.1145/3708359.3712145 | B227: ='Copy of INCEXC B'!A227 -> https://doi.org/10.1145/3708359.3712145 | C227: =A227=B227 -> TRUE | E227: ='Copy of INCEXC A'!C227 -> Enhancing Visitor Engagement in Interactive Art Exhibitions with Visual-Enhanced Conversational Agents | F227: ='Copy of INCEXC A'!D227 -> Kaiser | G227: ='Copy of INCEXC B'!D227 -> Taylor | H227: ='Copy of INCEXC A'!E227 -> Exclude | I227: ='Copy of INCEXC B'!E227 -> Exclude | J227: =H227=I227 -> TRUE | K227: =AND(H227="Include",J227) -> FALSE
A228: ='Copy of INCEXC A'!A228 -> https://doi.org/10.1145/3711896.3736563 | B228: ='Copy of INCEXC B'!A228 -> https://doi.org/10.1145/3711896.3736563 | C228: =A228=B228 -> TRUE | E228: ='Copy of INCEXC A'!C228 -> A Survey on Small Language Models in the Era of Large Language Models: Architecture | F228: ='Copy of INCEXC A'!D228 -> Kaiser | G228: ='Copy of INCEXC B'!D228 -> Danni | H228: ='Copy of INCEXC A'!E228 -> Exclude | I228: ='Copy of INCEXC B'!E228 -> Exclude | J228: =H228=I228 -> TRUE | K228: =AND(H228="Include",J228) -> FALSE
A229: ='Copy of INCEXC A'!A229 -> https://doi.org/10.1145/3714394.3756275 | B229: ='Copy of INCEXC B'!A229 -> https://doi.org/10.1145/3714394.3756275 | C229: =A229=B229 -> TRUE | E229: ='Copy of INCEXC A'!C229 -> Evaluating Large Language Models in Traditional Chinese Medicine with Enhanced Misinformation Detection | F229: ='Copy of INCEXC A'!D229 -> Marilyn | G229: ='Copy of INCEXC B'!D229 -> Taylor | H229: ='Copy of INCEXC A'!E229 -> Exclude | I229: ='Copy of INCEXC B'!E229 -> Exclude | J229: =H229=I229 -> TRUE | K229: =AND(H229="Include",J229) -> FALSE
... A240: ='Copy of INCEXC A'!A240 -> https://doi.org/10.1145/3719160.3736611 | B240: ='Copy of INCEXC B'!A240 -> https://doi.org/10.1145/3719160.3736611 | C240: =A240=B240 -> TRUE | E240: ='Copy of INCEXC A'!C240 -> Learn | F240: ='Copy of INCEXC A'!D240 -> Marilyn | G240: ='Copy of INCEXC B'!D240 -> Danni | H240: ='Copy of INCEXC A'!E240 -> Exclude | I240: ='Copy of INCEXC B'!E240 -> Exclude | J240: =H240=I240 -> TRUE | K240: =AND(H240="Include",J240) -> FALSE
A241: ='Copy of INCEXC A'!A241 -> https://doi.org/10.1145/3719160.3736618 | B241: ='Copy of INCEXC B'!A241 -> https://doi.org/10.1145/3719160.3736618 | C241: =A241=B241 -> TRUE | D241: ='INCEXC A'!B234 -> 10.1145/3715275.3732063 | E241: ='Copy of INCEXC A'!C241 -> Navigating the Fog: How University Students Recalibrate Sensemaking Practices to Address Plausible Falsehoods in LLM Outputs | F241: ='Copy of INCEXC A'!D241 -> Kaiser | G241: ='Copy of INCEXC B'!D241 -> Danni | H241: ='Copy of INCEXC A'!E241 -> Include | I241: ='Copy of INCEXC B'!E241 -> Include | J241: =H241=I241 -> TRUE | K241: =AND(H241="Include",J241) -> TRUE
A242: ='Copy of INCEXC A'!A242 -> https://doi.org/10.1145/3720554.3735862 | B242: ='Copy of INCEXC B'!A242 -> https://doi.org/10.1145/3720554.3735862 | C242: =A242=B242 -> TRUE | E242: ='Copy of INCEXC A'!C242 -> GenAI &amp; The Dual-Deception Process in Web Science | F242: ='Copy of INCEXC A'!D242 -> Marilyn | G242: ='Copy of INCEXC B'!D242 -> Taylor | H242: ='Copy of INCEXC A'!E242 -> Exclude | I242: ='Copy of INCEXC B'!E242 -> Exclude | J242: =H242=I242 -> TRUE | K242: =AND(H242="Include",J242) -> FALSE
A243: ='Copy of INCEXC A'!A243 -> https://doi.org/10.1145/3721201.3721385 | B243: ='Copy of INCEXC B'!A243 -> https://doi.org/10.1145/3721201.3721385 | C243: =A243=B243 -> TRUE | E243: ='Copy of INCEXC A'!C243 -> HALO: Hallucination Analysis and Learning Optimization to Empower LLMs with Retrieval-Augmented Context for Guided Clinical Decision Making | F243: ='Copy of INCEXC A'!D243 -> Marilyn | G243: ='Copy of INCEXC B'!D243 -> Danni | H243: ='Copy of INCEXC A'!E243 -> Exclude | I243: ='Copy of INCEXC B'!E243 -> Exclude | J243: =H243=I243 -> TRUE | K243: =AND(H243="Include",J243) -> FALSE
A244: ='Copy of INCEXC A'!A244 -> https://doi.org/10.1145/3727200.3727226 | B244: ='Copy of INCEXC B'!A244 -> https://doi.org/10.1145/3727200.3727226 | C244: =A244=B244 -> TRUE | E244: ='Copy of INCEXC A'!C244 -> Lovelock: Towards Smart NIC-Hosted Clusters | F244: ='Copy of INCEXC A'!D244 -> Marilyn | G244: ='Copy of INCEXC B'!D244 -> Taylor | H244: ='Copy of INCEXC A'!E244 -> Exclude | I244: ='Copy of INCEXC B'!E244 -> Exclude | J244: =H244=I244 -> TRUE | K244: =AND(H244="Include",J244) -> FALSE
A245: ='Copy of INCEXC A'!A245 -> https://doi.org/10.1145/3731459.3786222 | B245: ='Copy of INCEXC B'!A245 -> https://doi.org/10.1145/3731459.3786222 | C245: =A245=B245 -> TRUE | E245: ='Copy of INCEXC A'!C245 -> Wish You Were Here: Psychological and Sensory First Aid for Invisible Emergencies in Trauma and Neurodiversity | F245: ='Copy of INCEXC A'!D245 -> Jonathan | G245: ='Copy of INCEXC B'!D245 -> Taylor | H245: ='Copy of INCEXC A'!E245 | I245: ='Copy of INCEXC B'!E245 -> Exclude | J245: =H245=I245 -> FALSE | K245: =AND(H245="Include",J245) -> FALSE
A246: ='Copy of INCEXC A'!A246 -> https://doi.org/10.1145/3735402 | B246: ='Copy of INCEXC B'!A246 -> https://doi.org/10.1145/3735402 | C246: =A246=B246 -> TRUE | E246: ='Copy of INCEXC A'!C246 -> Culture | F246: ='Copy of INCEXC A'!D246 -> Marilyn | G246: ='Copy of INCEXC B'!D246 -> Taylor | H246: ='Copy of INCEXC A'!E246 -> Exclude | I246: ='Copy of INCEXC B'!E246 -> Exclude | J246: =H246=I246 -> TRUE | K246: =AND(H246="Include",J246) -> FALSE
A247: ='Copy of INCEXC A'!A247 -> https://doi.org/10.1145/3736425.3770093 | B247: ='Copy of INCEXC B'!A247 -> https://doi.org/10.1145/3736425.3770093 | C247: =A247=B247 -> TRUE | E247: ='Copy of INCEXC A'!C247 -> An LLM Framework for Inferring Household Energy Consumption Through Behaviour Simulation | F247: ='Copy of INCEXC A'!D247 -> Jonathan | G247: ='Copy of INCEXC B'!D247 -> Taylor | H247: ='Copy of INCEXC A'!E247 | I247: ='Copy of INCEXC B'!E247 -> Exclude | J247: =H247=I247 -> FALSE | K247: =AND(H247="Include",J247) -> FALSE
A248: ='Copy of INCEXC A'!A248 -> https://doi.org/10.1145/3736731.3746137 | B248: ='Copy of INCEXC B'!A248 -> https://doi.org/10.1145/3736731.3746137 | C248: =A248=B248 -> TRUE | E248: ='Copy of INCEXC A'!C248 -> LLMs in Citation Intent Classification: Progress | F248: ='Copy of INCEXC A'!D248 -> Marilyn | G248: ='Copy of INCEXC B'!D248 -> Taylor | H248: ='Copy of INCEXC A'!E248 -> Exclude | I248: ='Copy of INCEXC B'!E248 -> Include | J248: =H248=I248 -> FALSE | K248: =AND(H248="Include",J248) -> FALSE
A249: ='Copy of INCEXC A'!A249 -> https://doi.org/10.1145/3736731.3786118 | B249: ='Copy of INCEXC B'!A249 -> https://doi.org/10.1145/3736731.3786118 | C249: =A249=B249 -> TRUE | E249: ='Copy of INCEXC A'!C249 -> Session Summary Podcast: Session 3: Posters | F249: ='Copy of INCEXC A'!D249 -> Jonathan | G249: ='Copy of INCEXC B'!D249 -> Taylor | H249: ='Copy of INCEXC A'!E249 | I249: ='Copy of INCEXC B'!E249 -> Exclude | J249: =H249=I249 -> FALSE | K249: =AND(H249="Include",J249) -> FALSE
A250: ='Copy of INCEXC A'!A250 -> https://doi.org/10.1145/3742413.3789111 | B250: ='Copy of INCEXC B'!A250 -> https://doi.org/10.1145/3742413.3789111 | C250: =A250=B250 -> TRUE | E250: ='Copy of INCEXC A'!C250 -> SusBench: An Online Benchmark for Evaluating Dark Pattern Susceptibility of Computer-Use Agents | F250: ='Copy of INCEXC A'!D250 -> Kaiser | G250: ='Copy of INCEXC B'!D250 -> Danni | H250: ='Copy of INCEXC A'!E250 -> Include | I250: ='Copy of INCEXC B'!E250 -> Exclude | J250: =H250=I250 -> FALSE | K250: =AND(H250="Include",J250) -> FALSE
A251: ='Copy of INCEXC A'!A251 -> https://doi.org/10.1145/3742413.3789120 | B251: ='Copy of INCEXC B'!A251 -> https://doi.org/10.1145/3742413.3789120 | C251: =A251=B251 -> TRUE | E251: ='Copy of INCEXC A'!C251 -> Neural Transparency: Mechanistic Interpretability Interfaces for Anticipating Model Behaviors for Personalized AI | F251: ='Copy of INCEXC A'!D251 -> Jonathan | G251: ='Copy of INCEXC B'!D251 -> Taylor | H251: ='Copy of INCEXC A'!E251 | I251: ='Copy of INCEXC B'!E251 -> Include | J251: =H251=I251 -> FALSE | K251: =AND(H251="Include",J251) -> FALSE
A252: ='Copy of INCEXC A'!A252 -> https://doi.org/10.1145/3742413.3789123 | B252: ='Copy of INCEXC B'!A252 -> https://doi.org/10.1145/3742413.3789123 | C252: =A252=B252 -> TRUE | E252: ='Copy of INCEXC A'!C252 -> PersonaMail: Learning and Adapting Personal Communication Preferences for Context-Aware Email Writing | F252: ='Copy of INCEXC A'!D252 -> Kaiser | G252: ='Copy of INCEXC B'!D252 -> Ceren | H252: ='Copy of INCEXC A'!E252 -> Exclude | I252: ='Copy of INCEXC B'!E252 | J252: =H252=I252 -> FALSE | K252: =AND(H252="Include",J252) -> FALSE
A253: ='Copy of INCEXC A'!A253 -> https://doi.org/10.1145/3742413.3789136 | B253: ='Copy of INCEXC B'!A253 -> https://doi.org/10.1145/3742413.3789136 | C253: =A253=B253 -> TRUE | E253: ='Copy of INCEXC A'!C253 -> Adjust for Trust: Mitigating Trust-Induced Inappropriate Reliance on AI Assistance | F253: ='Copy of INCEXC A'!D253 -> Marilyn | G253: ='Copy of INCEXC B'!D253 -> Danni | H253: ='Copy of INCEXC A'!E253 -> Exclude | I253: ='Copy of INCEXC B'!E253 -> Exclude | J253: =H253=I253 -> TRUE | K253: =AND(H253="Include",J253) -> FALSE
... A258: ='Copy of INCEXC A'!A258 -> https://doi.org/10.1145/3744169.3744195 | B258: ='Copy of INCEXC B'!A258 -> https://doi.org/10.1145/3744169.3744195 | C258: =A258=B258 -> TRUE | E258: ='Copy of INCEXC A'!C258 -> From Bullshit to Cognition: Computing Within the Epistemic Crisis of Large Language Models in Systematic Literature Review | F258: ='Copy of INCEXC A'!D258 -> Jonathan | G258: ='Copy of INCEXC B'!D258 -> Ceren | H258: ='Copy of INCEXC A'!E258 | I258: ='Copy of INCEXC B'!E258 | J258: =H258=I258 -> TRUE | K258: =AND(H258="Include",J258) -> FALSE
A259: ='Copy of INCEXC A'!A259 -> https://doi.org/10.1145/3746027.3755778 | B259: ='Copy of INCEXC B'!A259 -> https://doi.org/10.1145/3746027.3755778 | C259: =A259=B259 -> TRUE | D259: ='INCEXC A'!B252 -> 10.1145/3742413.3789123 | E259: ='Copy of INCEXC A'!C259 -> Evaluating and Mitigating Sycophancy in Large Vision-Language Models | F259: ='Copy of INCEXC A'!D259 -> Kaiser | G259: ='Copy of INCEXC B'!D259 -> Ceren | H259: ='Copy of INCEXC A'!E259 -> Include | I259: ='Copy of INCEXC B'!E259 -> Include | J259: =H259=I259 -> TRUE | K259: =AND(H259="Include",J259) -> TRUE
A260: ='Copy of INCEXC A'!A260 -> https://doi.org/10.1145/3746058.3758468 | B260: ='Copy of INCEXC B'!A260 -> https://doi.org/10.1145/3746058.3758468 | C260: =A260=B260 -> TRUE | E260: ='Copy of INCEXC A'!C260 -> Enabling Real-World Assistive Agents: From Live Vision to Proactive Context-Aware Information Delivery | F260: ='Copy of INCEXC A'!D260 -> Jonathan | G260: ='Copy of INCEXC B'!D260 -> Ceren | H260: ='Copy of INCEXC A'!E260 | I260: ='Copy of INCEXC B'!E260 -> Exclude | J260: =H260=I260 -> FALSE | K260: =AND(H260="Include",J260) -> FALSE
A261: ='Copy of INCEXC A'!A261 -> https://doi.org/10.1145/3746059.3747680 | B261: ='Copy of INCEXC B'!A261 -> https://doi.org/10.1145/3746059.3747680 | C261: =A261=B261 -> TRUE | E261: ='Copy of INCEXC A'!C261 -> Policy Maps: Tools for Guiding the Unbounded Space of LLM Behaviors | F261: ='Copy of INCEXC A'!D261 -> Kaiser | G261: ='Copy of INCEXC B'!D261 -> Danni | H261: ='Copy of INCEXC A'!E261 -> Exclude | I261: ='Copy of INCEXC B'!E261 -> Exclude | J261: =H261=I261 -> TRUE | K261: =AND(H261="Include",J261) -> FALSE
A262: ='Copy of INCEXC A'!A262 -> https://doi.org/10.1145/3746252.3761151 | B262: ='Copy of INCEXC B'!A262 -> https://doi.org/10.1145/3746252.3761151 | C262: =A262=B262 -> TRUE | E262: ='Copy of INCEXC A'!C262 -> Where Does Legal AI Fail? Evaluating RAG Pipelines | F262: ='Copy of INCEXC A'!D262 -> Marilyn | G262: ='Copy of INCEXC B'!D262 -> Taylor | H262: ='Copy of INCEXC A'!E262 -> Exclude | I262: ='Copy of INCEXC B'!E262 -> Exclude | J262: =H262=I262 -> TRUE | K262: =AND(H262="Include",J262) -> FALSE
A263: ='Copy of INCEXC A'!A263 -> https://doi.org/10.1145/3746252.3761448 | B263: ='Copy of INCEXC B'!A263 -> https://doi.org/10.1145/3746252.3761448 | C263: =A263=B263 -> TRUE | E263: ='Copy of INCEXC A'!C263 -> Socially Responsible and Trustworthy Generative Foundation Models: Principles | F263: ='Copy of INCEXC A'!D263 -> Jonathan | G263: ='Copy of INCEXC B'!D263 -> Ceren | H263: ='Copy of INCEXC A'!E263 | I263: ='Copy of INCEXC B'!E263 | J263: =H263=I263 -> TRUE | K263: =AND(H263="Include",J263) -> FALSE
A264: ='Copy of INCEXC A'!A264 -> https://doi.org/10.1145/3748620 | B264: ='Copy of INCEXC B'!A264 -> https://doi.org/10.1145/3748620 | C264: =A264=B264 -> TRUE | E264: ='Copy of INCEXC A'!C264 -> First Contact with Dark Patterns and Deceptive Designs in Chinese and Japanese Free-to-Play Mobile Games | F264: ='Copy of INCEXC A'!D264 -> Kaiser | G264: ='Copy of INCEXC B'!D264 -> Taylor | H264: ='Copy of INCEXC A'!E264 -> Exclude | I264: ='Copy of INCEXC B'!E264 -> Exclude | J264: =H264=I264 -> TRUE | K264: =AND(H264="Include",J264) -> FALSE
